Workbook

Sheet Anúncios PBB-ABR-26
A1: CONTROLE DE DESEMPENHO DE CRIATIVOS - [PBB-ABR-26] | I1: Facebook Ads | O1: Google Ads
A2: TOTAL | B2: =SUM(B4:B1002) -> 353956.34 | D2: =SUM(D4:D1002) -> 102699 | E2: =IFERROR(B2/D2,"-") -> 3.4465413 | F2: =SUM(F4:F89) -> 385 | G2: =IFERROR(B2/F2,"-") -> 919.36712 | H2: =IFERROR(1574.65*F2/B2,"-") -> 1.7127543 | I2: =SUM(I4:I1002) -> 180450.42 | J2: =SUM(J4:J1002) -> 71456 | K2: =IFERROR(I2/J2,"-") -> 2.5253362 | L2: =SUM(L4:L89) -> 182 | M2: =IFERROR(I2/L2,"-") -> 991.48582 | N2: =IFERROR(1574.65*L2/I2,"-") -> 1.588172 | O2: =SUM(O4:O1002) -> 173505.92 | P2: =SUM(P4:P1002) -> 31243 | Q2: =IFERROR(O2/P2,"-") -> 5.5534334 | R2: =SUM(R4:R89) -> 203 | S2: =IFERROR(O2/R2,"-") -> 854.70897 | T2: =IFERROR(1574.65*R2/O2,"-") -> 1.842323 | V2: TOTAL
A3: Anúncio | B3: Investimento | C3: Miniatura | D3: Leads | E3: CPL | F3: Vendas | G3: Custo / Venda | H3: ROAS | I3: Investimento FB | J3: Leads FB | K3: CPL FB | L3: Vendas FB | M3: Custo / Venda FB | N3: ROAS FB | O3: Investimento YT | P3: Leads YT | Q3: CPL YT | R3: Vendas YT | S3: Custo / Venda YT | T3: ROAS YT
A4: =IFERROR(__xludf.DUMMYFUNCTION("LET( aba_fb, 'Anúncios FB PBB-ABR-26'!A4:F1002, aba_yt, 'Anúncios YT PBB-ABR-26'!A4:F1002, nomes_unicos, UNIQUE({CHOOSECOLS(aba_fb, 1); CHOOSECOLS(aba_yt, 1)}), nomes, FILTER(nomes_unicos, nomes_unicos<>""""), vendas, MAP(nomes, LAMBDA(n, "&" IFERROR(VLOOKUP(n, aba_fb, 6, 0), 0) + IFERROR(VLOOKUP(n, aba_yt, 6, 0), 0) )), ranking, SORT({nomes , vendas}, 2, 0), lista_final, CHOOSECOLS(ranking, 1), MAP(lista_final, LAMBDA(n, LET( fb_link, IFERROR(XLOOKUP(n, 'EXT"&"RACAO-BM'!A:A, 'EXTRACAO-BM'!H:H, """"), """"), yt_id, IFERROR(XLOOKUP(n, 'EXTRACAO-GA'!A:A, 'EXTRACAO-GA'!I:I, """"), """"), yt_link, IF(yt_id<>"""", ""https://www.youtube.com/watch?v="" & yt_id, """"), final_link, IF(fb_link<>"""", fb_"&"link, yt_link), IF(final_link<>"""", HYPERLINK(final_link, n), n) ) )) )"),"AD092 - Dois personagens casa do Thales - PBB-ABR-26") -> AD092 - Dois personagens casa do Thales - PBB-ABR-26 | B4: {=IF(A4:A1002="", "", I4:I1002 + O4:O1002)} -> 26472.84 | C4: {=MAP(A4:A1002, LAMBDA(n, IF(n="", "", IF(IFERROR(SEARCH("AD157", n), 0) > 0, IMAGE("https://scontent.frao5-1.fna.fbcdn.net/v/t45.1600-4/499368121_3450377525094777_6566430056816394720_n.jpg?stp=cp0_dst-jpg_p526x296_q75_spS444_tt6&_nc_cat=102&ccb=1-7&_nc_sid=f0a831&_nc_ohc=O2lTrkomxFkQ7kNvwHncz4G&_nc_oc=AdpKNVnzhKBOTdc9UUtB7oM8dk0o8JKoZWab"&"rkZucuVskaY_ui3mKrSkA9uwRjBWSkc&_nc_zt=1&_nc_ht=scontent.frao5-1.fna&_nc_gid=g7-GLvUaa1O0YSEwuICwfg&_nc_ss=7b2a8&oh=00_Af5PoUdgXxOfXebkPAuO4VyG1qcaasRsMiAmlEqbghhWBQ&oe=6A07B952"), IF(IFERROR(SEARCH("AD213", n), 0) > 0, IMAGE("https://scontent.frao5-1.fna.fbcdn.net/v/t45.1600-4/611676973_3708502889282238_4328212273790943146_n.jpg?stp=dst-jpg_s168x128_tt6&_nc_cat=108&ccb=1-7&_nc_sid=d5bd00&_nc_ohc=mXi2u9t5t5YQ7kNvwFezS1w&_nc_oc=AdrpGCQs1MxAOVQc6eyka9D7ooKfvzUyHzq92P374q9WRouWaJl"&"2o-QEGsTelEamlLw&_nc_zt=1&_nc_ht=scontent.frao5-1.fna&_nc_gid=51VBC5Aku7RbDZfD3swckw&_nc_ss=7b2a8&oh=00_Af6q1hpX492SXVH14YgqPZAsEbKlAJY38RVwGkxe937Cdg&oe=6A02841A"), LET( fb, XLOOKUP(n, 'EXTRACAO-BM'!A:A, 'EXTRACAO-BM'!J:J, ""), yt, XLOOKUP(n, 'EXTRACAO-GA'!A:A, 'EXTRACAO-GA'!H:H, ""), IF(fb<>"", IMAGE(fb), IF(yt<>"", IMAGE("https://img.youtube.com/vi/" & yt & "/hqdefault.jpg"), "" ) ) ) ) ) ) ))} | D4: {=IF(A4:A1002="", "", J4:J1002 + P4:P1002)} -> 6830 | E4: {=IF(B4:B1002="", "", IFERROR(B4:B1002 / D4:D1002, 0))} -> 3.8759649 | F4: {=IF(A4:A1002="", "", L4:L1002 + R4:R1002)} -> 63 | G4: {=IF(B4:B1002="", "", IFERROR(B4:B1002 / F4:F1002, 0))} -> 420.20381 | H4: {=IF(B4:B1002="", "", IFERROR((F4:F1002 * 1574.65) / B4:B1002, 0))} -> 3.7473482 | I4: {=MAP(A4:A1002, LAMBDA(anuncio, IF(anuncio="", "", SUMIFS('EXTRACAO-BM'!C:C, 'EXTRACAO-BM'!A:A, "*" & LEFT(anuncio, 5) & "*"))))} -> 5861.03 | J4: {=MAP(A4:A1002, LAMBDA(anuncio, IF(anuncio="", "", SUMIFS('EXTRACAO-BM'!D:D, 'EXTRACAO-BM'!A:A, "*" & LEFT(anuncio, 5) & "*"))))} -> 2376 | K4: {=IF(A4:A1002="", "", IF(J4:J1002=0, 0, I4:I1002 / J4:J1002))} -> 2.4667635 | L4: {=IF(A4:A1002="", "", IFERROR(VLOOKUP(A4:A1002, 'Anúncios FB PBB-ABR-26'!A:F, 6, 0), 0))} -> 26 | M4: {=IF(I4:I1002="", "", IFERROR(I4:I1002 / L4:L1002, 0))} -> 225.42423 | N4: {=IF(A4:A1002="", "", IFERROR(1574.65 * L4:L1002 / I4:I1002, ""))} -> 6.9852739 | O4: {=MAP(A4:A1002, LAMBDA(anuncio, IF(anuncio="", "", SUMIFS('EXTRACAO-GA'!C:C, 'EXTRACAO-GA'!A:A, "*" & LEFT(anuncio, 5) & "*"))))} -> 20611.81 | P4: {=MAP(A4:A1002, LAMBDA(anuncio, IF(anuncio="", "", SUMIFS('EXTRACAO-GA'!D:D, 'EXTRACAO-GA'!A:A, "*" & LEFT(anuncio, 5) & "*"))))} -> 4454 | Q4: {=IF(A4:A1002="", "", IF(P4:P1002=0, 0, O4:O1002 / P4:P1002))} -> 4.6277077 | R4: {=IF(A4:A1002="", "", IFERROR(VLOOKUP(A4:A1002, 'Anúncios YT PBB-ABR-26'!A:F, 6, 0), 0))} -> 37 | S4: {=IF(O4:O1002="", "", IFERROR(O4:O1002 / R4:R1002, 0))} -> 557.07595 | T4: {=IF(O4:O1002="", "", IFERROR((R4:R1002 * 1574.65) / O4:O1002, 0))} -> 2.8266343 | V4: AD054 - Banco do Brasil + IA - PBB-ABR-26
A5: =IFERROR(__xludf.DUMMYFUNCTION("""COMPUTED_VALUE"""),"AD058 - Casa do Thales - PBB-ABR-26") -> AD058 - Casa do Thales - PBB-ABR-26 | B5: 12930.63 | D5: 2653 | E5: 4.8739653 | F5: 47 | G5: 275.11979 | H5: 5.7235069 | I5: 4893.77 | J5: 1736 | K5: 2.8189919 | L5: 38 | M5: 128.78342 | N5: 12.227117 | O5: 8036.86 | P5: 917 | Q5: 8.7642966 | R5: 9 | S5: 892.98444 | T5: 1.7633566 | V5: AD110 - Banco do Brasil 2 - cx nova - PBB-ABR-26
A6: =IFERROR(__xludf.DUMMYFUNCTION("""COMPUTED_VALUE"""),"AD050 - Banco do Brasil 2 - cx nova - PBB-ABR-26") -> AD050 - Banco do Brasil 2 - cx nova - PBB-ABR-26 | B6: 34024.07 | D6: 10726 | E6: 3.1721117 | F6: 41 | G6: 829.85537 | H6: 1.8974993 | I6: 18922.74 | J6: 8061 | K6: 2.3474432 | L6: 27 | M6: 700.84222 | N6: 2.2467967 | O6: 15101.33 | P6: 2665 | Q6: 5.6665403 | R6: 14 | S6: 1078.6664 | T6: 1.4598118 | V6: AD113 - Dois personagens ape do Felipe - PBB-ABR-26
A7: =IFERROR(__xludf.DUMMYFUNCTION("""COMPUTED_VALUE"""),"AD109 - Fachada Banco do Brasil com cx PBB-ABR-26") -> AD109 - Fachada Banco do Brasil com cx PBB-ABR-26 | B7: 24324.86 | D7: 9084 | E7: 2.6777697 | F7: 39 | G7: 623.71436 | H7: 2.5246332 | I7: 20743.81 | J7: 8335 | K7: 2.4887594 | L7: 39 | M7: 531.89256 | N7: 2.9604663 | O7: 3581.05 | P7: 749 | Q7: 4.7811081 | S7: 0 | T7: 0 | V7: AD050 - Banco do Brasil 2 - cx nova - PBB-ABR-26
A8: =IFERROR(__xludf.DUMMYFUNCTION("""COMPUTED_VALUE"""),"AD097 - Carro + cx - PBB-ABR-26") -> AD097 - Carro + cx - PBB-ABR-26 | B8: 2690.49 | D8: 455 | E8: 5.9131648 | F8: 28 | G8: 96.088929 | H8: 16.387424 | I8: 921.05 | J8: 272 | K8: 3.3862132 | M8: 0 | N8: 0 | O8: 1769.44 | P8: 183 | Q8: 9.669071 | R8: 28 | S8: 63.194286 | T8: 24.917601 | V8: AD109 - Fachada Banco do Brasil com cx PBB-ABR-26
A9: =IFERROR(__xludf.DUMMYFUNCTION("""COMPUTED_VALUE"""),"AD031 - Pergunta e resposta - PBB-ABR-26") -> AD031 - Pergunta e resposta - PBB-ABR-26 | B9: 903.47 | D9: 83 | E9: 10.885181 | F9: 25 | G9: 36.1388 | H9: 43.572282 | I9: 0 | J9: 0 | K9: 0 | L9: 0 | M9: 0 | O9: 903.47 | P9: 83 | Q9: 10.885181 | R9: 25 | S9: 36.1388 | T9: 43.572282 | V9: AD084 - Duas pessoas com caixa - PBB-ABR-26
A10: =IFERROR(__xludf.DUMMYFUNCTION("""COMPUTED_VALUE"""),"AD037 - Banco do Brasil 2 - PBB-ABR-26") -> AD037 - Banco do Brasil 2 - PBB-ABR-26 | B10: 17751.44 | D10: 3425 | E10: 5.1829022 | F10: 23 | G10: 771.80174 | H10: 2.040226 | I10: 0 | J10: 0 | K10: 0 | L10: 0 | M10: 0 | O10: 17751.44 | P10: 3425 | Q10: 5.1829022 | R10: 23 | S10: 771.80174 | T10: 2.040226 | V10: AD092 - Dois personagens casa do Thales - PBB-ABR-26
A11: =IFERROR(__xludf.DUMMYFUNCTION("""COMPUTED_VALUE"""),"AD113 - Dois personagens apê do Felipe - PBB-ABR-26") -> AD113 - Dois personagens apê do Felipe - PBB-ABR-26 | B11: 29684.31 | D11: 11176 | E11: 2.6560764 | F11: 22 | G11: 1349.2868 | H11: 1.1670239 | I11: 24663.34 | J11: 10493 | K11: 2.3504565 | L11: 0 | M11: 0 | N11: 0 | O11: 5020.97 | P11: 683 | Q11: 7.351347 | R11: 22 | S11: 228.22591 | T11: 6.8995234 | V11: AD037 - Banco do Brasil 2 - PBB-ABR-26
A12: =IFERROR(__xludf.DUMMYFUNCTION("""COMPUTED_VALUE"""),"AD084 - Duas pessoas com caixa - PBB-ABR-26") -> AD084 - Duas pessoas com caixa - PBB-ABR-26 | B12: 28696.91 | D12: 7266 | E12: 3.9494784 | F12: 18 | G12: 1594.2728 | H12: 0.98769171 | I12: 0 | J12: 0 | K12: 0 | L12: 0 | M12: 0 | O12: 28696.91 | P12: 7266 | Q12: 3.9494784 | R12: 18 | S12: 1594.2728 | T12: 0.98769171 | V12: AD058 - Casa do Thales - PBB-ABR-26
A13: =IFERROR(__xludf.DUMMYFUNCTION("""COMPUTED_VALUE"""),"AD059 - Fachada Banco do Brasil + cx nova PBB-ABR-26") -> AD059 - Fachada Banco do Brasil + cx nova PBB-ABR-26 | B13: 9539.28 | D13: 2502 | E13: 3.8126619 | F13: 17 | G13: 561.13412 | H13: 2.8061919 | I13: 3517.34 | J13: 1210 | K13: 2.9068926 | L13: 17 | M13: 206.90235 | N13: 7.6105949 | O13: 6021.94 | P13: 1292 | Q13: 4.6609443 | R13: 0 | S13: 0 | T13: 0 | V13: AD059 - Fachada Banco do Brasil + cx nova PBB-ABR-26
A14: =IFERROR(__xludf.DUMMYFUNCTION("""COMPUTED_VALUE"""),"AD111 - Dois personagens - Brabo + legenda - PBB-ABR-26") -> AD111 - Dois personagens - Brabo + legenda - PBB-ABR-26 | B14: 1137.21 | D14: 64 | E14: 17.768906 | F14: 17 | G14: 66.894706 | H14: 23.539232 | I14: 84.19 | J14: 35 | K14: 2.4054286 | L14: 16 | M14: 5.261875 | N14: 299.25644 | O14: 1053.02 | P14: 29 | Q14: 36.311034 | R14: 1 | S14: 1053.02 | T14: 1.4953657 | V14: AD093 - Dois personagens casa do Thales - PBB-ABR-26
A15: =IFERROR(__xludf.DUMMYFUNCTION("""COMPUTED_VALUE"""),"AD071 - Casa do Felipe + cx - PBB-ABR-26") -> AD071 - Casa do Felipe + cx - PBB-ABR-26 | B15: 5360.26 | D15: 1779 | E15: 3.0130748 | F15: 6 | G15: 893.37667 | H15: 1.7625824 | I15: 5360.26 | J15: 1779 | K15: 3.0130748 | L15: 6 | M15: 893.37667 | N15: 1.7625824 | O15: 0 | P15: 0 | Q15: 0 | R15: 0 | S15: 0 | T15: 0 | V15: AD100 - Tudo em 1 minuto + legenda - PBB-ABR-26
A16: =IFERROR(__xludf.DUMMYFUNCTION("""COMPUTED_VALUE"""),"AD112 - Dois personagens - Brabo + legenda - PBB-ABR-26") -> AD112 - Dois personagens - Brabo + legenda - PBB-ABR-26 | B16: 4597.35 | D16: 861 | E16: 5.339547 | F16: 6 | G16: 766.225 | H16: 2.0550752 | I16: 1175.51 | J16: 370 | K16: 3.1770541 | L16: 0 | M16: 0 | N16: 0 | O16: 3421.84 | P16: 491 | Q16: 6.9691242 | R16: 6 | S16: 570.30667 | T16: 2.7610584 | V16: AD071 - Casa do Felipe + cx - PBB-ABR-26
A17: =IFERROR(__xludf.DUMMYFUNCTION("""COMPUTED_VALUE"""),"AD059 - Fachada Banco do Brasil + cx nova - PBB-ABR-26") -> AD059 - Fachada Banco do Brasil + cx nova - PBB-ABR-26 | B17: 9539.28 | D17: 2502 | E17: 3.8126619 | F17: 5 | G17: 1907.856 | H17: 0.82535055 | I17: 3517.34 | J17: 1210 | K17: 2.9068926 | L17: 0 | M17: 0 | N17: 0 | O17: 6021.94 | P17: 1292 | Q17: 4.6609443 | R17: 5 | S17: 1204.388 | T17: 1.3074275 | V17: AD112 - Dois personagens - Brabo+ legenda - PBB-ABR-26
A18: =IFERROR(__xludf.DUMMYFUNCTION("""COMPUTED_VALUE"""),"AD091 - Dois personagens violão - PBB-ABR-26") -> AD091 - Dois personagens violão - PBB-ABR-26 | B18: 1313.07 | D18: 73 | E18: 17.98726 | F18: 4 | G18: 328.2675 | H18: 4.7968501 | I18: 181.28 | J18: 43 | K18: 4.215814 | L18: 2 | M18: 90.64 | N18: 17.372573 | O18: 1131.79 | P18: 30 | Q18: 37.726333 | R18: 2 | S18: 565.895 | T18: 2.7825833 | V18: AD098 - Flip animado - PBB-ABR-26
A19: =IFERROR(__xludf.DUMMYFUNCTION("""COMPUTED_VALUE"""),"AD107 - Imagem apostilas - PBB-ABR-26") -> AD107 - Imagem apostilas - PBB-ABR-26 | B19: 5041.13 | D19: 1865 | E19: 2.7030188 | F19: 4 | G19: 1260.2825 | H19: 1.2494421 | I19: 5041.13 | J19: 1865 | K19: 2.7030188 | L19: 4 | M19: 1260.2825 | N19: 1.2494421 | O19: 0 | P19: 0 | Q19: 0 | R19: 0 | S19: 0 | T19: 0 | V19: AD108 - Imagem apostilas - PBB-ABR-26
A20: =IFERROR(__xludf.DUMMYFUNCTION("""COMPUTED_VALUE"""),"AD098 - Flip animado - PBB-ABR-26") -> AD098 - Flip animado - PBB-ABR-26 | B20: 5808.82 | D20: 828 | E20: 7.0154831 | F20: 4 | G20: 1452.205 | H20: 1.0843166 | I20: 0 | J20: 0 | K20: 0 | L20: 0 | M20: 0 | O20: 5808.82 | P20: 828 | Q20: 7.0154831 | R20: 4 | S20: 1452.205 | T20: 1.0843166 | V20: AD097 - Carro + cx - PBB-ABR-26
A21: =IFERROR(__xludf.DUMMYFUNCTION("""COMPUTED_VALUE"""),"AD093 - Dois personagens casa do Thales - PBB-ABR-26") -> AD093 - Dois personagens casa do Thales - PBB-ABR-26 | B21: 13513.13 | D21: 2475 | E21: 5.4598505 | F21: 3 | G21: 4504.3767 | H21: 0.34958222 | I21: 61.89 | J21: 10 | K21: 6.189 | L21: 3 | M21: 20.63 | N21: 76.328163 | O21: 13451.24 | P21: 2465 | Q21: 5.4568925 | S21: 0 | T21: 0 | V21: AD040 - Tela dividida - PBB-ABR-26
A22: =IFERROR(__xludf.DUMMYFUNCTION("""COMPUTED_VALUE"""),"AD110 - Banco do Brasil 2 - cx nova - PBB-ABR-26") -> AD110 - Banco do Brasil 2 - cx nova - PBB-ABR-26 | B22: 29666.02 | D22: 9782 | E22: 3.0327152 | F22: 3 | G22: 9888.6733 | H22: 0.15923774 | I22: 20401.41 | J22: 8053 | K22: 2.5333925 | M22: 0 | N22: 0 | O22: 9264.61 | P22: 1729 | Q22: 5.3583632 | R22: 3 | S22: 3088.2033 | T22: 0.50989194 | V22: AD115 - Banco do Brasil Reels - PBB-ABR-26
A23: =IFERROR(__xludf.DUMMYFUNCTION("""COMPUTED_VALUE"""),"AD090 - Dois personagens diva - PBB-ABR-26") -> AD090 - Dois personagens diva - PBB-ABR-26 | B23: 3531.86 | D23: 268 | E23: 13.178582 | F23: 3 | G23: 1177.2867 | H23: 1.3375247 | I23: 0 | J23: 0 | K23: 0 | L23: 0 | M23: 0 | O23: 3531.86 | P23: 268 | Q23: 13.178582 | R23: 3 | S23: 1177.2867 | T23: 1.3375247 | V23: AD090 - Dois personagens diva - PBB-ABR-26
A24: =IFERROR(__xludf.DUMMYFUNCTION("""COMPUTED_VALUE"""),"AD054 - Banco do Brasil + IA - PBB-ABR-26") -> AD054 - Banco do Brasil + IA - PBB-ABR-26 | B24: 26299.58 | D24: 11671 | E24: 2.2534127 | F24: 2 | G24: 13149.79 | H24: 0.11974716 | I24: 26299.58 | J24: 11671 | K24: 2.2534127 | L24: 2 | M24: 13149.79 | N24: 0.11974716 | O24: 0 | P24: 0 | Q24: 0 | R24: 0 | S24: 0 | T24: 0 | V24: AD048 - Estúdio Brabo - PBB-ABR-26
A25: =IFERROR(__xludf.DUMMYFUNCTION("""COMPUTED_VALUE"""),"AD099 - Felipe sentado - PBB-ABR-26") -> AD099 - Felipe sentado - PBB-ABR-26 | B25: 645.9 | D25: 71 | E25: 9.0971831 | F25: 2 | G25: 322.95 | H25: 4.8758322 | I25: 0 | J25: 0 | K25: 0 | L25: 0 | M25: 0 | O25: 645.9 | P25: 71 | Q25: 9.0971831 | R25: 2 | S25: 322.95 | T25: 4.8758322 | V25: AD049 - Flip + Canetão PBB-ABR-26
A26: =IFERROR(__xludf.DUMMYFUNCTION("""COMPUTED_VALUE"""),"AD095 - Felipe sentado - PBB-ABR-26") -> AD095 - Felipe sentado - PBB-ABR-26 | B26: 23.33 | D26: 0 | E26: 0 | F26: 1 | G26: 23.33 | H26: 67.494642 | I26: 23.33 | J26: 0 | K26: 0 | L26: 1 | M26: 23.33 | N26: 67.494642 | O26: 0 | P26: 0 | Q26: 0 | R26: 0 | S26: 0 | T26: 0 | V26: AD114 - Flip chart colorido Estúdio - PBB-ABR-26
A27: =IFERROR(__xludf.DUMMYFUNCTION("""COMPUTED_VALUE"""),"AD112 - Dois personagens - Brabo+ legenda - PBB-ABR-26") -> AD112 - Dois personagens - Brabo+ legenda - PBB-ABR-26 | B27: 4597.35 | D27: 861 | E27: 5.339547 | F27: 1 | G27: 4597.35 | H27: 0.34251253 | I27: 1175.51 | J27: 370 | K27: 3.1770541 | L27: 1 | M27: 1175.51 | N27: 1.3395462 | O27: 3421.84 | P27: 491 | Q27: 6.9691242 | R27: 0 | S27: 0 | T27: 0 | V27: AD117 - Em frente ao Banco do Brasil - PBB-ABR-26
A28: =IFERROR(__xludf.DUMMYFUNCTION("""COMPUTED_VALUE"""),"AD102 - Dois personagens - Brabo - PBB-ABR-26") -> AD102 - Dois personagens - Brabo - PBB-ABR-26 | B28: 895.78 | D28: 20 | E28: 44.789 | F28: 1 | G28: 895.78 | H28: 1.7578535 | I28: 0 | J28: 0 | K28: 0 | L28: 0 | M28: 0 | O28: 895.78 | P28: 20 | Q28: 44.789 | R28: 1 | S28: 895.78 | T28: 1.7578535 | V28: AD031 - Pergunta e resposta - PBB-ABR-26
A29: =IFERROR(__xludf.DUMMYFUNCTION("""COMPUTED_VALUE"""),"AD113 - Dois personagens ape do Felipe - PBB-ABR-26") -> AD113 - Dois personagens ape do Felipe - PBB-ABR-26 | B29: 29684.31 | D29: 11176 | E29: 2.6560764 | F29: 0 | G29: 0 | H29: 0 | I29: 24663.34 | J29: 10493 | K29: 2.3504565 | M29: 0 | N29: 0 | O29: 5020.97 | P29: 683 | Q29: 7.351347 | R29: 0 | S29: 0 | T29: 0 | V29: AD091 - Dois personagens violão - PBB-ABR-26
A30: =IFERROR(__xludf.DUMMYFUNCTION("""COMPUTED_VALUE"""),"AD049 - Flip + Canetão PBB-ABR-26") -> AD049 - Flip + Canetão PBB-ABR-26 | B30: 653.61 | D30: 203 | E30: 3.2197537 | F30: 0 | G30: 0 | H30: 0 | I30: 653.61 | J30: 203 | K30: 3.2197537 | L30: 0 | M30: 0 | N30: 0 | O30: 0 | P30: 0 | Q30: 0 | R30: 0 | S30: 0 | T30: 0 | V30: AD099 - Felipe sentado - PBB-ABR-26
A31: =IFERROR(__xludf.DUMMYFUNCTION("""COMPUTED_VALUE"""),"AD108 - Imagem apostilas - PBB-ABR-26") -> AD108 - Imagem apostilas - PBB-ABR-26 | B31: 1542.68 | D31: 651 | E31: 2.3697081 | F31: 0 | G31: 0 | H31: 0 | I31: 1542.68 | J31: 651 | K31: 2.3697081 | M31: 0 | N31: 0 | O31: 0 | P31: 0 | Q31: 0 | R31: 0 | S31: 0 | T31: 0 | V31: AD111 - Dois personagens - Brabo + legenda - PBB-ABR-26
A32: =IFERROR(__xludf.DUMMYFUNCTION("""COMPUTED_VALUE"""),"AD100 - Tudo em 1 minuto + legenda - PBB-ABR-26") -> AD100 - Tudo em 1 minuto + legenda - PBB-ABR-26 | B32: 9686.34 | D32: 1878 | E32: 5.1577955 | F32: 0 | G32: 0 | H32: 0 | I32: 9686.34 | J32: 1878 | K32: 5.1577955 | M32: 0 | N32: 0 | O32: 0 | P32: 0 | Q32: 0 | R32: 0 | S32: 0 | T32: 0 | V32: AD103 - Felipe TV - PBB-ABR-26
A33: =IFERROR(__xludf.DUMMYFUNCTION("""COMPUTED_VALUE"""),"AD114 - Flip chart colorido Estúdio - PBB-ABR-26") -> AD114 - Flip chart colorido Estúdio - PBB-ABR-26 | B33: 701.85 | D33: 111 | E33: 6.322973 | F33: 0 | G33: 0 | H33: 0 | I33: 27.32 | J33: 11 | K33: 2.4836364 | M33: 0 | N33: 0 | O33: 674.53 | P33: 100 | Q33: 6.7453 | R33: 0 | S33: 0 | T33: 0 | V33: AD102 - Dois personagens - Brabo - PBB-ABR-26
A34: =IFERROR(__xludf.DUMMYFUNCTION("""COMPUTED_VALUE"""),"AD115 - Banco do Brasil Reels - PBB-ABR-26") -> AD115 - Banco do Brasil Reels - PBB-ABR-26 | B34: 971.36 | D34: 309 | E34: 3.1435599 | F34: 0 | G34: 0 | H34: 0 | I34: 971.36 | J34: 309 | K34: 3.1435599 | M34: 0 | N34: 0 | O34: 0 | P34: 0 | Q34: 0 | R34: 0 | S34: 0 | T34: 0 | V34: AD116 - Banco do Brasil Reels - PBB-ABR-26
A35: =IFERROR(__xludf.DUMMYFUNCTION("""COMPUTED_VALUE"""),"AD116 - Banco do Brasil Reels - PBB-ABR-26") -> AD116 - Banco do Brasil Reels - PBB-ABR-26 | B35: 33.94 | D35: 11 | E35: 3.0854545 | F35: 0 | G35: 0 | H35: 0 | I35: 33.94 | J35: 11 | K35: 3.0854545 | L35: 0 | M35: 0 | N35: 0 | O35: 0 | P35: 0 | Q35: 0 | R35: 0 | S35: 0 | T35: 0 | V35: AD095 - Felipe sentado - PBB-ABR-26
A36: =IFERROR(__xludf.DUMMYFUNCTION("""COMPUTED_VALUE"""),"AD048 - Estúdio Brabo - PBB-ABR-26") -> AD048 - Estúdio Brabo - PBB-ABR-26 | B36: 2083.46 | D36: 206 | E36: 10.113883 | F36: 0 | G36: 0 | H36: 0 | I36: 0 | J36: 0 | K36: 0 | L36: 0 | M36: 0 | O36: 2083.46 | P36: 206 | Q36: 10.113883 | S36: 0 | T36: 0
A37: =IFERROR(__xludf.DUMMYFUNCTION("""COMPUTED_VALUE"""),"AD040 - Tela dividida - PBB-ABR-26") -> AD040 - Tela dividida - PBB-ABR-26 | B37: 3072.66 | D37: 314 | E37: 9.7855414 | F37: 0 | G37: 0 | H37: 0 | I37: 0 | J37: 0 | K37: 0 | L37: 0 | M37: 0 | O37: 3072.66 | P37: 314 | Q37: 9.7855414 | S37: 0 | T37: 0
A38: =IFERROR(__xludf.DUMMYFUNCTION("""COMPUTED_VALUE"""),"AD103 - Felipe TV - PBB-ABR-26") -> AD103 - Felipe TV - PBB-ABR-26 | B38: 1742.41 | D38: 56 | E38: 31.114464 | F38: 0 | G38: 0 | H38: 0 | I38: 0 | J38: 0 | K38: 0 | L38: 0 | M38: 0 | O38: 1742.41 | P38: 56 | Q38: 31.114464 | S38: 0 | T38: 0
A39: =IFERROR(__xludf.DUMMYFUNCTION("""COMPUTED_VALUE"""),"AD090 - Dois personagens no divã - PBB-ABR-26") -> AD090 - Dois personagens no divã - PBB-ABR-26 | B39: 3531.86 | D39: 268 | E39: 13.178582 | F39: 0 | G39: 0 | H39: 0 | I39: 0 | J39: 0 | K39: 0 | L39: 0 | M39: 0 | O39: 3531.86 | P39: 268 | Q39: 13.178582 | S39: 0 | T39: 0
A40: =IFERROR(__xludf.DUMMYFUNCTION("""COMPUTED_VALUE"""),"AD114 - Flip chart colorido Estúdio - PBB-ABR-26") -> AD114 - Flip chart colorido Estúdio - PBB-ABR-26 | B40: 701.85 | D40: 111 | E40: 6.322973 | F40: 0 | G40: 0 | H40: 0 | I40: 27.32 | J40: 11 | K40: 2.4836364 | M40: 0 | N40: 0 | O40: 674.53 | P40: 100 | Q40: 6.7453 | R40: 0 | S40: 0 | T40: 0
A41: =IFERROR(__xludf.DUMMYFUNCTION("""COMPUTED_VALUE"""),"AD117 - Em frente ao Banco do Brasil - PBB-ABR-26") -> AD117 - Em frente ao Banco do Brasil - PBB-ABR-26 | B41: 561.64 | D41: 85 | E41: 6.6075294 | F41: 0 | G41: 0 | H41: 0 | I41: 0 | J41: 0 | K41: 0 | L41: 0 | M41: 0 | O41: 561.64 | P41: 85 | Q41: 6.6075294 | R41: 0 | S41: 0 | T41: 0

Sheet Anúncios FB PBB-ABR-26
A1: Facebook Ads [PBB-ABR-26]
A2: TOTAL | C2: =SUM(C4:C1002) -> 107662.94 | D2: =SUM(D4:D1002) -> 59372 | E2: =IFERROR(C2/D2,"-") -> 1.8133622 | F2: =SUM(F4:F89) -> 182 | G2: =IFERROR(C2/F2,"-") -> 591.55462 | H2: =IFERROR(1574.65*F2/C2,"-") -> 2.6618844
A3: Anúncio | B3: Miniatura | C3: Investimento FB | D3: Leads FB | E3: CPL FB | F3: Vendas FB | G3: Custo / Venda FB | H3: ROAS FB
A4: =IFERROR(__xludf.DUMMYFUNCTION("LET( total_raw, 'EXTRACAO-BM'!A2:A1002, nomes_unicos, UNIQUE(FILTER(total_raw, (total_raw<>"""") * (total_raw<>""Ad Name""))), vendas, MAP(nomes_unicos, LAMBDA(n, IFERROR(SUMIFS('EXTRACAO-BM'!L:L, 'EXTRACAO-BM'!A:A, n, 'EXTRACAO-BM'!B:B, ""*"&"captação*""), 0) )), tabela_ranking, SORT({nomes_unicos , vendas}, 2, 0), CHOOSECOLS(tabela_ranking, 1) )"),"AD058 - Casa do Thales - PBB-ABR-26") -> AD058 - Casa do Thales - PBB-ABR-26 | B4: {=MAP(A4:A1002, LAMBDA(n, IF(n="", "", IF(IFERROR(SEARCH("AD157", n), 0) > 0, IMAGE("https://scontent.frao5-1.fna.fbcdn.net/v/t45.1600-4/499368121_3450377525094777_6566430056816394720_n.jpg?stp=cp0_dst-jpg_p526x296_q75_spS444_tt6&_nc_cat=102&ccb=1-7&_nc_sid=f0a831&_nc_ohc=O2lTrkomxFkQ7kNvwHncz4G&_nc_oc=AdpKNVnzhKBOTdc9UUtB7oM8dk0o8JKoZWab"&"rkZucuVskaY_ui3mKrSkA9uwRjBWSkc&_nc_zt=1&_nc_ht=scontent.frao5-1.fna&_nc_gid=g7-GLvUaa1O0YSEwuICwfg&_nc_ss=7b2a8&oh=00_Af5PoUdgXxOfXebkPAuO4VyG1qcaasRsMiAmlEqbghhWBQ&oe=6A07B952"), IF(IFERROR(SEARCH("AD213", n), 0) > 0, IMAGE("https://scontent.frao5-1.fna.fbcdn.net/v/t45.1600-4/611676973_3708502889282238_4328212273790943146_n.jpg?stp=dst-jpg_s168x128_tt6&_nc_cat=108&ccb=1-7&_nc_sid=d5bd00&_nc_ohc=mXi2u9t5t5YQ7kNvwFezS1w&_nc_oc=AdrpGCQs1MxAOVQc6eyka9D7ooKfvzUyHzq92P374q9WRouWaJl"&"2o-QEGsTelEamlLw&_nc_zt=1&_nc_ht=scontent.frao5-1.fna&_nc_gid=51VBC5Aku7RbDZfD3swckw&_nc_ss=7b2a8&oh=00_Af6q1hpX492SXVH14YgqPZAsEbKlAJY38RVwGkxe937Cdg&oe=6A02841A"), LET( fb, XLOOKUP(n, 'EXTRACAO-BM'!A:A, 'EXTRACAO-BM'!J:J, ""), yt, XLOOKUP(n, 'EXTRACAO-GA'!A:A, 'EXTRACAO-GA'!H:H, ""), IF(fb<>"", IMAGE(fb), IF(yt<>"", IMAGE("https://img.youtube.com/vi/" & yt & "/hqdefault.jpg"), "" ) ) ) ) ) ) ))} | C4: {=IF(A4:A1002="", "", IFERROR(SUMIFS('EXTRACAO-BM'!C:C, 'EXTRACAO-BM'!A:A, A4:A1002, 'EXTRACAO-BM'!B:B, "*captação*"), 0))} -> 4893.77 | D4: {=MAP(A4:A1002, LAMBDA(anuncio, IF(anuncio="", "", SUMIFS('EXTRACAO-BM'!D:D, 'EXTRACAO-BM'!A:A, "*" & LEFT(anuncio, 5) & "*"))))} -> 1736 | E4: {=IF(A4:A1002="", "", IF(D4:D1002=0, 0, C4:C1002 / D4:D1002))} -> 2.8189919 | F4: 38 | G4: {=IF(C4:C1002="", "", IFERROR(C4:C1002 / F4:F1002, 0))} -> 128.78342 | H4: {=IF(A4:A1002="", "", IFERROR(1574.65 * F4:F1002 / C4:C1002, ""))} -> 12.227117
A5: =IFERROR(__xludf.DUMMYFUNCTION("""COMPUTED_VALUE"""),"AD092 - Dois personagens casa do Thales - PBB-ABR-26") -> AD092 - Dois personagens casa do Thales - PBB-ABR-26 | C5: 4893.77 | D5: 2376 | E5: 2.0596675 | F5: 26 | G5: 188.22192 | H5: 8.3659224
A6: =IFERROR(__xludf.DUMMYFUNCTION("""COMPUTED_VALUE"""),"AD109 - Fachada Banco do Brasil com cx PBB-ABR-26") -> AD109 - Fachada Banco do Brasil com cx PBB-ABR-26 | C6: 4893.77 | D6: 8335 | E6: 0.58713497 | F6: 39 | G6: 125.48128 | H6: 12.548884
A7: =IFERROR(__xludf.DUMMYFUNCTION("""COMPUTED_VALUE"""),"AD050 - Banco do Brasil 2 - cx nova - PBB-ABR-26") -> AD050 - Banco do Brasil 2 - cx nova - PBB-ABR-26 | C7: 4893.77 | D7: 8061 | E7: 0.60709217 | F7: 27 | G7: 181.25074 | H7: 8.6876886
A8: =IFERROR(__xludf.DUMMYFUNCTION("""COMPUTED_VALUE"""),"AD059 - Fachada Banco do Brasil + cx nova PBB-ABR-26") -> AD059 - Fachada Banco do Brasil + cx nova PBB-ABR-26 | C8: 4893.77 | D8: 1210 | E8: 4.044438 | F8: 17 | G8: 287.86882 | H8: 5.4700262
A9: =IFERROR(__xludf.DUMMYFUNCTION("""COMPUTED_VALUE"""),"AD113 - Dois personagens ape do Felipe - PBB-ABR-26") -> AD113 - Dois personagens ape do Felipe - PBB-ABR-26 | C9: 4893.77 | D9: 10493 | E9: 0.46638426 | G9: 0 | H9: 0
A10: =IFERROR(__xludf.DUMMYFUNCTION("""COMPUTED_VALUE"""),"AD111 - Dois personagens - Brabo + legenda - PBB-ABR-26") -> AD111 - Dois personagens - Brabo + legenda - PBB-ABR-26 | C10: 4893.77 | D10: 35 | E10: 139.822 | F10: 16 | G10: 305.86062 | H10: 5.1482599
A11: =IFERROR(__xludf.DUMMYFUNCTION("""COMPUTED_VALUE"""),"AD097 - Carro + cx - PBB-ABR-26") -> AD097 - Carro + cx - PBB-ABR-26 | C11: 4893.77 | D11: 272 | E11: 17.991801 | G11: 0 | H11: 0
A12: =IFERROR(__xludf.DUMMYFUNCTION("""COMPUTED_VALUE"""),"AD071 - Casa do Felipe + cx - PBB-ABR-26") -> AD071 - Casa do Felipe + cx - PBB-ABR-26 | C12: 4893.77 | D12: 1779 | E12: 2.7508544 | F12: 6 | G12: 815.62833 | H12: 1.9305975
A13: =IFERROR(__xludf.DUMMYFUNCTION("""COMPUTED_VALUE"""),"AD095 - Felipe sentado - PBB-ABR-26") -> AD095 - Felipe sentado - PBB-ABR-26 | C13: 4893.77 | D13: 0 | E13: 0 | F13: 1 | G13: 4893.77 | H13: 0.32176625
A14: =IFERROR(__xludf.DUMMYFUNCTION("""COMPUTED_VALUE"""),"AD049 - Flip + Canetão PBB-ABR-26") -> AD049 - Flip + Canetão PBB-ABR-26 | C14: 4893.77 | D14: 203 | E14: 24.107241 | F14: 0 | G14: 0 | H14: 0
A15: =IFERROR(__xludf.DUMMYFUNCTION("""COMPUTED_VALUE"""),"AD091 - Dois personagens violão - PBB-ABR-26") -> AD091 - Dois personagens violão - PBB-ABR-26 | C15: 4893.77 | D15: 43 | E15: 113.8086 | F15: 2 | G15: 2446.885 | H15: 0.64353249
A16: =IFERROR(__xludf.DUMMYFUNCTION("""COMPUTED_VALUE"""),"AD093 - Dois personagens casa do Thales - PBB-ABR-26") -> AD093 - Dois personagens casa do Thales - PBB-ABR-26 | C16: 4893.77 | D16: 10 | E16: 489.377 | F16: 3 | G16: 1631.2567 | H16: 0.96529874
A17: =IFERROR(__xludf.DUMMYFUNCTION("""COMPUTED_VALUE"""),"AD112 - Dois personagens - Brabo+ legenda - PBB-ABR-26") -> AD112 - Dois personagens - Brabo+ legenda - PBB-ABR-26 | C17: 4893.77 | D17: 370 | E17: 13.226405 | F17: 1 | G17: 4893.77 | H17: 0.32176625
A18: =IFERROR(__xludf.DUMMYFUNCTION("""COMPUTED_VALUE"""),"AD110 - Banco do Brasil 2 - cx nova - PBB-ABR-26") -> AD110 - Banco do Brasil 2 - cx nova - PBB-ABR-26 | C18: 4893.77 | D18: 8053 | E18: 0.60769527 | G18: 0 | H18: 0
A19: =IFERROR(__xludf.DUMMYFUNCTION("""COMPUTED_VALUE"""),"AD107 - Imagem apostilas - PBB-ABR-26") -> AD107 - Imagem apostilas - PBB-ABR-26 | C19: 4893.77 | D19: 1865 | E19: 2.6240054 | F19: 4 | G19: 1223.4425 | H19: 1.287065
A20: =IFERROR(__xludf.DUMMYFUNCTION("""COMPUTED_VALUE"""),"AD108 - Imagem apostilas - PBB-ABR-26") -> AD108 - Imagem apostilas - PBB-ABR-26 | C20: 4893.77 | D20: 651 | E20: 7.5173118 | G20: 0 | H20: 0
A21: =IFERROR(__xludf.DUMMYFUNCTION("""COMPUTED_VALUE"""),"AD100 - Tudo em 1 minuto + legenda - PBB-ABR-26") -> AD100 - Tudo em 1 minuto + legenda - PBB-ABR-26 | C21: 4893.77 | D21: 1878 | E21: 2.6058413 | G21: 0 | H21: 0
A22: =IFERROR(__xludf.DUMMYFUNCTION("""COMPUTED_VALUE"""),"AD054 - Banco do Brasil + IA - PBB-ABR-26") -> AD054 - Banco do Brasil + IA - PBB-ABR-26 | C22: 4893.77 | D22: 11671 | E22: 0.41931026 | F22: 2 | G22: 2446.885 | H22: 0.64353249
A23: =IFERROR(__xludf.DUMMYFUNCTION("""COMPUTED_VALUE"""),"AD114 - Flip chart colorido Estúdio - PBB-ABR-26") -> AD114 - Flip chart colorido Estúdio - PBB-ABR-26 | C23: 4893.77 | D23: 11 | E23: 444.88818 | G23: 0 | H23: 0
A24: =IFERROR(__xludf.DUMMYFUNCTION("""COMPUTED_VALUE"""),"AD115 - Banco do Brasil Reels - PBB-ABR-26") -> AD115 - Banco do Brasil Reels - PBB-ABR-26 | C24: 4893.77 | D24: 309 | E24: 15.837443 | G24: 0 | H24: 0
A25: =IFERROR(__xludf.DUMMYFUNCTION("""COMPUTED_VALUE"""),"AD116 - Banco do Brasil Reels - PBB-ABR-26") -> AD116 - Banco do Brasil Reels - PBB-ABR-26 | C25: 4893.77 | D25: 11 | E25: 444.88818 | F25: 0 | G25: 0 | H25: 0
F26: 0
F27: 0
F29: 0
F31: 0
F34: 0
F35: 0

Sheet Anúncios YT PBB-ABR-26
A1: Google Ads [PBB-ABR-26]
A2: TOTAL | C2: =SUM(C4:C1002) -> 158366.64 | D2: =SUM(D4:D1002) -> 28677 | E2: =IFERROR(C2/D2,"-") -> 5.522427 | F2: =SUM(F4:F89) -> 203 | G2: =IFERROR(C2/F2,"-") -> 780.13123 | H2: =IFERROR(1574.65*F2/C2,"-") -> 2.0184425
A3: Anúncio | B3: Miniatura | C3: Investimento YT | D3: Leads YT | E3: CPL YT | F3: Vendas YT | G3: Custo / Venda YT | H3: ROAS YT
A4: =IFERROR(__xludf.DUMMYFUNCTION("LET( total_raw, 'EXTRACAO-GA'!A2:A1002, nomes_unicos, UNIQUE(FILTER(total_raw, (total_raw<>"""") * (total_raw<>""Ad Name""))), vendas, MAP(nomes_unicos, LAMBDA(n, IFERROR(SUMIFS('EXTRACAO-GA'!R:R, 'EXTRACAO-GA'!A:A, n, 'EXTRACAO-GA'!B:B, ""*"&"captação*""), 0) )), tabela_ranking, SORT({nomes_unicos , vendas}, 2, 0), CHOOSECOLS(tabela_ranking, 1) )"),"AD093 - Dois personagens casa do Thales - PBB-ABR-26") -> AD093 - Dois personagens casa do Thales - PBB-ABR-26 | B4: {=MAP(A4:A1002, LAMBDA(n, IF(n="", "", IF(IFERROR(SEARCH("AD157", n), 0) > 0, IMAGE("https://scontent.frao5-1.fna.fbcdn.net/v/t45.1600-4/499368121_3450377525094777_6566430056816394720_n.jpg?stp=cp0_dst-jpg_p526x296_q75_spS444_tt6&_nc_cat=102&ccb=1-7&_nc_sid=f0a831&_nc_ohc=O2lTrkomxFkQ7kNvwHncz4G&_nc_oc=AdpKNVnzhKBOTdc9UUtB7oM8dk0o8JKoZWab"&"rkZucuVskaY_ui3mKrSkA9uwRjBWSkc&_nc_zt=1&_nc_ht=scontent.frao5-1.fna&_nc_gid=g7-GLvUaa1O0YSEwuICwfg&_nc_ss=7b2a8&oh=00_Af5PoUdgXxOfXebkPAuO4VyG1qcaasRsMiAmlEqbghhWBQ&oe=6A07B952"), IF(IFERROR(SEARCH("AD213", n), 0) > 0, IMAGE("https://scontent.frao5-1.fna.fbcdn.net/v/t45.1600-4/611676973_3708502889282238_4328212273790943146_n.jpg?stp=dst-jpg_s168x128_tt6&_nc_cat=108&ccb=1-7&_nc_sid=d5bd00&_nc_ohc=mXi2u9t5t5YQ7kNvwFezS1w&_nc_oc=AdrpGCQs1MxAOVQc6eyka9D7ooKfvzUyHzq92P374q9WRouWaJl"&"2o-QEGsTelEamlLw&_nc_zt=1&_nc_ht=scontent.frao5-1.fna&_nc_gid=51VBC5Aku7RbDZfD3swckw&_nc_ss=7b2a8&oh=00_Af6q1hpX492SXVH14YgqPZAsEbKlAJY38RVwGkxe937Cdg&oe=6A02841A"), LET( fb, XLOOKUP(n, 'EXTRACAO-BM'!A:A, 'EXTRACAO-BM'!J:J, ""), yt, XLOOKUP(n, 'EXTRACAO-GA'!A:A, 'EXTRACAO-GA'!H:H, ""), IF(fb<>"", IMAGE(fb), IF(yt<>"", IMAGE("https://img.youtube.com/vi/" & yt & "/hqdefault.jpg"), "" ) ) ) ) ) ) ))} | C4: {=MAP(A4:A1002, LAMBDA(anuncio, IF(anuncio="", "", SUMIFS('EXTRACAO-GA'!C:C, 'EXTRACAO-GA'!A:A, "*" & LEFT(anuncio, 5) & "*"))))} -> 13451.24 | D4: {=MAP(A4:A1002, LAMBDA(anuncio, IF(anuncio="", "", SUMIFS('EXTRACAO-GA'!D:D, 'EXTRACAO-GA'!A:A, "*" & LEFT(anuncio, 5) & "*"))))} -> 2465 | E4: {=IF(A4:A1002="", "", IF(D4:D1002=0, 0, C4:C1002 / D4:D1002))} -> 5.4568925 | G4: {=IF(C4:C1002="", "", IFERROR(C4:C1002 / F4:F1002, 0))} -> 0 | H4: {=IF(C4:C1002="", "", IFERROR((F4:F1002 * 1574.65) / C4:C1002, 0))} -> 0
A5: =IFERROR(__xludf.DUMMYFUNCTION("""COMPUTED_VALUE"""),"AD084 - Duas pessoas com caixa - PBB-ABR-26") -> AD084 - Duas pessoas com caixa - PBB-ABR-26 | C5: 28696.91 | D5: 7266 | E5: 3.9494784 | F5: 18 | G5: 1594.2728 | H5: 0.98769171
A6: =IFERROR(__xludf.DUMMYFUNCTION("""COMPUTED_VALUE"""),"AD050 - Banco do Brasil 2 - cx nova - PBB-ABR-26") -> AD050 - Banco do Brasil 2 - cx nova - PBB-ABR-26 | C6: 15101.33 | D6: 2665 | E6: 5.6665403 | F6: 14 | G6: 1078.6664 | H6: 1.4598118
A7: =IFERROR(__xludf.DUMMYFUNCTION("""COMPUTED_VALUE"""),"AD097 - Carro + cx - PBB-ABR-26") -> AD097 - Carro + cx - PBB-ABR-26 | C7: 1769.44 | D7: 183 | E7: 9.669071 | F7: 28 | G7: 63.194286 | H7: 24.917601
A8: =IFERROR(__xludf.DUMMYFUNCTION("""COMPUTED_VALUE"""),"AD090 - Dois personagens diva - PBB-ABR-26") -> AD090 - Dois personagens diva - PBB-ABR-26 | C8: 3531.86 | D8: 268 | E8: 13.178582 | F8: 3 | G8: 1177.2867 | H8: 1.3375247
A9: =IFERROR(__xludf.DUMMYFUNCTION("""COMPUTED_VALUE"""),"AD031 - Pergunta e resposta - PBB-ABR-26") -> AD031 - Pergunta e resposta - PBB-ABR-26 | C9: 903.47 | D9: 83 | E9: 10.885181 | F9: 25 | G9: 36.1388 | H9: 43.572282
A10: =IFERROR(__xludf.DUMMYFUNCTION("""COMPUTED_VALUE"""),"AD092 - Dois personagens casa do Thales - PBB-ABR-26") -> AD092 - Dois personagens casa do Thales - PBB-ABR-26 | C10: 20611.81 | D10: 4454 | E10: 4.6277077 | F10: 37 | G10: 557.07595 | H10: 2.8266343
A11: =IFERROR(__xludf.DUMMYFUNCTION("""COMPUTED_VALUE"""),"AD113 - Dois personagens apê do Felipe - PBB-ABR-26") -> AD113 - Dois personagens apê do Felipe - PBB-ABR-26 | C11: 5020.97 | D11: 683 | E11: 7.351347 | F11: 22 | G11: 228.22591 | H11: 6.8995234
A12: =IFERROR(__xludf.DUMMYFUNCTION("""COMPUTED_VALUE"""),"AD058 - Casa do Thales - PBB-ABR-26") -> AD058 - Casa do Thales - PBB-ABR-26 | C12: 8036.86 | D12: 917 | E12: 8.7642966 | F12: 9 | G12: 892.98444 | H12: 1.7633566
A13: =IFERROR(__xludf.DUMMYFUNCTION("""COMPUTED_VALUE"""),"AD098 - Flip animado - PBB-ABR-26") -> AD098 - Flip animado - PBB-ABR-26 | C13: 5808.82 | D13: 828 | E13: 7.0154831 | F13: 4 | G13: 1452.205 | H13: 1.0843166
A14: =IFERROR(__xludf.DUMMYFUNCTION("""COMPUTED_VALUE"""),"AD037 - Banco do Brasil 2 - PBB-ABR-26") -> AD037 - Banco do Brasil 2 - PBB-ABR-26 | C14: 17751.44 | D14: 3425 | E14: 5.1829022 | F14: 23 | G14: 771.80174 | H14: 2.040226
A15: =IFERROR(__xludf.DUMMYFUNCTION("""COMPUTED_VALUE"""),"AD048 - Estúdio Brabo - PBB-ABR-26") -> AD048 - Estúdio Brabo - PBB-ABR-26 | C15: 2083.46 | D15: 206 | E15: 10.113883 | G15: 0 | H15: 0
A16: =IFERROR(__xludf.DUMMYFUNCTION("""COMPUTED_VALUE"""),"AD040 - Tela dividida - PBB-ABR-26") -> AD040 - Tela dividida - PBB-ABR-26 | C16: 3072.66 | D16: 314 | E16: 9.7855414 | G16: 0 | H16: 0
A17: =IFERROR(__xludf.DUMMYFUNCTION("""COMPUTED_VALUE"""),"AD112 - Dois personagens - Brabo + legenda - PBB-ABR-26") -> AD112 - Dois personagens - Brabo + legenda - PBB-ABR-26 | C17: 3421.84 | D17: 491 | E17: 6.9691242 | F17: 6 | G17: 570.30667 | H17: 2.7610584
A18: =IFERROR(__xludf.DUMMYFUNCTION("""COMPUTED_VALUE"""),"AD059 - Fachada Banco do Brasil + cx nova - PBB-ABR-26") -> AD059 - Fachada Banco do Brasil + cx nova - PBB-ABR-26 | C18: 6021.94 | D18: 1292 | E18: 4.6609443 | F18: 5 | G18: 1204.388 | H18: 1.3074275
A19: =IFERROR(__xludf.DUMMYFUNCTION("""COMPUTED_VALUE"""),"AD103 - Felipe TV - PBB-ABR-26") -> AD103 - Felipe TV - PBB-ABR-26 | C19: 1742.41 | D19: 56 | E19: 31.114464 | G19: 0 | H19: 0
A20: =IFERROR(__xludf.DUMMYFUNCTION("""COMPUTED_VALUE"""),"AD102 - Dois personagens - Brabo - PBB-ABR-26") -> AD102 - Dois personagens - Brabo - PBB-ABR-26 | C20: 895.78 | D20: 20 | E20: 44.789 | F20: 1 | G20: 895.78 | H20: 1.7578535
A21: =IFERROR(__xludf.DUMMYFUNCTION("""COMPUTED_VALUE"""),"AD111 - Dois personagens - Brabo + legenda - PBB-ABR-26") -> AD111 - Dois personagens - Brabo + legenda - PBB-ABR-26 | C21: 1053.02 | D21: 29 | E21: 36.311034 | F21: 1 | G21: 1053.02 | H21: 1.4953657
A22: =IFERROR(__xludf.DUMMYFUNCTION("""COMPUTED_VALUE"""),"AD090 - Dois personagens no divã - PBB-ABR-26") -> AD090 - Dois personagens no divã - PBB-ABR-26 | C22: 3531.86 | D22: 268 | E22: 13.178582 | G22: 0 | H22: 0
A23: =IFERROR(__xludf.DUMMYFUNCTION("""COMPUTED_VALUE"""),"AD091 - Dois personagens violão - PBB-ABR-26") -> AD091 - Dois personagens violão - PBB-ABR-26 | C23: 1131.79 | D23: 30 | E23: 37.726333 | F23: 2 | G23: 565.895 | H23: 2.7825833
A24: =IFERROR(__xludf.DUMMYFUNCTION("""COMPUTED_VALUE"""),"AD110 - Banco do Brasil 2 - cx nova - PBB-ABR-26") -> AD110 - Banco do Brasil 2 - cx nova - PBB-ABR-26 | C24: 9264.61 | D24: 1729 | E24: 5.3583632 | F24: 3 | G24: 3088.2033 | H24: 0.50989194
A25: =IFERROR(__xludf.DUMMYFUNCTION("""COMPUTED_VALUE"""),"AD109 - Fachada Banco do Brasil com cx PBB-ABR-26") -> AD109 - Fachada Banco do Brasil com cx PBB-ABR-26 | C25: 3581.05 | D25: 749 | E25: 4.7811081 | G25: 0 | H25: 0
A26: =IFERROR(__xludf.DUMMYFUNCTION("""COMPUTED_VALUE"""),"AD114 - Flip chart colorido Estúdio - PBB-ABR-26") -> AD114 - Flip chart colorido Estúdio - PBB-ABR-26 | C26: 674.53 | D26: 100 | E26: 6.7453 | F26: 0 | G26: 0 | H26: 0
A27: =IFERROR(__xludf.DUMMYFUNCTION("""COMPUTED_VALUE"""),"AD099 - Felipe sentado - PBB-ABR-26") -> AD099 - Felipe sentado - PBB-ABR-26 | C27: 645.9 | D27: 71 | E27: 9.0971831 | F27: 2 | G27: 322.95 | H27: 4.8758322
A28: =IFERROR(__xludf.DUMMYFUNCTION("""COMPUTED_VALUE"""),"AD117 - Em frente ao Banco do Brasil - PBB-ABR-26") -> AD117 - Em frente ao Banco do Brasil - PBB-ABR-26 | C28: 561.64 | D28: 85 | E28: 6.6075294 | F28: 0 | G28: 0 | H28: 0
F29: 0
F30: 0
F31: 0
F32: 0
F33: 0

Sheet EXTRACAO-BM
A1: Ad Name | B1: Campaign Name | C1: Amount Spent | D1: Leads | E1: Cost per Lead | F1: Ad Set Name | G1: Ad ID | H1: Creative Post Link | I1: Creative Instagram Permalink | J1: Creative Thumbnail
A2: AD058 - Casa do Thales - PBB-ABR-26 | B2: [MA][cadastro][captação][quente][principal][PBB-ABR-26][30.03.26] | C2: 58.48 | D2: 39 | E2: 1.5 | F2: 00 - Cadastrados Antigos | G2: 120243988211350520 | H2: https://www.facebook.com/418887747980692/posts/122214479714542386 | I2: https://www.instagram.com/p/DWZTEQngNck/ | J2: https://scontent.xx.fbcdn.net/v/t15.5256-10/656850466_36157958293803722_1530186273580255821_n.jpg?_nc_cat=103&ccb=1-7&_nc_ohc=JYPaxhvv7rIQ7kNvwHRUTtz&_nc_oc=Adpxh15DH63wYqune_Ejk8r7whiigcxrC686H31xoY8jibaYtTg9TpRABbGTObPMyoA&_nc_zt=23&_nc_ht=scontent.xx&edm=AAwGEdEEAAAA&_nc_gid=iEndcDk33bF5gt7MdoYrfg&_nc_tpa=Q5bMBQEKP547DATcX1mm6BM8zbResvAQQACGaZeOmu3dtCPaphQOfypGACj7MFzBhhuDAxxn0pAC6Lh0&stp=c0.5000x0.5000f_dst-emg0_p64x64_q75_tt6&ur=b696e2&_nc_sid=58080a&oh=00_Af7GRJBGhZfSYjGSyLIEla2aiK2U_1Wb-1hCfrzD93OpGg&oe=6A073222
A3: AD092 - Dois personagens casa do Thales - PBB-ABR-26 | B3: [MA][cadastro][captação][quente][principal][PBB-ABR-26][30.03.26] | C3: 77.79 | D3: 42 | E3: 1.85 | F3: 00 - Cadastrados Antigos | G3: 120244008325510520 | H3: https://www.facebook.com/418887747980692/posts/122214479702542386 | I3: https://www.instagram.com/p/DWZTEaFADsG/ | J3: https://scontent.xx.fbcdn.net/v/t15.5256-10/660096093_1479960643565032_1947641573874748707_n.jpg?_nc_cat=106&ccb=1-7&_nc_ohc=zLPmXguhBaAQ7kNvwEc4GUe&_nc_oc=AdpIw_n2s5yvv8v2AXk1nUqUr_JySByp8KjnPuoYi_fanlKPQgXJcsr4C9gJ2Fr-OmY&_nc_zt=23&_nc_ht=scontent.xx&edm=AAwGEdEEAAAA&_nc_gid=iEndcDk33bF5gt7MdoYrfg&_nc_tpa=Q5bMBQG50FheyS1gTA2HEgeoqaF2I-_U6u_FBvp0j20PxqUpolAWsjJinWicqoQdLZ0ZmE2O_zxyJ-r6&stp=c0.5000x0.5000f_dst-emg0_p64x64_q75_tt6&ur=b696e2&_nc_sid=58080a&oh=00_Af6GUqM98WXhjbujQDlge1_gIGAjIp2JDWhmgoX_24KVxw&oe=6A072BAC
A4: AD109 - Fachada Banco do Brasil com cx PBB-ABR-26 | B4: [MA][cadastro][captação][quente][principal][PBB-ABR-26][30.03.26] | C4: 100.09 | D4: 35 | E4: 2.86 | F4: 00 - Cadastrados Antigos | G4: 120244008672760520 | H4: https://www.facebook.com/418887747980692/posts/122214479618542386 | I4: https://www.instagram.com/p/DWZTEEkAESA/ | J4: https://scontent.xx.fbcdn.net/v/t15.5256-10/656855442_1594235935028329_1659051163966614332_n.jpg?_nc_cat=104&ccb=1-7&_nc_ohc=xqN22eWerpwQ7kNvwFXVIIy&_nc_oc=AdpKfFNiYT9TkJjp1Xe-RO2MlMHUv8fhB-L5zmp4gbRcQYlgjuKT2aluzY1IxXuyqdo&_nc_zt=23&_nc_ht=scontent.xx&edm=AAwGEdEEAAAA&_nc_gid=iEndcDk33bF5gt7MdoYrfg&_nc_tpa=Q5bMBQF00DNXoRjpNbtJyCgBSSt4vZc2A299b8N012i-QUDZuPnqM91ozCL_a37QTC-EePYsHWBBSjTF&stp=c0.5000x0.5000f_dst-emg0_p64x64_q75_tt6&ur=b696e2&_nc_sid=58080a&oh=00_Af5oMbSR-vgiWFSDPek0H2ygHKZU9PnwS9cR-J1YmiPERQ&oe=6A074314
A5: AD050 - Banco do Brasil 2 - cx nova - PBB-ABR-26 | B5: [MA][cadastro][captação][quente][principal][PBB-ABR-26][30.03.26] | C5: 646.62 | D5: 317 | E5: 2.04 | F5: 00 - Cadastrados Antigos | G5: 120244008702140520 | H5: https://www.facebook.com/418887747980692/posts/122214479732542386 | I5: https://www.instagram.com/p/DWZTEkgAHA2/ | J5: https://scontent.xx.fbcdn.net/v/t15.5256-10/656950733_925953933387415_8803657205054814029_n.jpg?_nc_cat=104&ccb=1-7&_nc_ohc=J_K2Ip3KpmYQ7kNvwFbZHvI&_nc_oc=Adose2P1PbqhQHY4XpfgdR8yYnjUWQuawDYdOdmcmUPQn7VZxTIJFCyDfZpISCe7oa0&_nc_zt=23&_nc_ht=scontent.xx&edm=AAwGEdEEAAAA&_nc_gid=iEndcDk33bF5gt7MdoYrfg&_nc_tpa=Q5bMBQGxuQ8PXmCil8EAT0RfF2O8MeD2uw_Mxp35CbU8bJK1UYpAZ-cu04uhic4e9ygkhSC2bWhcVo9y&stp=c0.5000x0.5000f_dst-emg0_p64x64_q75_tt6&ur=b696e2&_nc_sid=58080a&oh=00_Af6q5h4ZRajxszSctSYWlklyxEPkQ2a5UYLIzIKULEfpkw&oe=6A070D3D
A6: AD059 - Fachada Banco do Brasil + cx nova PBB-ABR-26 | B6: [MA][cadastro][captação][quente][principal][PBB-ABR-26][30.03.26] | C6: 15.7 | F6: 00 - Cadastrados Antigos | G6: 120244008722830520 | H6: https://www.facebook.com/418887747980692/posts/122214479636542386 | I6: https://www.instagram.com/p/DWZTEbXgEMB/ | J6: https://scontent.xx.fbcdn.net/v/t15.5256-10/655230990_2188016461967465_1976998085957988302_n.jpg?_nc_cat=108&ccb=1-7&_nc_ohc=RKZogepcc-cQ7kNvwHnCAqf&_nc_oc=AdpXy-s9kR-jSJxByVuBiEOT9v0JvZAf-cZycxP9Dj6qctXnO6YZYcNhJ4rwocDjo2E&_nc_zt=23&_nc_ht=scontent.xx&edm=AAwGEdEEAAAA&_nc_gid=iEndcDk33bF5gt7MdoYrfg&_nc_tpa=Q5bMBQGWV81HLcG08eSXKOL6gH7ximqIGDrg8bmTW4Rd2c56qTKDvdxpdFOpPADi4DH8uGFMpmEHcerK&stp=c0.5000x0.5000f_dst-emg0_p64x64_q75_tt6&ur=b696e2&_nc_sid=58080a&oh=00_Af6BPwKO6PsfrRNbWR5PDcWJfvpai_6EPVViW6jT2UhMsQ&oe=6A071423
A7: AD113 - Dois personagens ape do Felipe - PBB-ABR-26 | B7: [MA][cadastro][captação][quente][principal][PBB-ABR-26][30.03.26] | C7: 538.27 | D7: 252 | E7: 2.14 | F7: 00 - Cadastrados Antigos | G7: 120244008745810520 | H7: https://www.facebook.com/418887747980692/posts/122214479822542386 | I7: https://www.instagram.com/p/DWZTEq-AMPu/ | J7: https://scontent.xx.fbcdn.net/v/t15.5256-10/656850466_36157958293803722_1530186273580255821_n.jpg?_nc_cat=103&ccb=1-7&_nc_ohc=JYPaxhvv7rIQ7kNvwHRUTtz&_nc_oc=Adpxh15DH63wYqune_Ejk8r7whiigcxrC686H31xoY8jibaYtTg9TpRABbGTObPMyoA&_nc_zt=23&_nc_ht=scontent.xx&edm=AAwGEdEEAAAA&_nc_gid=iEndcDk33bF5gt7MdoYrfg&_nc_tpa=Q5bMBQGfC6uK_vx3QSEl5nacQov5-VUAKN_Rfgpz_WHvsTLnyLDxUCNexMtWci7v6AqQRqYiL9nFUDKW&stp=c0.5000x0.5000f_dst-emg0_p64x64_q75_tt6&ur=b696e2&_nc_sid=58080a&oh=00_Af54XMeMqt72wnKHJE37K1jk-3Zb8WpcTFwnv7qULLi56A&oe=6A073222
A8: AD111 - Dois personagens - Brabo + legenda - PBB-ABR-26 | B8: [MA][cadastro][captação][quente][principal][PBB-ABR-26][30.03.26] | C8: 1.04 | D8: 2 | E8: 0.52 | F8: 00 - Cadastrados Antigos | G8: 120244009119600520 | H8: https://www.facebook.com/418887747980692/posts/122214479648542386 | I8: https://www.instagram.com/p/DWZTEc_ABMS/ | J8: https://scontent.xx.fbcdn.net/v/t15.5256-10/659377503_788056310657693_6745498894763113159_n.jpg?_nc_cat=109&ccb=1-7&_nc_ohc=VJCwaQA0_H0Q7kNvwEbIKi_&_nc_oc=AdoqnwEXofOYXOtDjaqYazSyW-oak98Furv6opQ9dkj9e3quRPOGqVjW8OEdj8LXTnU&_nc_zt=23&_nc_ht=scontent.xx&edm=AAwGEdEEAAAA&_nc_gid=iEndcDk33bF5gt7MdoYrfg&_nc_tpa=Q5bMBQEgq_A_qxK4ku8pWq9dHpCTTinV2cBxjuDjnXz31kjZIW0XTESByp2vrDMcUUxMQUi6dVZj0BZX&stp=c0.5000x0.5000f_dst-emg0_p64x64_q75_tt6&ur=b696e2&_nc_sid=58080a&oh=00_Af717oKbXGdCpyZrEe5kejpEssZXq7-gXCg7iezwT6NYkg&oe=6A07186A
A9: AD097 - Carro + cx - PBB-ABR-26 | B9: [MA][cadastro][captação][quente][potencial][PBB-ABR-26][30.03.26] | C9: 17.7 | D9: 6 | E9: 2.95 | F9: 00 - Cadastrados Antigos | G9: 120244068664000520 | H9: https://www.facebook.com/418887747980692/posts/122214576476542386 | I9: https://www.instagram.com/p/DWZTYL2gFWK/ | J9: https://scontent.xx.fbcdn.net/v/t15.5256-10/659321723_2254137601661098_3915150513522158111_n.jpg?_nc_cat=100&ccb=1-7&_nc_ohc=VDBtqY-s7H0Q7kNvwEEuHpl&_nc_oc=Adp2uDM1qy8yyLJ_op-8Na2qHkq9BqN9Q9teAv248oq4_356dfjrnKKzkn3yAWG1Chg&_nc_zt=23&_nc_ht=scontent.xx&edm=AAwGEdEEAAAA&_nc_gid=iEndcDk33bF5gt7MdoYrfg&_nc_tpa=Q5bMBQE80Wvh6QISuT-KvwJMO8kR3Jdw1esDaejgzHQTNr6cLkxspVYjSQhQDzXHkUvObH65axbOQeUm&stp=c0.5000x0.5000f_dst-emg0_p64x64_q75_tt6&ur=b696e2&_nc_sid=58080a&oh=00_Af7lWVM3zo9LU_shzHmDsl1lhgSXUSFOB8GquYjDbVV1hQ&oe=6A07199E
A10: AD071 - Casa do Felipe + cx - PBB-ABR-26 | B10: [MA][cadastro][captação][quente][potencial][PBB-ABR-26][30.03.26] | C10: 0.33 | F10: 00 - Cadastrados Antigos | G10: 120244069161470520 | H10: https://www.facebook.com/418887747980692/posts/122214577814542386 | I10: https://www.instagram.com/p/DWZTX4LAD2u/ | J10: https://scontent.xx.fbcdn.net/v/t15.5256-10/660365971_975418021505104_4535425168932836668_n.jpg?_nc_cat=109&ccb=1-7&_nc_ohc=hVjAM1sNlSkQ7kNvwEinrqP&_nc_oc=Adp-UGcMbs0xv-7Px4kAfTrBWpat2kiYy9BJWxG_J5XrIsxLI4JZzBDiU9dI-Z8ENEM&_nc_zt=23&_nc_ht=scontent.xx&edm=AAwGEdEEAAAA&_nc_gid=iEndcDk33bF5gt7MdoYrfg&_nc_tpa=Q5bMBQFDvDxjZNi7bJjSXErkGmnotJE97Wg9i1Tr5QBlCWl9NIjI2h5mk_tOidVfwwVaC6CLOePFVmA8&stp=c0.5000x0.5000f_dst-emg0_p64x64_q75_tt6&ur=b696e2&_nc_sid=58080a&oh=00_Af5G_1nSXeOII4gG_PNUID3oqhNwlw0DRct4icecAahXRw&oe=6A070B62
A11: AD095 - Felipe sentado - PBB-ABR-26 | B11: [MA][cadastro][captação][quente][potencial][PBB-ABR-26][30.03.26] | C11: 0.34 | F11: 00 - Cadastrados Antigos | G11: 120244069326730520 | H11: https://www.facebook.com/418887747980692/posts/122214579746542386 | I11: https://www.instagram.com/p/DWZTYbxAFFD/ | J11: https://scontent.xx.fbcdn.net/v/t15.5256-10/659015521_777825872069344_6853330414113120707_n.jpg?_nc_cat=102&ccb=1-7&_nc_ohc=BIvTDzLRsM0Q7kNvwE0L0iS&_nc_oc=Adq1MMqW9lS0rlj5wMYi6BrleQUDxMNpeF0LX67bYqwSRSXB5s5UgCADW5X2lO8j_G0&_nc_zt=23&_nc_ht=scontent.xx&edm=AAwGEdEEAAAA&_nc_gid=iEndcDk33bF5gt7MdoYrfg&_nc_tpa=Q5bMBQFrRYuKa5ebbkQuRuLu-d_GuEFS1IKrMkQB1bXoJ5vjOGsYBmzs4y3IEIgWNoxOyWQ8Esx-6rbS&stp=c0.5000x0.5000f_dst-emg0_p64x64_q75_tt6&ur=b696e2&_nc_sid=58080a&oh=00_Af5pXW1RBeyCBN_UrlSXJAEWbEaOAGxyg0Xv2frp7q9ZcA&oe=6A072CA5
A12: AD049 - Flip + Canetão PBB-ABR-26 | B12: [MA][cadastro][captação][quente][potencial][PBB-ABR-26][30.03.26] | C12: 0.63 | F12: 00 - Cadastrados Antigos | G12: 120244069410560520 | H12: https://www.facebook.com/418887747980692/posts/122214581852542386 | I12: https://www.instagram.com/p/DWZTYXOgBca/ | J12: https://scontent.xx.fbcdn.net/v/t15.5256-10/658912530_964767329323365_336155474875441123_n.jpg?_nc_cat=108&ccb=1-7&_nc_ohc=fe34ezdWe50Q7kNvwHtIJXa&_nc_oc=AdqzYA-tTeB3StQhylV9tV-zSAsXjpiOsLZIux-hMKQWv3Sd2KK1N3ZIvqrMb8sedIY&_nc_zt=23&_nc_ht=scontent.xx&edm=AAwGEdEEAAAA&_nc_gid=iEndcDk33bF5gt7MdoYrfg&_nc_tpa=Q5bMBQHlTPo95TmnTMW8Ud6jDRUBkIKI59EZYIVvq4OhNyyu8Zq1ri3vIqxc2W1bNVbUOP0nj4QtV3ly&stp=c0.5000x0.5000f_dst-emg0_p64x64_q75_tt6&ur=b696e2&_nc_sid=58080a&oh=00_Af5B4e6N6eiNHUv8ma4s-i6ZohVvMg37Euu7Y28NY_Q-4A&oe=6A072D09
A13: AD091 - Dois personagens violão - PBB-ABR-26 | B13: [MA][cadastro][captação][quente][potencial][PBB-ABR-26][30.03.26] | C13: 0.2 | F13: 00 - Cadastrados Antigos | G13: 120244069561480520 | H13: https://www.facebook.com/418887747980692/posts/122214584036542386 | I13: https://www.instagram.com/p/DWZTYaVAMgi/ | J13: https://scontent.xx.fbcdn.net/v/t15.5256-10/659727968_1414282403831192_297067356207755898_n.jpg?_nc_cat=105&ccb=1-7&_nc_ohc=G5hKJk2PLlgQ7kNvwEFg0rM&_nc_oc=AdplhTQH3fp3SNxnByyBbycj1mmfCOodVgUoACuClZcn721lc2kpt7r9POuRM0FssyU&_nc_zt=23&_nc_ht=scontent.xx&edm=AAwGEdEEAAAA&_nc_gid=iEndcDk33bF5gt7MdoYrfg&_nc_tpa=Q5bMBQG-F6wJRXWHPfeEIq_yng5rsMiYuCMErZjxbiCsjDOK6-yNB3lzlvm6Q2IuRSccwtFzERDUNIvu&stp=c0.5000x0.5000f_dst-emg0_p64x64_q75_tt6&ur=b696e2&_nc_sid=58080a&oh=00_Af6kX11xNReTkN9B-R0Jtfy_09QIWgBBSen9gROyDBQETw&oe=6A0729E5
A14: AD093 - Dois personagens casa do Thales - PBB-ABR-26 | B14: [MA][cadastro][captação][quente][potencial][PBB-ABR-26][30.03.26] | C14: 0.58 | F14: 00 - Cadastrados Antigos | G14: 120244069794730520 | H14: https://www.facebook.com/418887747980692/posts/122214586136542386 | I14: https://www.instagram.com/p/DWZTYAJAEIg/ | J14: https://scontent.xx.fbcdn.net/v/t15.5256-10/659258083_3872133279756228_6646461170497367954_n.jpg?_nc_cat=103&ccb=1-7&_nc_ohc=bhRFkE2FzpcQ7kNvwGnxlCf&_nc_oc=AdoNaaJNXmdnykgQVwxZnMQWVeF45gR_IuB650BNQD0HhenZHTVNh99oWmCS3EQbR9A&_nc_zt=23&_nc_ht=scontent.xx&edm=AAwGEdEEAAAA&_nc_gid=iEndcDk33bF5gt7MdoYrfg&_nc_tpa=Q5bMBQHO3XPvH5dB-ThT9wPcUuVkqLwRDdEbp0aYQh5-I9S8cIwKDpyYYoDaGFWvUIsng244cmW_Efv_&stp=c0.5000x0.5000f_dst-emg0_p64x64_q75_tt6&ur=b696e2&_nc_sid=58080a&oh=00_Af4kv2Ooq_c0RDMyploddA99vpmmwMQ45fGOBSbmmAamfw&oe=6A072CB3
A15: AD112 - Dois personagens - Brabo+ legenda - PBB-ABR-26 | B15: [MA][cadastro][captação][quente][potencial][PBB-ABR-26][30.03.26] | C15: 57.1 | D15: 40 | E15: 1.43 | F15: 00 - Cadastrados Antigos | G15: 120244069905680520 | H15: https://www.facebook.com/418887747980692/posts/122214588368542386 | I15: https://www.instagram.com/p/DWZTYH4ANuK/ | J15: https://scontent.xx.fbcdn.net/v/t15.5256-10/656738039_1263737895730885_5448108828000008158_n.jpg?_nc_cat=106&ccb=1-7&_nc_ohc=irq3tXoRXr4Q7kNvwHfhpfX&_nc_oc=AdoYUAyhG0pc1eAEo4rmaCWwg14IzdWsfcGCdxNpVqwo13wS5eO91I4ddCVFKcTQGXw&_nc_zt=23&_nc_ht=scontent.xx&edm=AAwGEdEEAAAA&_nc_gid=iEndcDk33bF5gt7MdoYrfg&_nc_tpa=Q5bMBQGE7sJ-gBNRFrEsOnWmP761fSHpzRrwyvRk6kOtEJn7gFmETqAPY0UL4I6IPySK3Ot7qvrpBmvk&stp=c0.5000x0.5000f_dst-emg0_p64x64_q75_tt6&ur=b696e2&_nc_sid=58080a&oh=00_Af5rlF0ATQJelyqtQI-mzrCXapAWspxfDhPE1k2rQa145A&oe=6A072D6E
A16: AD110 - Banco do Brasil 2 - cx nova - PBB-ABR-26 | B16: [MA][cadastro][captação][quente][potencial][PBB-ABR-26][30.03.26] | C16: 2.97 | D16: 1 | E16: 2.97 | F16: 00 - Cadastrados Antigos | G16: 120244069995020520 | H16: https://www.facebook.com/418887747980692/posts/122214590924542386 | I16: https://www.instagram.com/p/DWZTX58AEgK/ | J16: https://scontent.xx.fbcdn.net/v/t15.5256-10/657320602_952154174159507_7148290027186586603_n.jpg?_nc_cat=102&ccb=1-7&_nc_ohc=2qVV1ntMrJMQ7kNvwFNUoqc&_nc_oc=Adrj0pnnRilH8ZRJilrWiMsiVTDSANVGL94u5nS7E7RrB2qUIG-1e2OBQ7Fp_49LzEw&_nc_zt=23&_nc_ht=scontent.xx&edm=AAwGEdEEAAAA&_nc_gid=iEndcDk33bF5gt7MdoYrfg&_nc_tpa=Q5bMBQE3fX5fV5UVSGcmU8Og0O5Fq1a0gvQQSf4TBUfxHop9UQDBwwPjQYvkoIfpdv-fUHF5FJg9jsC9&stp=c0.5000x0.5000f_dst-emg0_p64x64_q75_tt6&ur=b696e2&_nc_sid=58080a&oh=00_Af4BaeD20zkhfmqkekABBDay2xA4r39uH-jLP65bo6FkUw&oe=6A0712D4
A17: AD107 - Imagem apostilas - PBB-ABR-26 | B17: [MA][cadastro][captação][quente][potencial][PBB-ABR-26][30.03.26] | C17: 44.68 | D17: 31 | E17: 1.44 | F17: 00 - Cadastrados Antigos | G17: 120244070285940520 | H17: https://www.facebook.com/418887747980692/posts/122214595862542386 | I17: https://www.instagram.com/p/DWZTXsPgORt/ | J17: https://scontent.xx.fbcdn.net/v/t45.1600-4/656007801_10241909975789633_3853226454270751295_n.jpg?_nc_cat=108&ccb=1-7&_nc_ohc=kT8nFml0jDMQ7kNvwGA7MPn&_nc_oc=Ado3cT5Cfy_kQvlN6xgA8vHng99VREb0P4JtrfCHfH7j8Z0lxTQIRB4rRjq4NASMPpI&_nc_zt=1&_nc_ht=scontent.xx&edm=AAwGEdEEAAAA&_nc_gid=iEndcDk33bF5gt7MdoYrfg&_nc_tpa=Q5bMBQE3zcWbJJyOjLWMoTpSGlY9S5lJ3U8da1U3SpJhGATbMKn80SUdtI9PqdtdQieyrPTv0dDzGkbt&stp=c0.5000x0.5000f_dst-emg0_p64x64_q75_tt6&ur=52f3c4&_nc_sid=58080a&oh=00_Af4BW_JLxHLDprAP4LfoxtIuJO2knCpCL6wAMRp4yUocbQ&oe=6A07362D
A18: AD108 - Imagem apostilas - PBB-ABR-26 | B18: [MA][cadastro][captação][quente][principal][PBB-ABR-26][30.03.26] | C18: 135.25 | D18: 77 | E18: 1.76 | F18: 00 - Cadastrados Antigos | G18: 120244071707840520 | H18: https://www.facebook.com/418887747980692/posts/122214599870542386 | I18: https://www.instagram.com/p/DWZTD62ADrR/ | J18: https://scontent.xx.fbcdn.net/v/t45.1600-4/657704700_10241910228635954_4215404491985677412_n.jpg?_nc_cat=102&ccb=1-7&_nc_ohc=1yrs_l8o3FYQ7kNvwHLe3fc&_nc_oc=Adoj1E7Pt5d42wlWp85hOgWXwa3avWQNfrmbvCDkh0bVA1rKxG8nZix7Lpln1MosKao&_nc_zt=1&_nc_ht=scontent.xx&edm=AAwGEdEEAAAA&_nc_gid=iEndcDk33bF5gt7MdoYrfg&_nc_tpa=Q5bMBQEZ4QXI9c3lLzHyiOh-K_h9P9oFzeI6MWjUxl2p4BzvLUirYdnvheX_iCjfoULM_m6GXi6xg2jd&stp=c0.5000x0.5000f_dst-emg0_p64x64_q75_tt6&ur=52f3c4&_nc_sid=58080a&oh=00_Af43fggfLIpn2YAXka8oGLxokwUVWoqu_NtqgvZpN5X7dQ&oe=6A073D71
A19: AD109 - Fachada Banco do Brasil com cx PBB-ABR-26 | B19: [MA][cadastro][captação][quente][reels][PBB-ABR-26][30.03.26] | C19: 63.71 | D19: 28 | E19: 2.28 | F19: 00 - Cadastrados Antigos | G19: 120244072425100520 | H19: https://www.facebook.com/418887747980692/posts/122215596530542386 | I19: https://www.instagram.com/p/DWofuilgJuK/ | J19: https://scontent.xx.fbcdn.net/v/t15.5256-10/660117186_3010128652711523_244912281596665918_n.jpg?_nc_cat=104&ccb=1-7&_nc_ohc=JhTbN-h--1kQ7kNvwG6H2W7&_nc_oc=AdpgVAFih9s_VsNQsHaQ9yYBeAGS5dWR_tSG9Gy8-UGvoRjY6x5h0UIWK_tB1ENA2_I&_nc_zt=23&_nc_ht=scontent.xx&edm=AAwGEdEEAAAA&_nc_gid=iEndcDk33bF5gt7MdoYrfg&_nc_tpa=Q5bMBQENYGQTifya7iUPR5TiAFHqutcgx5GcX8hOtJl1YvERXrgcgirogV6-fchGhCTahek98AhVJKmI&stp=c0.5000x0.5000f_dst-emg0_p64x64_q75_tt6&ur=5fad0e&_nc_sid=58080a&oh=00_Af53T-wh2HNsOh5MORF4s-Geb9R6CySxM6tVSrO2mirFHA&oe=6A072B9E
A20: AD097 - Carro + cx - PBB-ABR-26 | B20: [MA][cadastro][captação][quente][reels][PBB-ABR-26][30.03.26] | C20: 2.5 | F20: 00 - Cadastrados Antigos | G20: 120244072853620520 | H20: https://www.facebook.com/418887747980692/posts/122214605852542386 | I20: https://www.instagram.com/p/DWY8z91gDAd/ | J20: https://scontent.xx.fbcdn.net/v/t15.5256-10/659321723_2254137601661098_3915150513522158111_n.jpg?_nc_cat=100&ccb=1-7&_nc_ohc=VDBtqY-s7H0Q7kNvwEEuHpl&_nc_oc=Adp2uDM1qy8yyLJ_op-8Na2qHkq9BqN9Q9teAv248oq4_356dfjrnKKzkn3yAWG1Chg&_nc_zt=23&_nc_ht=scontent.xx&edm=AAwGEdEEAAAA&_nc_gid=iEndcDk33bF5gt7MdoYrfg&_nc_tpa=Q5bMBQGe9iGjTvMVUfyAD0-kdTG9ZJ51Mk9ekAjTikzWnfxiAJPfOxzmJXwzBKLvSJZyS3AgJrv-ddLJ&stp=c0.5000x0.5000f_dst-emg0_p64x64_q75_tt6&ur=5fad0e&_nc_sid=58080a&oh=00_Af7VXVyozR6pPEN57l4Mg0j_cpQhY1yTiu1NXWAnxzszng&oe=6A07199E
A21: AD100 - Tudo em 1 minuto + legenda - PBB-ABR-26 | B21: [MA][cadastro][captação][quente][reels][PBB-ABR-26][30.03.26] | C21: 59.04 | D21: 32 | E21: 1.85 | F21: 00 - Cadastrados Antigos | G21: 120244072934100520 | H21: https://www.facebook.com/418887747980692/posts/122214609122542386 | I21: https://www.instagram.com/p/DWY9T1aAIeM/ | J21: https://scontent.xx.fbcdn.net/v/t15.5256-10/659682602_924106003701176_4683466467973586042_n.jpg?_nc_cat=103&ccb=1-7&_nc_ohc=Q13eDLtD47oQ7kNvwGSlk-c&_nc_oc=AdpwFxFnL2EYRNojSFUxAepq9EdAQ7AXSv5XQOwNZA_MbQptgaJcaGBsIqJ4vcANMEg&_nc_zt=23&_nc_ht=scontent.xx&edm=AAwGEdEEAAAA&_nc_gid=iEndcDk33bF5gt7MdoYrfg&_nc_tpa=Q5bMBQFu9sgyq3bZLw6Rkj0dpvWhXWW71Bw_uU4_5qdr4MYjyn5fYlYGka2y-HAR2d36O54phbauMeBp&stp=c0.5000x0.5000f_dst-emg0_p64x64_q75_tt6&ur=5fad0e&_nc_sid=58080a&oh=00_Af6GCNVNTdVkP6NPRPh0ZAZO5hmYQ-u809-uM811YmtwZw&oe=6A0738D6
A22: AD092 - Dois personagens casa do Thales - PBB-ABR-26 | B22: [MA][cadastro][captação][quente][principal][PBB-ABR-26][30.03.26] | C22: 129.28 | D22: 55 | E22: 2.35 | F22: 04 - Viu 25% da Captação - PBB-ABR-26 | G22: 120244080589020520 | H22: https://www.facebook.com/418887747980692/posts/122214479702542386 | I22: https://www.instagram.com/p/DWmfVsgALR1/ | J22: https://scontent.xx.fbcdn.net/v/t15.5256-10/660096093_1479960643565032_1947641573874748707_n.jpg?_nc_cat=106&ccb=1-7&_nc_ohc=zLPmXguhBaAQ7kNvwEc4GUe&_nc_oc=AdpIw_n2s5yvv8v2AXk1nUqUr_JySByp8KjnPuoYi_fanlKPQgXJcsr4C9gJ2Fr-OmY&_nc_zt=23&_nc_ht=scontent.xx&edm=AAwGEdEEAAAA&_nc_gid=iEndcDk33bF5gt7MdoYrfg&_nc_tpa=Q5bMBQE8_Ea_V-pBCMbjQRfiTUfCXP-DTbbMcBOx6xVUGQ2PYRcRs0yVXIJ9pmjsptVvF3ETqGbKSiVY&stp=c0.5000x0.5000f_dst-emg0_p64x64_q75_tt6&ur=b696e2&_nc_sid=58080a&oh=00_Af7wcEG704TQkTlwID44yIQ5Zry6JmqVCQ4OJMW3hMWuiw&oe=6A072BAC
A23: AD113 - Dois personagens ape do Felipe - PBB-ABR-26 | B23: [MA][cadastro][captação][quente][principal][PBB-ABR-26][30.03.26] | C23: 2599.91 | D23: 1027 | E23: 2.53 | F23: 04 - Viu 25% da Captação - PBB-ABR-26 | G23: 120244080589030520 | H23: https://www.facebook.com/418887747980692/posts/122214479822542386 | I23: https://www.instagram.com/p/DWmfWq9AIB_/ | J23: https://scontent.xx.fbcdn.net/v/t15.5256-10/656850466_36157958293803722_1530186273580255821_n.jpg?_nc_cat=103&ccb=1-7&_nc_ohc=JYPaxhvv7rIQ7kNvwHRUTtz&_nc_oc=Adpxh15DH63wYqune_Ejk8r7whiigcxrC686H31xoY8jibaYtTg9TpRABbGTObPMyoA&_nc_zt=23&_nc_ht=scontent.xx&edm=AAwGEdEEAAAA&_nc_gid=iEndcDk33bF5gt7MdoYrfg&_nc_tpa=Q5bMBQGfC6uK_vx3QSEl5nacQov5-VUAKN_Rfgpz_WHvsTLnyLDxUCNexMtWci7v6AqQRqYiL9nFUDKW&stp=c0.5000x0.5000f_dst-emg0_p64x64_q75_tt6&ur=b696e2&_nc_sid=58080a&oh=00_Af54XMeMqt72wnKHJE37K1jk-3Zb8WpcTFwnv7qULLi56A&oe=6A073222
A24: AD108 - Imagem apostilas - PBB-ABR-26 | B24: [MA][cadastro][captação][quente][principal][PBB-ABR-26][30.03.26] | C24: 368.55 | D24: 133 | E24: 2.77 | F24: 04 - Viu 25% da Captação - PBB-ABR-26 | G24: 120244080589040520 | H24: https://www.facebook.com/418887747980692/posts/122214599870542386 | I24: https://www.instagram.com/p/DWmfVxKgOsh/ | J24: https://scontent.xx.fbcdn.net/v/t45.1600-4/657704700_10241910228635954_4215404491985677412_n.jpg?_nc_cat=102&ccb=1-7&_nc_ohc=1yrs_l8o3FYQ7kNvwHLe3fc&_nc_oc=Adoj1E7Pt5d42wlWp85hOgWXwa3avWQNfrmbvCDkh0bVA1rKxG8nZix7Lpln1MosKao&_nc_zt=1&_nc_ht=scontent.xx&edm=AAwGEdEEAAAA&_nc_gid=iEndcDk33bF5gt7MdoYrfg&_nc_tpa=Q5bMBQEyAPar-zZkdsI3SO9IwoD1LwXhpbhfkSVQsGcj3jzU6hNpuljGmOK42yAPUm_Ua_QseM1fVLah&stp=c0.5000x0.5000f_dst-emg0_p64x64_q75_tt6&ur=52f3c4&_nc_sid=58080a&oh=00_Af7jcyx9J08S2Ej_ZbQHjwYt2yQ9khEknjvdrdCru-A2gw&oe=6A073D71
A25: AD058 - Casa do Thales - PBB-ABR-26 | B25: [MA][cadastro][captação][quente][principal][PBB-ABR-26][30.03.26] | C25: 197.21 | D25: 78 | E25: 2.53 | F25: 04 - Viu 25% da Captação - PBB-ABR-26 | G25: 120244080589050520 | H25: https://www.facebook.com/418887747980692/posts/122214479714542386 | I25: https://www.instagram.com/p/DWmfVAngLG3/ | J25: https://scontent.xx.fbcdn.net/v/t15.5256-10/656850466_36157958293803722_1530186273580255821_n.jpg?_nc_cat=103&ccb=1-7&_nc_ohc=JYPaxhvv7rIQ7kNvwHRUTtz&_nc_oc=Adpxh15DH63wYqune_Ejk8r7whiigcxrC686H31xoY8jibaYtTg9TpRABbGTObPMyoA&_nc_zt=23&_nc_ht=scontent.xx&edm=AAwGEdEEAAAA&_nc_gid=iEndcDk33bF5gt7MdoYrfg&_nc_tpa=Q5bMBQH9k6Qh16ZuLkQG3TsZ1Z88F9zcUXt-jBZBTGoghFsMWHUL8gSySxi7qKLe3vWakL3yG_VLXYZb&stp=c0.5000x0.5000f_dst-emg0_p64x64_q75_tt6&ur=b696e2&_nc_sid=58080a&oh=00_Af5pB8aKWlfSCF2EiLYNIGwX-9bxQqxmHB3BdtyLC2qxwA&oe=6A073222
A26: AD059 - Fachada Banco do Brasil + cx nova PBB-ABR-26 | B26: [MA][cadastro][captação][quente][principal][PBB-ABR-26][30.03.26] | C26: 58.2 | D26: 17 | E26: 3.42 | F26: 04 - Viu 25% da Captação - PBB-ABR-26 | G26: 120244080589060520 | H26: https://www.facebook.com/418887747980692/posts/122214479636542386 | I26: https://www.instagram.com/p/DWmfVVPAHxL/ | J26: https://scontent.xx.fbcdn.net/v/t15.5256-10/655230990_2188016461967465_1976998085957988302_n.jpg?_nc_cat=108&ccb=1-7&_nc_ohc=RKZogepcc-cQ7kNvwHnCAqf&_nc_oc=AdpXy-s9kR-jSJxByVuBiEOT9v0JvZAf-cZycxP9Dj6qctXnO6YZYcNhJ4rwocDjo2E&_nc_zt=23&_nc_ht=scontent.xx&edm=AAwGEdEEAAAA&_nc_gid=iEndcDk33bF5gt7MdoYrfg&_nc_tpa=Q5bMBQH7txmO0nKkMu128d1x_QkSn9l-eQFnDC-WinHZ-6uoPf6MyEdHP3jb7RVfTf4mjZGWUrAIyUtz&stp=c0.5000x0.5000f_dst-emg0_p64x64_q75_tt6&ur=b696e2&_nc_sid=58080a&oh=00_Af5HsbIoLJOM-zRqebavVuae_R95TdZem3JqaydjfUi_SQ&oe=6A071423
A27: AD050 - Banco do Brasil 2 - cx nova - PBB-ABR-26 | B27: [MA][cadastro][captação][quente][principal][PBB-ABR-26][30.03.26] | C27: 3011.97 | D27: 1211 | E27: 2.49 | F27: 04 - Viu 25% da Captação - PBB-ABR-26 | G27: 120244080589070520 | H27: https://www.facebook.com/418887747980692/posts/122214479732542386 | I27: https://www.instagram.com/p/DWmfV26AHCk/ | J27: https://scontent.xx.fbcdn.net/v/t15.5256-10/656950733_925953933387415_8803657205054814029_n.jpg?_nc_cat=104&ccb=1-7&_nc_ohc=J_K2Ip3KpmYQ7kNvwFbZHvI&_nc_oc=Adose2P1PbqhQHY4XpfgdR8yYnjUWQuawDYdOdmcmUPQn7VZxTIJFCyDfZpISCe7oa0&_nc_zt=23&_nc_ht=scontent.xx&edm=AAwGEdEEAAAA&_nc_gid=iEndcDk33bF5gt7MdoYrfg&_nc_tpa=Q5bMBQGG2jDH-HD7mCvbhQhf0HJE0eMXa1fzDpvTLFHbmiJf9nLL_qO1KXyCTS6P2tFVnADhySuVLxtW&stp=c0.5000x0.5000f_dst-emg0_p64x64_q75_tt6&ur=b696e2&_nc_sid=58080a&oh=00_Af512HcfWitX8J_2bnmgNrwAY6mIIMWHypzZVFVkvfyedA&oe=6A070D3D
A28: AD109 - Fachada Banco do Brasil com cx PBB-ABR-26 | B28: [MA][cadastro][captação][quente][principal][PBB-ABR-26][30.03.26] | C28: 1177.56 | D28: 449 | E28: 2.62 | F28: 04 - Viu 25% da Captação - PBB-ABR-26 | G28: 120244080589080520 | H28: https://www.facebook.com/418887747980692/posts/122214479618542386 | I28: https://www.instagram.com/p/DWmfVlEgE0O/ | J28: https://scontent.xx.fbcdn.net/v/t15.5256-10/656855442_1594235935028329_1659051163966614332_n.jpg?_nc_cat=104&ccb=1-7&_nc_ohc=xqN22eWerpwQ7kNvwFXVIIy&_nc_oc=AdpKfFNiYT9TkJjp1Xe-RO2MlMHUv8fhB-L5zmp4gbRcQYlgjuKT2aluzY1IxXuyqdo&_nc_zt=23&_nc_ht=scontent.xx&edm=AAwGEdEEAAAA&_nc_gid=iEndcDk33bF5gt7MdoYrfg&_nc_tpa=Q5bMBQEMzfYUOfsEtVn3OwedlZbrUjeUNtUPLdbCHFWyjMaquA0nheFcOkThyLOQSem7j_kI24Sve4mv&stp=c0.5000x0.5000f_dst-emg0_p64x64_q75_tt6&ur=b696e2&_nc_sid=58080a&oh=00_Af6R6aWO3NIfjb9Q6D8BMfxe5eJCfugfb3X2vBZDkykl1Q&oe=6A074314
A29: AD111 - Dois personagens - Brabo + legenda - PBB-ABR-26 | B29: [MA][cadastro][captação][quente][principal][PBB-ABR-26][30.03.26] | C29: 3.71 | D29: 1 | E29: 3.71 | F29: 04 - Viu 25% da Captação - PBB-ABR-26 | G29: 120244080589090520 | H29: https://www.facebook.com/418887747980692/posts/122214479648542386 | I29: https://www.instagram.com/p/DWmfVbNANjQ/ | J29: https://scontent.xx.fbcdn.net/v/t15.5256-10/659377503_788056310657693_6745498894763113159_n.jpg?_nc_cat=109&ccb=1-7&_nc_ohc=VJCwaQA0_H0Q7kNvwEbIKi_&_nc_oc=AdoqnwEXofOYXOtDjaqYazSyW-oak98Furv6opQ9dkj9e3quRPOGqVjW8OEdj8LXTnU&_nc_zt=23&_nc_ht=scontent.xx&edm=AAwGEdEEAAAA&_nc_gid=iEndcDk33bF5gt7MdoYrfg&_nc_tpa=Q5bMBQH3_gfNknFi5rre_T4XUoZnzfqFTdzMihDGEnAeCOi2Ca-XBalmaBHtLSeeNRDCQ4-dnO-ZTPqL&stp=c0.5000x0.5000f_dst-emg0_p64x64_q75_tt6&ur=b696e2&_nc_sid=58080a&oh=00_Af7SYxd_FTukeYxmRUUj4xoC8g4woebbeHsfC3Gb-1mGLQ&oe=6A07186A
A30: AD113 - Dois personagens ape do Felipe - PBB-ABR-26 | B30: [MA][cadastro][captação][quente][principal][PBB-ABR-26][30.03.26] | C30: 914.27 | D30: 360 | E30: 2.54 | F30: 01 - Caiu na pag. de Captura [PBB-ABR-26] | G30: 120244080589100520 | H30: https://www.facebook.com/418887747980692/posts/122214479822542386 | I30: https://www.instagram.com/p/DWZTTKogAW-/ | J30: https://scontent.xx.fbcdn.net/v/t15.5256-10/656850466_36157958293803722_1530186273580255821_n.jpg?_nc_cat=103&ccb=1-7&_nc_ohc=JYPaxhvv7rIQ7kNvwHRUTtz&_nc_oc=Adpxh15DH63wYqune_Ejk8r7whiigcxrC686H31xoY8jibaYtTg9TpRABbGTObPMyoA&_nc_zt=23&_nc_ht=scontent.xx&edm=AAwGEdEEAAAA&_nc_gid=iEndcDk33bF5gt7MdoYrfg&_nc_tpa=Q5bMBQGfC6uK_vx3QSEl5nacQov5-VUAKN_Rfgpz_WHvsTLnyLDxUCNexMtWci7v6AqQRqYiL9nFUDKW&stp=c0.5000x0.5000f_dst-emg0_p64x64_q75_tt6&ur=b696e2&_nc_sid=58080a&oh=00_Af54XMeMqt72wnKHJE37K1jk-3Zb8WpcTFwnv7qULLi56A&oe=6A073222
A31: AD050 - Banco do Brasil 2 - cx nova - PBB-ABR-26 | B31: [MA][cadastro][captação][quente][principal][PBB-ABR-26][30.03.26] | C31: 1086.68 | D31: 424 | E31: 2.56 | F31: 01 - Caiu na pag. de Captura [PBB-ABR-26] | G31: 120244080589110520 | H31: https://www.facebook.com/418887747980692/posts/122214479732542386 | I31: https://www.instagram.com/p/DWZTSyZgD1l/ | J31: https://scontent.xx.fbcdn.net/v/t15.5256-10/656950733_925953933387415_8803657205054814029_n.jpg?_nc_cat=104&ccb=1-7&_nc_ohc=J_K2Ip3KpmYQ7kNvwFbZHvI&_nc_oc=Adose2P1PbqhQHY4XpfgdR8yYnjUWQuawDYdOdmcmUPQn7VZxTIJFCyDfZpISCe7oa0&_nc_zt=23&_nc_ht=scontent.xx&edm=AAwGEdEEAAAA&_nc_gid=iEndcDk33bF5gt7MdoYrfg&_nc_tpa=Q5bMBQEcRPuNCDLA1a5dOjhZI4UKdPBbKVZKUZyqpSGy9eQnkaXUfXh5N-n3QDQLk_y-fo7F0aHCKw6Z&stp=c0.5000x0.5000f_dst-emg0_p64x64_q75_tt6&ur=b696e2&_nc_sid=58080a&oh=00_Af5WuYVujW7VAUepA7QgHUd4zs2tn4fu5GGhZY6poXFZow&oe=6A070D3D
A32: AD092 - Dois personagens casa do Thales - PBB-ABR-26 | B32: [MA][cadastro][captação][quente][principal][PBB-ABR-26][30.03.26] | C32: 287.39 | D32: 94 | E32: 3.06 | F32: 01 - Caiu na pag. de Captura [PBB-ABR-26] | G32: 120244080589120520 | H32: https://www.facebook.com/418887747980692/posts/122214479702542386 | I32: https://www.instagram.com/p/DWZTS2WANnt/ | J32: https://scontent.xx.fbcdn.net/v/t15.5256-10/660096093_1479960643565032_1947641573874748707_n.jpg?_nc_cat=106&ccb=1-7&_nc_ohc=zLPmXguhBaAQ7kNvwEc4GUe&_nc_oc=AdpIw_n2s5yvv8v2AXk1nUqUr_JySByp8KjnPuoYi_fanlKPQgXJcsr4C9gJ2Fr-OmY&_nc_zt=23&_nc_ht=scontent.xx&edm=AAwGEdEEAAAA&_nc_gid=iEndcDk33bF5gt7MdoYrfg&_nc_tpa=Q5bMBQHglKzz8kyTTpK3ji_eZ6u6IO6TScA-luu8Zi-xSxEuwOvxztmrNMINSHkmWPWC4PakLs7LTcjz&stp=c0.5000x0.5000f_dst-emg0_p64x64_q75_tt6&ur=b696e2&_nc_sid=58080a&oh=00_Af7Wq_oZy5odJ-e8DNjJyKjMTiI-ylKugEhMPnObuFQQTg&oe=6A072BAC
... A44: AD059 - Fachada Banco do Brasil + cx nova PBB-ABR-26 | B44: [MA][cadastro][captação][quente][principal][PBB-ABR-26][30.03.26] | C44: 42.87 | D44: 10 | E44: 4.29 | F44: 05 - [Felipe Graton] Envolvimento 60D | G44: 120244080589240520 | H44: https://www.facebook.com/418887747980692/posts/122214479636542386 | I44: https://www.instagram.com/p/DWZTSkOAMba/ | J44: https://scontent.xx.fbcdn.net/v/t15.5256-10/655230990_2188016461967465_1976998085957988302_n.jpg?_nc_cat=108&ccb=1-7&_nc_ohc=RKZogepcc-cQ7kNvwHnCAqf&_nc_oc=AdpXy-s9kR-jSJxByVuBiEOT9v0JvZAf-cZycxP9Dj6qctXnO6YZYcNhJ4rwocDjo2E&_nc_zt=23&_nc_ht=scontent.xx&edm=AAwGEdEEAAAA&_nc_gid=iEndcDk33bF5gt7MdoYrfg&_nc_tpa=Q5bMBQFSeJCgTJ8wXOWGrg1FXeoFG-tZmTQIMegIUyb9rmNF9tdik6M-aYGOSGEcVBLe8cOPFoZ_BHqG&stp=c0.5000x0.5000f_dst-emg0_p64x64_q75_tt6&ur=b696e2&_nc_sid=58080a&oh=00_Af5OBYJCRp9JRUZG9MkZ0E7XQAQd8x--EWJNmp948ZrpSQ&oe=6A071423
A45: AD111 - Dois personagens - Brabo + legenda - PBB-ABR-26 | B45: [MA][cadastro][captação][quente][principal][PBB-ABR-26][30.03.26] | C45: 2.06 | F45: 05 - [Felipe Graton] Envolvimento 60D | G45: 120244080589250520 | H45: https://www.facebook.com/418887747980692/posts/122214479648542386 | I45: https://www.instagram.com/p/DWZTSsxAIhD/ | J45: https://scontent.xx.fbcdn.net/v/t15.5256-10/659377503_788056310657693_6745498894763113159_n.jpg?_nc_cat=109&ccb=1-7&_nc_ohc=VJCwaQA0_H0Q7kNvwEbIKi_&_nc_oc=AdoqnwEXofOYXOtDjaqYazSyW-oak98Furv6opQ9dkj9e3quRPOGqVjW8OEdj8LXTnU&_nc_zt=23&_nc_ht=scontent.xx&edm=AAwGEdEEAAAA&_nc_gid=iEndcDk33bF5gt7MdoYrfg&_nc_tpa=Q5bMBQEPCAcByGB8hwDM9Qo_HSr0m-_sEl0WhCGjlZrkejBsduP61NpsVG6sKTAgPEPq2AVnfGulnliO&stp=c0.5000x0.5000f_dst-emg0_p64x64_q75_tt6&ur=b696e2&_nc_sid=58080a&oh=00_Af58v1KZWk7rhnJrOrCIV-KpY5FtDjUdf0XcQ458u-LR7g&oe=6A07186A
A46: AD111 - Dois personagens - Brabo + legenda - PBB-ABR-26 | B46: [MA][cadastro][captação][quente][principal][PBB-ABR-26][30.03.26] | C46: 55.62 | D46: 19 | E46: 2.93 | F46: 03 - Viu 50% da Captação - PBB-ABR-26 | G46: 120244080589280520 | H46: https://www.facebook.com/418887747980692/posts/122214479648542386 | I46: https://www.instagram.com/p/DWmfUsJAHIz/ | J46: https://scontent.xx.fbcdn.net/v/t15.5256-10/659377503_788056310657693_6745498894763113159_n.jpg?_nc_cat=109&ccb=1-7&_nc_ohc=VJCwaQA0_H0Q7kNvwEbIKi_&_nc_oc=AdoqnwEXofOYXOtDjaqYazSyW-oak98Furv6opQ9dkj9e3quRPOGqVjW8OEdj8LXTnU&_nc_zt=23&_nc_ht=scontent.xx&edm=AAwGEdEEAAAA&_nc_gid=iEndcDk33bF5gt7MdoYrfg&_nc_tpa=Q5bMBQH3_gfNknFi5rre_T4XUoZnzfqFTdzMihDGEnAeCOi2Ca-XBalmaBHtLSeeNRDCQ4-dnO-ZTPqL&stp=c0.5000x0.5000f_dst-emg0_p64x64_q75_tt6&ur=b696e2&_nc_sid=58080a&oh=00_Af7SYxd_FTukeYxmRUUj4xoC8g4woebbeHsfC3Gb-1mGLQ&oe=6A07186A
A47: AD113 - Dois personagens ape do Felipe - PBB-ABR-26 | B47: [MA][cadastro][captação][quente][principal][PBB-ABR-26][30.03.26] | C47: 6025.5 | D47: 3134 | E47: 1.92 | F47: 03 - Viu 50% da Captação - PBB-ABR-26 | G47: 120244080589290520 | H47: https://www.facebook.com/418887747980692/posts/122214479822542386 | I47: https://www.instagram.com/p/DWmfVWegBJr/ | J47: https://scontent.xx.fbcdn.net/v/t15.5256-10/656850466_36157958293803722_1530186273580255821_n.jpg?_nc_cat=103&ccb=1-7&_nc_ohc=JYPaxhvv7rIQ7kNvwHRUTtz&_nc_oc=Adpxh15DH63wYqune_Ejk8r7whiigcxrC686H31xoY8jibaYtTg9TpRABbGTObPMyoA&_nc_zt=23&_nc_ht=scontent.xx&edm=AAwGEdEEAAAA&_nc_gid=iEndcDk33bF5gt7MdoYrfg&_nc_tpa=Q5bMBQGfC6uK_vx3QSEl5nacQov5-VUAKN_Rfgpz_WHvsTLnyLDxUCNexMtWci7v6AqQRqYiL9nFUDKW&stp=c0.5000x0.5000f_dst-emg0_p64x64_q75_tt6&ur=b696e2&_nc_sid=58080a&oh=00_Af54XMeMqt72wnKHJE37K1jk-3Zb8WpcTFwnv7qULLi56A&oe=6A073222
A48: AD092 - Dois personagens casa do Thales - PBB-ABR-26 | B48: [MA][cadastro][captação][quente][principal][PBB-ABR-26][30.03.26] | C48: 316.35 | D48: 141 | E48: 2.24 | F48: 03 - Viu 50% da Captação - PBB-ABR-26 | G48: 120244080589300520 | H48: https://www.facebook.com/418887747980692/posts/122214479702542386 | I48: https://www.instagram.com/p/DWmfT8FAF70/ | J48: https://scontent.xx.fbcdn.net/v/t15.5256-10/660096093_1479960643565032_1947641573874748707_n.jpg?_nc_cat=106&ccb=1-7&_nc_ohc=zLPmXguhBaAQ7kNvwEc4GUe&_nc_oc=AdpIw_n2s5yvv8v2AXk1nUqUr_JySByp8KjnPuoYi_fanlKPQgXJcsr4C9gJ2Fr-OmY&_nc_zt=23&_nc_ht=scontent.xx&edm=AAwGEdEEAAAA&_nc_gid=iEndcDk33bF5gt7MdoYrfg&_nc_tpa=Q5bMBQE8_Ea_V-pBCMbjQRfiTUfCXP-DTbbMcBOx6xVUGQ2PYRcRs0yVXIJ9pmjsptVvF3ETqGbKSiVY&stp=c0.5000x0.5000f_dst-emg0_p64x64_q75_tt6&ur=b696e2&_nc_sid=58080a&oh=00_Af7wcEG704TQkTlwID44yIQ5Zry6JmqVCQ4OJMW3hMWuiw&oe=6A072BAC
A49: AD108 - Imagem apostilas - PBB-ABR-26 | B49: [MA][cadastro][captação][quente][principal][PBB-ABR-26][30.03.26] | C49: 365.82 | D49: 160 | E49: 2.29 | F49: 03 - Viu 50% da Captação - PBB-ABR-26 | G49: 120244080589310520 | H49: https://www.facebook.com/418887747980692/posts/122214599870542386 | I49: https://www.instagram.com/p/DWmfVxKgOsh/ | J49: https://scontent.xx.fbcdn.net/v/t45.1600-4/657704700_10241910228635954_4215404491985677412_n.jpg?_nc_cat=102&ccb=1-7&_nc_ohc=1yrs_l8o3FYQ7kNvwHLe3fc&_nc_oc=Adoj1E7Pt5d42wlWp85hOgWXwa3avWQNfrmbvCDkh0bVA1rKxG8nZix7Lpln1MosKao&_nc_zt=1&_nc_ht=scontent.xx&edm=AAwGEdEEAAAA&_nc_gid=iEndcDk33bF5gt7MdoYrfg&_nc_tpa=Q5bMBQEyAPar-zZkdsI3SO9IwoD1LwXhpbhfkSVQsGcj3jzU6hNpuljGmOK42yAPUm_Ua_QseM1fVLah&stp=c0.5000x0.5000f_dst-emg0_p64x64_q75_tt6&ur=52f3c4&_nc_sid=58080a&oh=00_Af7jcyx9J08S2Ej_ZbQHjwYt2yQ9khEknjvdrdCru-A2gw&oe=6A073D71
A50: AD109 - Fachada Banco do Brasil com cx PBB-ABR-26 | B50: [MA][cadastro][captação][quente][principal][PBB-ABR-26][30.03.26] | C50: 1007.1 | D50: 94 | E50: 10.71 | F50: 03 - Viu 50% da Captação - PBB-ABR-26 | G50: 120244080589320520 | H50: https://www.facebook.com/418887747980692/posts/122214479618542386 | I50: https://www.instagram.com/p/DWmfUbggPGQ/ | J50: https://scontent.xx.fbcdn.net/v/t15.5256-10/656855442_1594235935028329_1659051163966614332_n.jpg?_nc_cat=104&ccb=1-7&_nc_ohc=xqN22eWerpwQ7kNvwFXVIIy&_nc_oc=AdpKfFNiYT9TkJjp1Xe-RO2MlMHUv8fhB-L5zmp4gbRcQYlgjuKT2aluzY1IxXuyqdo&_nc_zt=23&_nc_ht=scontent.xx&edm=AAwGEdEEAAAA&_nc_gid=iEndcDk33bF5gt7MdoYrfg&_nc_tpa=Q5bMBQEMzfYUOfsEtVn3OwedlZbrUjeUNtUPLdbCHFWyjMaquA0nheFcOkThyLOQSem7j_kI24Sve4mv&stp=c0.5000x0.5000f_dst-emg0_p64x64_q75_tt6&ur=b696e2&_nc_sid=58080a&oh=00_Af6R6aWO3NIfjb9Q6D8BMfxe5eJCfugfb3X2vBZDkykl1Q&oe=6A074314
A51: AD050 - Banco do Brasil 2 - cx nova - PBB-ABR-26 | B51: [MA][cadastro][captação][quente][principal][PBB-ABR-26][30.03.26] | C51: 2261.41 | D51: 919 | E51: 2.46 | F51: 03 - Viu 50% da Captação - PBB-ABR-26 | G51: 120244080589330520 | H51: https://www.facebook.com/418887747980692/posts/122214479732542386 | I51: https://www.instagram.com/p/DWmfUpOAECH/ | J51: https://scontent.xx.fbcdn.net/v/t15.5256-10/656950733_925953933387415_8803657205054814029_n.jpg?_nc_cat=104&ccb=1-7&_nc_ohc=J_K2Ip3KpmYQ7kNvwFbZHvI&_nc_oc=Adose2P1PbqhQHY4XpfgdR8yYnjUWQuawDYdOdmcmUPQn7VZxTIJFCyDfZpISCe7oa0&_nc_zt=23&_nc_ht=scontent.xx&edm=AAwGEdEEAAAA&_nc_gid=iEndcDk33bF5gt7MdoYrfg&_nc_tpa=Q5bMBQGG2jDH-HD7mCvbhQhf0HJE0eMXa1fzDpvTLFHbmiJf9nLL_qO1KXyCTS6P2tFVnADhySuVLxtW&stp=c0.5000x0.5000f_dst-emg0_p64x64_q75_tt6&ur=b696e2&_nc_sid=58080a&oh=00_Af512HcfWitX8J_2bnmgNrwAY6mIIMWHypzZVFVkvfyedA&oe=6A070D3D
A52: AD058 - Casa do Thales - PBB-ABR-26 | B52: [MA][cadastro][captação][quente][principal][PBB-ABR-26][30.03.26] | C52: 213.23 | D52: 81 | E52: 2.63 | F52: 03 - Viu 50% da Captação - PBB-ABR-26 | G52: 120244080589340520 | H52: https://www.facebook.com/418887747980692/posts/122214479714542386 | I52: https://www.instagram.com/p/DWmfTuyALgB/ | J52: https://scontent.xx.fbcdn.net/v/t15.5256-10/656850466_36157958293803722_1530186273580255821_n.jpg?_nc_cat=103&ccb=1-7&_nc_ohc=JYPaxhvv7rIQ7kNvwHRUTtz&_nc_oc=Adpxh15DH63wYqune_Ejk8r7whiigcxrC686H31xoY8jibaYtTg9TpRABbGTObPMyoA&_nc_zt=23&_nc_ht=scontent.xx&edm=AAwGEdEEAAAA&_nc_gid=iEndcDk33bF5gt7MdoYrfg&_nc_tpa=Q5bMBQEOXnMRg9RIqQXSkzMs2yf-6D40T9FUrWlAMldkEvexYOONIyb_yYT_TnNeEoTaKqGT__JA0zN9&stp=c0.5000x0.5000f_dst-emg0_p64x64_q75_tt6&ur=b696e2&_nc_sid=58080a&oh=00_Af5xU9ZA4HST7puidCoa5ObaXw6epOI17rzf6xXOjzjuyA&oe=6A073222
A53: AD059 - Fachada Banco do Brasil + cx nova PBB-ABR-26 | B53: [MA][cadastro][captação][quente][principal][PBB-ABR-26][30.03.26] | C53: 126.79 | D53: 21 | E53: 6.04 | F53: 03 - Viu 50% da Captação - PBB-ABR-26 | G53: 120244080589350520 | H53: https://www.facebook.com/418887747980692/posts/122214479636542386 | I53: https://www.instagram.com/p/DWmfUlFAHcM/ | J53: https://scontent.xx.fbcdn.net/v/t15.5256-10/655230990_2188016461967465_1976998085957988302_n.jpg?_nc_cat=108&ccb=1-7&_nc_ohc=RKZogepcc-cQ7kNvwHnCAqf&_nc_oc=AdpXy-s9kR-jSJxByVuBiEOT9v0JvZAf-cZycxP9Dj6qctXnO6YZYcNhJ4rwocDjo2E&_nc_zt=23&_nc_ht=scontent.xx&edm=AAwGEdEEAAAA&_nc_gid=iEndcDk33bF5gt7MdoYrfg&_nc_tpa=Q5bMBQH7txmO0nKkMu128d1x_QkSn9l-eQFnDC-WinHZ-6uoPf6MyEdHP3jb7RVfTf4mjZGWUrAIyUtz&stp=c0.5000x0.5000f_dst-emg0_p64x64_q75_tt6&ur=b696e2&_nc_sid=58080a&oh=00_Af5HsbIoLJOM-zRqebavVuae_R95TdZem3JqaydjfUi_SQ&oe=6A071423
A54: AD113 - Dois personagens ape do Felipe - PBB-ABR-26 | B54: [MA][cadastro][captação][quente][principal][PBB-ABR-26][30.03.26] | C54: 1600.12 | D54: 564 | E54: 2.84 | F54: 06 - [Felipe Graton] Envolvimento 180D | G54: 120244080589370520 | H54: https://www.facebook.com/418887747980692/posts/122214479822542386 | I54: https://www.instagram.com/p/DWZTTKogAW-/ | J54: https://scontent.xx.fbcdn.net/v/t15.5256-10/656850466_36157958293803722_1530186273580255821_n.jpg?_nc_cat=103&ccb=1-7&_nc_ohc=JYPaxhvv7rIQ7kNvwHRUTtz&_nc_oc=Adpxh15DH63wYqune_Ejk8r7whiigcxrC686H31xoY8jibaYtTg9TpRABbGTObPMyoA&_nc_zt=23&_nc_ht=scontent.xx&edm=AAwGEdEEAAAA&_nc_gid=iEndcDk33bF5gt7MdoYrfg&_nc_tpa=Q5bMBQGfC6uK_vx3QSEl5nacQov5-VUAKN_Rfgpz_WHvsTLnyLDxUCNexMtWci7v6AqQRqYiL9nFUDKW&stp=c0.5000x0.5000f_dst-emg0_p64x64_q75_tt6&ur=b696e2&_nc_sid=58080a&oh=00_Af54XMeMqt72wnKHJE37K1jk-3Zb8WpcTFwnv7qULLi56A&oe=6A073222
A55: AD109 - Fachada Banco do Brasil com cx PBB-ABR-26 | B55: [MA][cadastro][captação][quente][principal][PBB-ABR-26][30.03.26] | C55: 550.76 | D55: 207 | E55: 2.66 | F55: 06 - [Felipe Graton] Envolvimento 180D | G55: 120244080589380520 | H55: https://www.facebook.com/418887747980692/posts/122214479618542386 | I55: https://www.instagram.com/p/DWZTTBCgI9r/ | J55: https://scontent.xx.fbcdn.net/v/t15.5256-10/656855442_1594235935028329_1659051163966614332_n.jpg?_nc_cat=104&ccb=1-7&_nc_ohc=xqN22eWerpwQ7kNvwFXVIIy&_nc_oc=AdpKfFNiYT9TkJjp1Xe-RO2MlMHUv8fhB-L5zmp4gbRcQYlgjuKT2aluzY1IxXuyqdo&_nc_zt=23&_nc_ht=scontent.xx&edm=AAwGEdEEAAAA&_nc_gid=iEndcDk33bF5gt7MdoYrfg&_nc_tpa=Q5bMBQH6qLIwn-tmpsoYE7hK1zPIio6ztSGQJqSvFZ7r_Jk5eG-KOgVsWnIzeXtUGZUIv7m2ZxAu6rud&stp=c0.5000x0.5000f_dst-emg0_p64x64_q75_tt6&ur=b696e2&_nc_sid=58080a&oh=00_Af50v2D2cmWcm2tBqbFXpmdM6hE68WGtx6IPiDMIYqGRwQ&oe=6A074314
A56: AD111 - Dois personagens - Brabo + legenda - PBB-ABR-26 | B56: [MA][cadastro][captação][quente][principal][PBB-ABR-26][30.03.26] | C56: 1.67 | D56: 1 | E56: 1.67 | F56: 06 - [Felipe Graton] Envolvimento 180D | G56: 120244080589390520 | H56: https://www.facebook.com/418887747980692/posts/122214479648542386 | I56: https://www.instagram.com/p/DWZTSsxAIhD/ | J56: https://scontent.xx.fbcdn.net/v/t15.5256-10/659377503_788056310657693_6745498894763113159_n.jpg?_nc_cat=109&ccb=1-7&_nc_ohc=VJCwaQA0_H0Q7kNvwEbIKi_&_nc_oc=AdoqnwEXofOYXOtDjaqYazSyW-oak98Furv6opQ9dkj9e3quRPOGqVjW8OEdj8LXTnU&_nc_zt=23&_nc_ht=scontent.xx&edm=AAwGEdEEAAAA&_nc_gid=iEndcDk33bF5gt7MdoYrfg&_nc_tpa=Q5bMBQEPCAcByGB8hwDM9Qo_HSr0m-_sEl0WhCGjlZrkejBsduP61NpsVG6sKTAgPEPq2AVnfGulnliO&stp=c0.5000x0.5000f_dst-emg0_p64x64_q75_tt6&ur=b696e2&_nc_sid=58080a&oh=00_Af58v1KZWk7rhnJrOrCIV-KpY5FtDjUdf0XcQ458u-LR7g&oe=6A07186A
A57: AD059 - Fachada Banco do Brasil + cx nova PBB-ABR-26 | B57: [MA][cadastro][captação][quente][principal][PBB-ABR-26][30.03.26] | C57: 23.48 | D57: 7 | E57: 3.35 | F57: 06 - [Felipe Graton] Envolvimento 180D | G57: 120244080589400520 | H57: https://www.facebook.com/418887747980692/posts/122214479636542386 | I57: https://www.instagram.com/p/DWZTSkOAMba/ | J57: https://scontent.xx.fbcdn.net/v/t15.5256-10/655230990_2188016461967465_1976998085957988302_n.jpg?_nc_cat=108&ccb=1-7&_nc_ohc=RKZogepcc-cQ7kNvwHnCAqf&_nc_oc=AdpXy-s9kR-jSJxByVuBiEOT9v0JvZAf-cZycxP9Dj6qctXnO6YZYcNhJ4rwocDjo2E&_nc_zt=23&_nc_ht=scontent.xx&edm=AAwGEdEEAAAA&_nc_gid=iEndcDk33bF5gt7MdoYrfg&_nc_tpa=Q5bMBQGWV81HLcG08eSXKOL6gH7ximqIGDrg8bmTW4Rd2c56qTKDvdxpdFOpPADi4DH8uGFMpmEHcerK&stp=c0.5000x0.5000f_dst-emg0_p64x64_q75_tt6&ur=b696e2&_nc_sid=58080a&oh=00_Af6BPwKO6PsfrRNbWR5PDcWJfvpai_6EPVViW6jT2UhMsQ&oe=6A071423
... A65: AD113 - Dois personagens ape do Felipe - PBB-ABR-26 | B65: [MA][cadastro][captação][quente][principal][PBB-ABR-26][30.03.26] | C65: 1372.79 | D65: 390 | E65: 3.52 | F65: 02 - Visitou o Site da Brabo - 180D | G65: 120244080589590520 | H65: https://www.facebook.com/418887747980692/posts/122214479822542386 | I65: https://www.instagram.com/p/DWZTTikAGL1/ | J65: https://scontent.xx.fbcdn.net/v/t15.5256-10/656850466_36157958293803722_1530186273580255821_n.jpg?_nc_cat=103&ccb=1-7&_nc_ohc=JYPaxhvv7rIQ7kNvwHRUTtz&_nc_oc=Adpxh15DH63wYqune_Ejk8r7whiigcxrC686H31xoY8jibaYtTg9TpRABbGTObPMyoA&_nc_zt=23&_nc_ht=scontent.xx&edm=AAwGEdEEAAAA&_nc_gid=iEndcDk33bF5gt7MdoYrfg&_nc_tpa=Q5bMBQGfC6uK_vx3QSEl5nacQov5-VUAKN_Rfgpz_WHvsTLnyLDxUCNexMtWci7v6AqQRqYiL9nFUDKW&stp=c0.5000x0.5000f_dst-emg0_p64x64_q75_tt6&ur=b696e2&_nc_sid=58080a&oh=00_Af54XMeMqt72wnKHJE37K1jk-3Zb8WpcTFwnv7qULLi56A&oe=6A073222
A66: AD059 - Fachada Banco do Brasil + cx nova PBB-ABR-26 | B66: [MA][cadastro][captação][quente][principal][PBB-ABR-26][30.03.26] | C66: 11.25 | F66: 02 - Visitou o Site da Brabo - 180D | G66: 120244080589600520 | H66: https://www.facebook.com/418887747980692/posts/122214479636542386 | I66: https://www.instagram.com/p/DWZTSkOAMba/ | J66: https://scontent.xx.fbcdn.net/v/t15.5256-10/655230990_2188016461967465_1976998085957988302_n.jpg?_nc_cat=108&ccb=1-7&_nc_ohc=RKZogepcc-cQ7kNvwHnCAqf&_nc_oc=AdpXy-s9kR-jSJxByVuBiEOT9v0JvZAf-cZycxP9Dj6qctXnO6YZYcNhJ4rwocDjo2E&_nc_zt=23&_nc_ht=scontent.xx&edm=AAwGEdEEAAAA&_nc_gid=iEndcDk33bF5gt7MdoYrfg&_nc_tpa=Q5bMBQGWV81HLcG08eSXKOL6gH7ximqIGDrg8bmTW4Rd2c56qTKDvdxpdFOpPADi4DH8uGFMpmEHcerK&stp=c0.5000x0.5000f_dst-emg0_p64x64_q75_tt6&ur=b696e2&_nc_sid=58080a&oh=00_Af6BPwKO6PsfrRNbWR5PDcWJfvpai_6EPVViW6jT2UhMsQ&oe=6A071423
A67: AD108 - Imagem apostilas - PBB-ABR-26 | B67: [MA][cadastro][captação][quente][principal][PBB-ABR-26][30.03.26] | C67: 7.94 | D67: 2 | E67: 3.97 | F67: 02 - Visitou o Site da Brabo - 180D | G67: 120244080589610520 | H67: https://www.facebook.com/418887747980692/posts/122214599870542386 | I67: https://www.instagram.com/p/DWZTS5mABqq/ | J67: https://scontent.xx.fbcdn.net/v/t45.1600-4/657704700_10241910228635954_4215404491985677412_n.jpg?_nc_cat=102&ccb=1-7&_nc_ohc=1yrs_l8o3FYQ7kNvwHLe3fc&_nc_oc=Adoj1E7Pt5d42wlWp85hOgWXwa3avWQNfrmbvCDkh0bVA1rKxG8nZix7Lpln1MosKao&_nc_zt=1&_nc_ht=scontent.xx&edm=AAwGEdEEAAAA&_nc_gid=iEndcDk33bF5gt7MdoYrfg&_nc_tpa=Q5bMBQH_B-qbzkXzok_8wVdp85KiOzt88XdTUOkJ7m4q7TsZ-Y3Gp0X3OQAAUlSMe3hCCe2CqZuQOi-4&stp=c0.5000x0.5000f_dst-emg0_p64x64_q75_tt6&ur=52f3c4&_nc_sid=58080a&oh=00_Af6jsP72Zx3Zp7ievGdo7pCgbzhA4NRSj9RqH3uX3okd3g&oe=6A073D71
A68: AD050 - Banco do Brasil 2 - cx nova - PBB-ABR-26 | B68: [MA][cadastro][captação][quente][principal][PBB-ABR-26][30.03.26] | C68: 1380.64 | D68: 542 | E68: 2.55 | F68: 02 - Visitou o Site da Brabo - 180D | G68: 120244080589620520 | H68: https://www.facebook.com/418887747980692/posts/122214479732542386 | I68: https://www.instagram.com/p/DWZTSk2AHQB/ | J68: https://scontent.xx.fbcdn.net/v/t15.5256-10/656950733_925953933387415_8803657205054814029_n.jpg?_nc_cat=104&ccb=1-7&_nc_ohc=J_K2Ip3KpmYQ7kNvwFbZHvI&_nc_oc=Adose2P1PbqhQHY4XpfgdR8yYnjUWQuawDYdOdmcmUPQn7VZxTIJFCyDfZpISCe7oa0&_nc_zt=23&_nc_ht=scontent.xx&edm=AAwGEdEEAAAA&_nc_gid=iEndcDk33bF5gt7MdoYrfg&_nc_tpa=Q5bMBQEcRPuNCDLA1a5dOjhZI4UKdPBbKVZKUZyqpSGy9eQnkaXUfXh5N-n3QDQLk_y-fo7F0aHCKw6Z&stp=c0.5000x0.5000f_dst-emg0_p64x64_q75_tt6&ur=b696e2&_nc_sid=58080a&oh=00_Af5WuYVujW7VAUepA7QgHUd4zs2tn4fu5GGhZY6poXFZow&oe=6A070D3D
A69: AD109 - Fachada Banco do Brasil com cx PBB-ABR-26 | B69: [MA][cadastro][captação][quente][principal][PBB-ABR-26][30.03.26] | C69: 61.51 | D69: 2 | E69: 30.76 | F69: 02 - Visitou o Site da Brabo - 180D | G69: 120244080589630520 | H69: https://www.facebook.com/418887747980692/posts/122214479618542386 | I69: https://www.instagram.com/p/DWZTTBCgI9r/ | J69: https://scontent.xx.fbcdn.net/v/t15.5256-10/656855442_1594235935028329_1659051163966614332_n.jpg?_nc_cat=104&ccb=1-7&_nc_ohc=xqN22eWerpwQ7kNvwFXVIIy&_nc_oc=AdpKfFNiYT9TkJjp1Xe-RO2MlMHUv8fhB-L5zmp4gbRcQYlgjuKT2aluzY1IxXuyqdo&_nc_zt=23&_nc_ht=scontent.xx&edm=AAwGEdEEAAAA&_nc_gid=iEndcDk33bF5gt7MdoYrfg&_nc_tpa=Q5bMBQEoctBBN2ITCAaNsbmsvanEZUaQNYRMOig3-EzQ2Iuq1-F051ZM27pf4Sy9BM0edwClKwrrFoSa&stp=c0.5000x0.5000f_dst-emg0_p64x64_q75_tt6&ur=b696e2&_nc_sid=58080a&oh=00_Af5h7RnMbVKQyiVpU_1g6fzGNVVWkDPPELKD_p2e307qJg&oe=6A074314
A70: AD107 - Imagem apostilas - PBB-ABR-26 | B70: [MA][cadastro][captação][quente][potencial][PBB-ABR-26][30.03.26] | C70: 261.29 | D70: 82 | E70: 3.19 | F70: 02 - Visitou o Site da Brabo - 180D | G70: 120244080799880520 | H70: https://www.facebook.com/418887747980692/posts/122214595862542386 | I70: https://www.instagram.com/p/DWZTjMeAEIH/ | J70: https://scontent.xx.fbcdn.net/v/t45.1600-4/656007801_10241909975789633_3853226454270751295_n.jpg?_nc_cat=108&ccb=1-7&_nc_ohc=kT8nFml0jDMQ7kNvwGA7MPn&_nc_oc=Ado3cT5Cfy_kQvlN6xgA8vHng99VREb0P4JtrfCHfH7j8Z0lxTQIRB4rRjq4NASMPpI&_nc_zt=1&_nc_ht=scontent.xx&edm=AAwGEdEEAAAA&_nc_gid=iEndcDk33bF5gt7MdoYrfg&_nc_tpa=Q5bMBQH2J-e6cGImHBXAopemWKxhuyvZ544zmux4wcicAa1Wb7EwND6ra2x62H0kwxayZ8uydxZsHTR7&stp=c0.5000x0.5000f_dst-emg0_p64x64_q75_tt6&ur=52f3c4&_nc_sid=58080a&oh=00_Af6w2WX9yOklmUfVzIFmtfbVGVnV8z_B9NERRLeltR6nGw&oe=6A07362D
A71: AD110 - Banco do Brasil 2 - cx nova - PBB-ABR-26 | B71: [MA][cadastro][captação][quente][potencial][PBB-ABR-26][30.03.26] | C71: 787.82 | D71: 10 | E71: 78.78 | F71: 02 - Visitou o Site da Brabo - 180D | G71: 120244080799890520 | H71: https://www.facebook.com/418887747980692/posts/122214590924542386 | I71: https://www.instagram.com/p/DWZTjHKAORA/ | J71: https://scontent.xx.fbcdn.net/v/t15.5256-10/657320602_952154174159507_7148290027186586603_n.jpg?_nc_cat=102&ccb=1-7&_nc_ohc=2qVV1ntMrJMQ7kNvwFNUoqc&_nc_oc=Adrj0pnnRilH8ZRJilrWiMsiVTDSANVGL94u5nS7E7RrB2qUIG-1e2OBQ7Fp_49LzEw&_nc_zt=23&_nc_ht=scontent.xx&edm=AAwGEdEEAAAA&_nc_gid=iEndcDk33bF5gt7MdoYrfg&_nc_tpa=Q5bMBQFBepwbghP0VrczglluSZFCcdHi1K0teEFSZBXjEc7gUm2Aye_Xi5aMbLD7geSIq3YOyk20SGHJ&stp=c0.5000x0.5000f_dst-emg0_p64x64_q75_tt6&ur=b696e2&_nc_sid=58080a&oh=00_Af7Mul7D0oxHyY8IZOc5vq3LY5WN770cDDv0wrYg67SLQA&oe=6A0712D4
A72: AD112 - Dois personagens - Brabo+ legenda - PBB-ABR-26 | B72: [MA][cadastro][captação][quente][potencial][PBB-ABR-26][30.03.26] | C72: 257.68 | D72: 66 | E72: 3.9 | F72: 02 - Visitou o Site da Brabo - 180D | G72: 120244080799900520 | H72: https://www.facebook.com/418887747980692/posts/122214588368542386 | I72: https://www.instagram.com/p/DWZTjG4AKMq/ | J72: https://scontent.xx.fbcdn.net/v/t15.5256-10/656738039_1263737895730885_5448108828000008158_n.jpg?_nc_cat=106&ccb=1-7&_nc_ohc=irq3tXoRXr4Q7kNvwHfhpfX&_nc_oc=AdoYUAyhG0pc1eAEo4rmaCWwg14IzdWsfcGCdxNpVqwo13wS5eO91I4ddCVFKcTQGXw&_nc_zt=23&_nc_ht=scontent.xx&edm=AAwGEdEEAAAA&_nc_gid=iEndcDk33bF5gt7MdoYrfg&_nc_tpa=Q5bMBQFrWhSr5PceHtNys53kup_Iw-dp7pmnNaTHxm2QAWiQWQyJlP2Ese51LgyP2dFQJX1DP2l6vXM-&stp=c0.5000x0.5000f_dst-emg0_p64x64_q75_tt6&ur=b696e2&_nc_sid=58080a&oh=00_Af4CvnXmVe5YOr60eUzENo7Xoe_Ygnd2VIcGnS-XEy5tTg&oe=6A072D6E
A73: AD091 - Dois personagens violão - PBB-ABR-26 | B73: [MA][cadastro][captação][quente][potencial][PBB-ABR-26][30.03.26] | C73: 42.45 | D73: 9 | E73: 4.72 | F73: 02 - Visitou o Site da Brabo - 180D | G73: 120244080799910520 | H73: https://www.facebook.com/418887747980692/posts/122214584036542386 | I73: https://www.instagram.com/p/DWZTi6WAEOv/ | J73: https://scontent.xx.fbcdn.net/v/t15.5256-10/659727968_1414282403831192_297067356207755898_n.jpg?_nc_cat=105&ccb=1-7&_nc_ohc=G5hKJk2PLlgQ7kNvwEFg0rM&_nc_oc=AdplhTQH3fp3SNxnByyBbycj1mmfCOodVgUoACuClZcn721lc2kpt7r9POuRM0FssyU&_nc_zt=23&_nc_ht=scontent.xx&edm=AAwGEdEEAAAA&_nc_gid=iEndcDk33bF5gt7MdoYrfg&_nc_tpa=Q5bMBQEpMejtKO18_DFTNhKvVGeqXhtTAQJ4UXSgqvIPQxzBb06H_juib4AoIXCVeGwKepRrMOM1FHSw&stp=c0.5000x0.5000f_dst-emg0_p64x64_q75_tt6&ur=b696e2&_nc_sid=58080a&oh=00_Af51Idxgg0hdNNCFcbIhHWROFAZP0lzG6SBYFIZ0hUzUSg&oe=6A0729E5
A74: AD093 - Dois personagens casa do Thales - PBB-ABR-26 | B74: [MA][cadastro][captação][quente][potencial][PBB-ABR-26][30.03.26] | C74: 24.66 | D74: 5 | E74: 4.93 | F74: 02 - Visitou o Site da Brabo - 180D | G74: 120244080799920520 | H74: https://www.facebook.com/418887747980692/posts/122214586136542386 | I74: https://www.instagram.com/p/DWZTivLgFwR/ | J74: https://scontent.xx.fbcdn.net/v/t15.5256-10/659258083_3872133279756228_6646461170497367954_n.jpg?_nc_cat=103&ccb=1-7&_nc_ohc=bhRFkE2FzpcQ7kNvwGnxlCf&_nc_oc=AdoNaaJNXmdnykgQVwxZnMQWVeF45gR_IuB650BNQD0HhenZHTVNh99oWmCS3EQbR9A&_nc_zt=23&_nc_ht=scontent.xx&edm=AAwGEdEEAAAA&_nc_gid=iEndcDk33bF5gt7MdoYrfg&_nc_tpa=Q5bMBQHTqjH0Bnw7JHjAamHBRanXd923OAAEoAqjxFg5dDd5v6AmIvS9LN0myqn3OyZ11hxVwClrbHmA&stp=c0.5000x0.5000f_dst-emg0_p64x64_q75_tt6&ur=b696e2&_nc_sid=58080a&oh=00_Af47jkMoXMz7ka59ECvYzLb9QsggfKjYz7gx0PjdldezrQ&oe=6A072CB3
A75: AD049 - Flip + Canetão PBB-ABR-26 | B75: [MA][cadastro][captação][quente][potencial][PBB-ABR-26][30.03.26] | C75: 253.76 | D75: 79 | E75: 3.21 | F75: 02 - Visitou o Site da Brabo - 180D | G75: 120244080799930520 | H75: https://www.facebook.com/418887747980692/posts/122214581852542386 | I75: https://www.instagram.com/p/DWZTjRsADVg/ | J75: https://scontent.xx.fbcdn.net/v/t15.5256-10/658912530_964767329323365_336155474875441123_n.jpg?_nc_cat=108&ccb=1-7&_nc_ohc=fe34ezdWe50Q7kNvwHtIJXa&_nc_oc=AdqzYA-tTeB3StQhylV9tV-zSAsXjpiOsLZIux-hMKQWv3Sd2KK1N3ZIvqrMb8sedIY&_nc_zt=23&_nc_ht=scontent.xx&edm=AAwGEdEEAAAA&_nc_gid=iEndcDk33bF5gt7MdoYrfg&_nc_tpa=Q5bMBQH4UF38ubsmCT_khYrLTVIppGFHRT0dBTDFbJ3eAxhh_e0V4_YaFXAbP5Y_dsCt3rKLE7MT7TFP&stp=c0.5000x0.5000f_dst-emg0_p64x64_q75_tt6&ur=b696e2&_nc_sid=58080a&oh=00_Af4Ygf60RNwsve5pTOTSBx-rM2I1P45G8suHP8u5a8L2cA&oe=6A072D09
A76: AD095 - Felipe sentado - PBB-ABR-26 | B76: [MA][cadastro][captação][quente][potencial][PBB-ABR-26][30.03.26] | C76: 0.55 | F76: 02 - Visitou o Site da Brabo - 180D | G76: 120244080799940520 | H76: https://www.facebook.com/418887747980692/posts/122214579746542386 | I76: https://www.instagram.com/p/DWZTjAgAGOL/ | J76: https://scontent.xx.fbcdn.net/v/t15.5256-10/659015521_777825872069344_6853330414113120707_n.jpg?_nc_cat=102&ccb=1-7&_nc_ohc=BIvTDzLRsM0Q7kNvwE0L0iS&_nc_oc=Adq1MMqW9lS0rlj5wMYi6BrleQUDxMNpeF0LX67bYqwSRSXB5s5UgCADW5X2lO8j_G0&_nc_zt=23&_nc_ht=scontent.xx&edm=AAwGEdEEAAAA&_nc_gid=iEndcDk33bF5gt7MdoYrfg&_nc_tpa=Q5bMBQGlfuvvVW0OOy_MuVyckFVF0epU5JkE7SiRLTVImYtLPEKMll9fIDzicOGXIo_0-9KprGPec59c&stp=c0.5000x0.5000f_dst-emg0_p64x64_q75_tt6&ur=b696e2&_nc_sid=58080a&oh=00_Af7pq1hNv7xJuf6LKYPLsMN3Gld0Bx-mtUAXxDuF7I37vg&oe=6A072CA5
A77: AD097 - Carro + cx - PBB-ABR-26 | B77: [MA][cadastro][captação][quente][potencial][PBB-ABR-26][30.03.26] | C77: 28.5 | D77: 10 | E77: 2.85 | F77: 02 - Visitou o Site da Brabo - 180D | G77: 120244080799950520 | H77: https://www.facebook.com/418887747980692/posts/122214576476542386 | I77: https://www.instagram.com/p/DWZTiw_ADPp/ | J77: https://scontent.xx.fbcdn.net/v/t15.5256-10/659321723_2254137601661098_3915150513522158111_n.jpg?_nc_cat=100&ccb=1-7&_nc_ohc=VDBtqY-s7H0Q7kNvwEEuHpl&_nc_oc=Adp2uDM1qy8yyLJ_op-8Na2qHkq9BqN9Q9teAv248oq4_356dfjrnKKzkn3yAWG1Chg&_nc_zt=23&_nc_ht=scontent.xx&edm=AAwGEdEEAAAA&_nc_gid=iEndcDk33bF5gt7MdoYrfg&_nc_tpa=Q5bMBQHJqsG94mDfc2UFJ7KvzvUp_Fn9uGiU-JoQI35RfLvwh2RB8ZbvxAVHYRw7_JFr0EqVH7-4Gzkj&stp=c0.5000x0.5000f_dst-emg0_p64x64_q75_tt6&ur=b696e2&_nc_sid=58080a&oh=00_Af6bKLetwkv4w20TXOFjDR36El7LSJvjf-aozJUOTirq5A&oe=6A07199E
A78: AD093 - Dois personagens casa do Thales - PBB-ABR-26 | B78: [MA][cadastro][captação][quente][potencial][PBB-ABR-26][30.03.26] | C78: 0.87 | F78: 03 - Viu 50% da Captação - PBB-FEV-26 | G78: 120244080799960520 | H78: https://www.facebook.com/418887747980692/posts/122214586136542386 | I78: https://www.instagram.com/p/DWmf1U4gL76/ | J78: https://scontent.xx.fbcdn.net/v/t15.5256-10/659258083_3872133279756228_6646461170497367954_n.jpg?_nc_cat=103&ccb=1-7&_nc_ohc=bhRFkE2FzpcQ7kNvwGnxlCf&_nc_oc=AdoNaaJNXmdnykgQVwxZnMQWVeF45gR_IuB650BNQD0HhenZHTVNh99oWmCS3EQbR9A&_nc_zt=23&_nc_ht=scontent.xx&edm=AAwGEdEEAAAA&_nc_gid=iEndcDk33bF5gt7MdoYrfg&_nc_tpa=Q5bMBQFbN_IqczOprNvlxtJ_tigWAI3YG23tTkhzwmFebVQG71rr3kbFm3_njsK6Qg4dT-F67qQLZF9c&stp=c0.5000x0.5000f_dst-emg0_p64x64_q75_tt6&ur=b696e2&_nc_sid=58080a&oh=00_Af4mYpuUlctnkbVWQwxa3d4gAElTGlJIbtsfvKza5sfjjA&oe=6A072CB3
A79: AD049 - Flip + Canetão PBB-ABR-26 | B79: [MA][cadastro][captação][quente][potencial][PBB-ABR-26][30.03.26] | C79: 4.82 | D79: 2 | E79: 2.41 | F79: 03 - Viu 50% da Captação - PBB-FEV-26 | G79: 120244080799970520 | H79: https://www.facebook.com/418887747980692/posts/122214581852542386 | I79: https://www.instagram.com/p/DWmf1G1ALzY/ | J79: https://scontent.xx.fbcdn.net/v/t15.5256-10/658912530_964767329323365_336155474875441123_n.jpg?_nc_cat=108&ccb=1-7&_nc_ohc=fe34ezdWe50Q7kNvwHtIJXa&_nc_oc=AdqzYA-tTeB3StQhylV9tV-zSAsXjpiOsLZIux-hMKQWv3Sd2KK1N3ZIvqrMb8sedIY&_nc_zt=23&_nc_ht=scontent.xx&edm=AAwGEdEEAAAA&_nc_gid=iEndcDk33bF5gt7MdoYrfg&_nc_tpa=Q5bMBQHYGerjq_p6TD16aBD8bdeEW-6bdTb6biD7lA13nDpHCNBULTKPbh5-aUATKnXipt3roKmj5mgm&stp=c0.5000x0.5000f_dst-emg0_p64x64_q75_tt6&ur=b696e2&_nc_sid=58080a&oh=00_Af6mXgsD0MiQBQ2Q7P0ucoYkzBi_b6TvJh7ylTe7ad9mlQ&oe=6A072D09
A80: AD107 - Imagem apostilas - PBB-ABR-26 | B80: [MA][cadastro][captação][quente][potencial][PBB-ABR-26][30.03.26] | C80: 421.29 | D80: 191 | E80: 2.21 | F80: 03 - Viu 50% da Captação - PBB-FEV-26 | G80: 120244080799980520 | H80: https://www.facebook.com/418887747980692/posts/122214595862542386 | I80: https://www.instagram.com/p/DWmf2exAG0d/ | J80: https://scontent.xx.fbcdn.net/v/t45.1600-4/656007801_10241909975789633_3853226454270751295_n.jpg?_nc_cat=108&ccb=1-7&_nc_ohc=kT8nFml0jDMQ7kNvwGA7MPn&_nc_oc=Ado3cT5Cfy_kQvlN6xgA8vHng99VREb0P4JtrfCHfH7j8Z0lxTQIRB4rRjq4NASMPpI&_nc_zt=1&_nc_ht=scontent.xx&edm=AAwGEdEEAAAA&_nc_gid=iEndcDk33bF5gt7MdoYrfg&_nc_tpa=Q5bMBQEpQmz5Y5Lfzh3-wBuyvxBA_n6wAKFBo3FfHnr6QThQA7cTcPmp_SEQJo6OvTIgysR3htDIh1d8&stp=c0.5000x0.5000f_dst-emg0_p64x64_q75_tt6&ur=52f3c4&_nc_sid=58080a&oh=00_Af6yWrdVKjFgOO44CRSkxzj8SvFz-IyY5jVLHsKa8TmJ_g&oe=6A07362D
A81: AD071 - Casa do Felipe + cx - PBB-ABR-26 | B81: [MA][cadastro][captação][quente][potencial][PBB-ABR-26][30.03.26] | C81: 395.1 | D81: 129 | E81: 3.06 | F81: 02 - Visitou o Site da Brabo - 180D | G81: 120244080799990520 | H81: https://www.facebook.com/418887747980692/posts/122214577814542386 | I81: https://www.instagram.com/p/DWZTiwsgGbU/ | J81: https://scontent.xx.fbcdn.net/v/t15.5256-10/660365971_975418021505104_4535425168932836668_n.jpg?_nc_cat=109&ccb=1-7&_nc_ohc=hVjAM1sNlSkQ7kNvwEinrqP&_nc_oc=Adp-UGcMbs0xv-7Px4kAfTrBWpat2kiYy9BJWxG_J5XrIsxLI4JZzBDiU9dI-Z8ENEM&_nc_zt=23&_nc_ht=scontent.xx&edm=AAwGEdEEAAAA&_nc_gid=iEndcDk33bF5gt7MdoYrfg&_nc_tpa=Q5bMBQHQPNRbxb-BTJpCWmhOo9VRSZ7bOZix0Px7JSO8qqgN55ZGYmQcg0yuoFRerM45x79BuorQ34hh&stp=c0.5000x0.5000f_dst-emg0_p64x64_q75_tt6&ur=b696e2&_nc_sid=58080a&oh=00_Af5rCcU0vMNiv2C81FJHeAfZJmC6_yj6nP3wXnYWBjTRPw&oe=6A070B62
A82: AD091 - Dois personagens violão - PBB-ABR-26 | B82: [MA][cadastro][captação][quente][potencial][PBB-ABR-26][30.03.26] | C82: 42.77 | D82: 15 | E82: 2.85 | F82: 03 - Viu 50% da Captação - PBB-FEV-26 | G82: 120244080800000520 | H82: https://www.facebook.com/418887747980692/posts/122214584036542386 | I82: https://www.instagram.com/p/DWmf04cgCOT/ | J82: https://scontent.xx.fbcdn.net/v/t15.5256-10/659727968_1414282403831192_297067356207755898_n.jpg?_nc_cat=105&ccb=1-7&_nc_ohc=G5hKJk2PLlgQ7kNvwEFg0rM&_nc_oc=AdplhTQH3fp3SNxnByyBbycj1mmfCOodVgUoACuClZcn721lc2kpt7r9POuRM0FssyU&_nc_zt=23&_nc_ht=scontent.xx&edm=AAwGEdEEAAAA&_nc_gid=iEndcDk33bF5gt7MdoYrfg&_nc_tpa=Q5bMBQGNL4cAH51efzJSFlleRRFT9b4IDqz1AQw34dhOVLDBs11Pu9T6ywqxm1EwOis6AFr__0TE9QiE&stp=c0.5000x0.5000f_dst-emg0_p64x64_q75_tt6&ur=b696e2&_nc_sid=58080a&oh=00_Af6H31v5HWelY2FcYGma4wUzrZuIh5dL-LsovGz8K3I9Dg&oe=6A0729E5
A83: AD110 - Banco do Brasil 2 - cx nova - PBB-ABR-26 | B83: [MA][cadastro][captação][quente][potencial][PBB-ABR-26][30.03.26] | C83: 2577.99 | D83: 1176 | E83: 2.19 | F83: 03 - Viu 50% da Captação - PBB-FEV-26 | G83: 120244080800010520 | H83: https://www.facebook.com/418887747980692/posts/122214590924542386 | I83: https://www.instagram.com/p/DWmf08tAPtX/ | J83: https://scontent.xx.fbcdn.net/v/t15.5256-10/657320602_952154174159507_7148290027186586603_n.jpg?_nc_cat=102&ccb=1-7&_nc_ohc=2qVV1ntMrJMQ7kNvwFNUoqc&_nc_oc=Adrj0pnnRilH8ZRJilrWiMsiVTDSANVGL94u5nS7E7RrB2qUIG-1e2OBQ7Fp_49LzEw&_nc_zt=23&_nc_ht=scontent.xx&edm=AAwGEdEEAAAA&_nc_gid=iEndcDk33bF5gt7MdoYrfg&_nc_tpa=Q5bMBQG1iepg64J9SPHD4XCqk3FQ4Qk-5HZ59vnN7jZOhI8Rn6ZtXkyfIVsv8i0XlrDRMfMWFiD5Js4v&stp=c0.5000x0.5000f_dst-emg0_p64x64_q75_tt6&ur=b696e2&_nc_sid=58080a&oh=00_Af77g8S40POyGfqxbYjqTiuFhFsZQzJjZVmIzw5qm4wPJA&oe=6A0712D4
A84: AD112 - Dois personagens - Brabo+ legenda - PBB-ABR-26 | B84: [MA][cadastro][captação][quente][potencial][PBB-ABR-26][30.03.26] | C84: 4.62 | D84: 1 | E84: 4.62 | F84: 03 - Viu 50% da Captação - PBB-FEV-26 | G84: 120244080800020520 | H84: https://www.facebook.com/418887747980692/posts/122214588368542386 | I84: https://www.instagram.com/p/DWmf0hMAA2n/ | J84: https://scontent.xx.fbcdn.net/v/t15.5256-10/656738039_1263737895730885_5448108828000008158_n.jpg?_nc_cat=106&ccb=1-7&_nc_ohc=irq3tXoRXr4Q7kNvwHfhpfX&_nc_oc=AdoYUAyhG0pc1eAEo4rmaCWwg14IzdWsfcGCdxNpVqwo13wS5eO91I4ddCVFKcTQGXw&_nc_zt=23&_nc_ht=scontent.xx&edm=AAwGEdEEAAAA&_nc_gid=iEndcDk33bF5gt7MdoYrfg&_nc_tpa=Q5bMBQGjp2QxcL8EWvtIXbHNxK8jRCcete1qNl0wHT7QuRH8R8qSJljxiNSLKBRbxIucQQisR-zYkdKN&stp=c0.5000x0.5000f_dst-emg0_p64x64_q75_tt6&ur=b696e2&_nc_sid=58080a&oh=00_Af7Ss-tCXw-KpqHywYiiM-jAEVS0ADnattYrOd40aUtFqQ&oe=6A072D6E
A85: AD095 - Felipe sentado - PBB-ABR-26 | B85: [MA][cadastro][captação][quente][potencial][PBB-ABR-26][30.03.26] | C85: 3.99 | F85: 03 - Viu 50% da Captação - PBB-FEV-26 | G85: 120244080800030520 | H85: https://www.facebook.com/418887747980692/posts/122214579746542386 | I85: https://www.instagram.com/p/DWmf1QigKLv/ | J85: https://scontent.xx.fbcdn.net/v/t15.5256-10/659015521_777825872069344_6853330414113120707_n.jpg?_nc_cat=102&ccb=1-7&_nc_ohc=BIvTDzLRsM0Q7kNvwE0L0iS&_nc_oc=Adq1MMqW9lS0rlj5wMYi6BrleQUDxMNpeF0LX67bYqwSRSXB5s5UgCADW5X2lO8j_G0&_nc_zt=23&_nc_ht=scontent.xx&edm=AAwGEdEEAAAA&_nc_gid=iEndcDk33bF5gt7MdoYrfg&_nc_tpa=Q5bMBQGlfuvvVW0OOy_MuVyckFVF0epU5JkE7SiRLTVImYtLPEKMll9fIDzicOGXIo_0-9KprGPec59c&stp=c0.5000x0.5000f_dst-emg0_p64x64_q75_tt6&ur=b696e2&_nc_sid=58080a&oh=00_Af7pq1hNv7xJuf6LKYPLsMN3Gld0Bx-mtUAXxDuF7I37vg&oe=6A072CA5
A86: AD071 - Casa do Felipe + cx - PBB-ABR-26 | B86: [MA][cadastro][captação][quente][potencial][PBB-ABR-26][30.03.26] | C86: 28.56 | D86: 9 | E86: 3.17 | F86: 03 - Viu 50% da Captação - PBB-FEV-26 | G86: 120244080800040520 | H86: https://www.facebook.com/418887747980692/posts/122214577814542386 | I86: https://www.instagram.com/p/DWmf1UzgG-D/ | J86: https://scontent.xx.fbcdn.net/v/t15.5256-10/660365971_975418021505104_4535425168932836668_n.jpg?_nc_cat=109&ccb=1-7&_nc_ohc=hVjAM1sNlSkQ7kNvwEinrqP&_nc_oc=Adp-UGcMbs0xv-7Px4kAfTrBWpat2kiYy9BJWxG_J5XrIsxLI4JZzBDiU9dI-Z8ENEM&_nc_zt=23&_nc_ht=scontent.xx&edm=AAwGEdEEAAAA&_nc_gid=iEndcDk33bF5gt7MdoYrfg&_nc_tpa=Q5bMBQGZrrrkXiVq-DvjNKax1Up-98-WYEJP5SlCD56lNnCHMP2aYUoAXsBjHASCVD4C0K45tCZu0EIY&stp=c0.5000x0.5000f_dst-emg0_p64x64_q75_tt6&ur=b696e2&_nc_sid=58080a&oh=00_Af6S9-AejdK2Lf-7PqQJfr9rG5_TJf9NDxOtesRyVQsvtw&oe=6A070B62
A87: AD107 - Imagem apostilas - PBB-ABR-26 | B87: [MA][cadastro][captação][quente][potencial][PBB-ABR-26][30.03.26] | C87: 783.64 | D87: 296 | E87: 2.65 | F87: 05 - [Felipe Graton] Envolvimento 60D | G87: 120244080800050520 | H87: https://www.facebook.com/418887747980692/posts/122214595862542386 | I87: https://www.instagram.com/p/DWZTjMeAEIH/ | J87: https://scontent.xx.fbcdn.net/v/t45.1600-4/656007801_10241909975789633_3853226454270751295_n.jpg?_nc_cat=108&ccb=1-7&_nc_ohc=kT8nFml0jDMQ7kNvwGA7MPn&_nc_oc=Ado3cT5Cfy_kQvlN6xgA8vHng99VREb0P4JtrfCHfH7j8Z0lxTQIRB4rRjq4NASMPpI&_nc_zt=1&_nc_ht=scontent.xx&edm=AAwGEdEEAAAA&_nc_gid=iEndcDk33bF5gt7MdoYrfg&_nc_tpa=Q5bMBQH2J-e6cGImHBXAopemWKxhuyvZ544zmux4wcicAa1Wb7EwND6ra2x62H0kwxayZ8uydxZsHTR7&stp=c0.5000x0.5000f_dst-emg0_p64x64_q75_tt6&ur=52f3c4&_nc_sid=58080a&oh=00_Af6w2WX9yOklmUfVzIFmtfbVGVnV8z_B9NERRLeltR6nGw&oe=6A07362D
A88: AD110 - Banco do Brasil 2 - cx nova - PBB-ABR-26 | B88: [MA][cadastro][captação][quente][potencial][PBB-ABR-26][30.03.26] | C88: 1810.87 | D88: 767 | E88: 2.36 | F88: 05 - [Felipe Graton] Envolvimento 60D | G88: 120244080800060520 | H88: https://www.facebook.com/418887747980692/posts/122214590924542386 | I88: https://www.instagram.com/p/DWZTizvAJb2/ | J88: https://scontent.xx.fbcdn.net/v/t15.5256-10/657320602_952154174159507_7148290027186586603_n.jpg?_nc_cat=102&ccb=1-7&_nc_ohc=2qVV1ntMrJMQ7kNvwFNUoqc&_nc_oc=Adrj0pnnRilH8ZRJilrWiMsiVTDSANVGL94u5nS7E7RrB2qUIG-1e2OBQ7Fp_49LzEw&_nc_zt=23&_nc_ht=scontent.xx&edm=AAwGEdEEAAAA&_nc_gid=iEndcDk33bF5gt7MdoYrfg&_nc_tpa=Q5bMBQFBepwbghP0VrczglluSZFCcdHi1K0teEFSZBXjEc7gUm2Aye_Xi5aMbLD7geSIq3YOyk20SGHJ&stp=c0.5000x0.5000f_dst-emg0_p64x64_q75_tt6&ur=b696e2&_nc_sid=58080a&oh=00_Af7Mul7D0oxHyY8IZOc5vq3LY5WN770cDDv0wrYg67SLQA&oe=6A0712D4
A89: AD097 - Carro + cx - PBB-ABR-26 | B89: [MA][cadastro][captação][quente][potencial][PBB-ABR-26][30.03.26] | C89: 8.28 | D89: 2 | E89: 4.14 | F89: 03 - Viu 50% da Captação - PBB-FEV-26 | G89: 120244080800070520 | H89: https://www.facebook.com/418887747980692/posts/122214576476542386 | I89: https://www.instagram.com/p/DWmf1z2gCgR/ | J89: https://scontent.xx.fbcdn.net/v/t15.5256-10/659321723_2254137601661098_3915150513522158111_n.jpg?_nc_cat=100&ccb=1-7&_nc_ohc=VDBtqY-s7H0Q7kNvwEEuHpl&_nc_oc=Adp2uDM1qy8yyLJ_op-8Na2qHkq9BqN9Q9teAv248oq4_356dfjrnKKzkn3yAWG1Chg&_nc_zt=23&_nc_ht=scontent.xx&edm=AAwGEdEEAAAA&_nc_gid=iEndcDk33bF5gt7MdoYrfg&_nc_tpa=Q5bMBQHQ6osrmQexTU8rd4jJDZnW8xA_NPjHJsN2bbctV6zYfV_3twDk-XF5JV5zldiL7-VbwKtGtw3i&stp=c0.5000x0.5000f_dst-emg0_p64x64_q75_tt6&ur=b696e2&_nc_sid=58080a&oh=00_Af6dc3G11CtUL7vh7sIrqIPEVhf6wlQQbbGFa-NAvamP1A&oe=6A07199E
A90: AD093 - Dois personagens casa do Thales - PBB-ABR-26 | B90: [MA][cadastro][captação][quente][potencial][PBB-ABR-26][30.03.26] | C90: 0.18 | F90: 05 - [Felipe Graton] Envolvimento 60D | G90: 120244080800080520 | H90: https://www.facebook.com/418887747980692/posts/122214586136542386 | I90: https://www.instagram.com/p/DWZTjOwgLPO/ | J90: https://scontent.xx.fbcdn.net/v/t15.5256-10/659258083_3872133279756228_6646461170497367954_n.jpg?_nc_cat=103&ccb=1-7&_nc_ohc=bhRFkE2FzpcQ7kNvwGnxlCf&_nc_oc=AdoNaaJNXmdnykgQVwxZnMQWVeF45gR_IuB650BNQD0HhenZHTVNh99oWmCS3EQbR9A&_nc_zt=23&_nc_ht=scontent.xx&edm=AAwGEdEEAAAA&_nc_gid=iEndcDk33bF5gt7MdoYrfg&_nc_tpa=Q5bMBQHUi-1MXBsk3AS9ZZbm7eUsTd38IWUGUnAGlr8OlBM3HNYy1vrjeJak0QuqwPmUvxwwkLkUAv3L&stp=c0.5000x0.5000f_dst-emg0_p64x64_q75_tt6&ur=b696e2&_nc_sid=58080a&oh=00_Af638K0EHUk12v66WYOAG14BinHRCaMip5sovsxT5ld07Q&oe=6A072CB3
A91: AD112 - Dois personagens - Brabo+ legenda - PBB-ABR-26 | B91: [MA][cadastro][captação][quente][potencial][PBB-ABR-26][30.03.26] | C91: 7.64 | D91: 3 | E91: 2.55 | F91: 05 - [Felipe Graton] Envolvimento 60D | G91: 120244080800090520 | H91: https://www.facebook.com/418887747980692/posts/122214588368542386 | I91: https://www.instagram.com/p/DWZTi6ZAEXv/ | J91: https://scontent.xx.fbcdn.net/v/t15.5256-10/656738039_1263737895730885_5448108828000008158_n.jpg?_nc_cat=106&ccb=1-7&_nc_ohc=irq3tXoRXr4Q7kNvwHfhpfX&_nc_oc=AdoYUAyhG0pc1eAEo4rmaCWwg14IzdWsfcGCdxNpVqwo13wS5eO91I4ddCVFKcTQGXw&_nc_zt=23&_nc_ht=scontent.xx&edm=AAwGEdEEAAAA&_nc_gid=iEndcDk33bF5gt7MdoYrfg&_nc_tpa=Q5bMBQEkx1wgxlaAcSd6psOGLShJ6oOb25A-77qASypX3GsuTcT3vkj3xONqZQ7BLGqeDZmTYcbPOl2L&stp=c0.5000x0.5000f_dst-emg0_p64x64_q75_tt6&ur=b696e2&_nc_sid=58080a&oh=00_Af4zoX40S_YAj5hZPbqcFj43OkaxhC95Rq92GSG_u_fPdw&oe=6A072D6E
A92: AD091 - Dois personagens violão - PBB-ABR-26 | B92: [MA][cadastro][captação][quente][potencial][PBB-ABR-26][30.03.26] | C92: 10.21 | D92: 1 | E92: 10.21 | F92: 05 - [Felipe Graton] Envolvimento 60D | G92: 120244080800100520 | H92: https://www.facebook.com/418887747980692/posts/122214584036542386 | I92: https://www.instagram.com/p/DWZTi3hAPYf/ | J92: https://scontent.xx.fbcdn.net/v/t15.5256-10/659727968_1414282403831192_297067356207755898_n.jpg?_nc_cat=105&ccb=1-7&_nc_ohc=G5hKJk2PLlgQ7kNvwEFg0rM&_nc_oc=AdplhTQH3fp3SNxnByyBbycj1mmfCOodVgUoACuClZcn721lc2kpt7r9POuRM0FssyU&_nc_zt=23&_nc_ht=scontent.xx&edm=AAwGEdEEAAAA&_nc_gid=iEndcDk33bF5gt7MdoYrfg&_nc_tpa=Q5bMBQEbEmhIPSQgKr5cuZ1uAIT1iBwYIo2vhxhPUlpdea3q5QLydpUYqCBZzz-5k2l7MXYj9EynRt6b&stp=c0.5000x0.5000f_dst-emg0_p64x64_q75_tt6&ur=b696e2&_nc_sid=58080a&oh=00_Af7iW0KqbUYwj_z2agX6a8kC1YeFnVDuWj9cGL-SMTquCA&oe=6A0729E5
A93: AD095 - Felipe sentado - PBB-ABR-26 | B93: [MA][cadastro][captação][quente][potencial][PBB-ABR-26][30.03.26] | C93: 0.09 | F93: 05 - [Felipe Graton] Envolvimento 60D | G93: 120244080800110520 | H93: https://www.facebook.com/418887747980692/posts/122214579746542386 | I93: https://www.instagram.com/p/DWZTjAgAGOL/ | J93: https://scontent.xx.fbcdn.net/v/t15.5256-10/659015521_777825872069344_6853330414113120707_n.jpg?_nc_cat=102&ccb=1-7&_nc_ohc=BIvTDzLRsM0Q7kNvwE0L0iS&_nc_oc=Adq1MMqW9lS0rlj5wMYi6BrleQUDxMNpeF0LX67bYqwSRSXB5s5UgCADW5X2lO8j_G0&_nc_zt=23&_nc_ht=scontent.xx&edm=AAwGEdEEAAAA&_nc_gid=iEndcDk33bF5gt7MdoYrfg&_nc_tpa=Q5bMBQGzY6YXMAk6Bz3zSlre8Y_J8jeEacELugpAncfuqxtvX4TpW2iVY3PelU044_VD8SjEUH-OwjOg&stp=c0.5000x0.5000f_dst-emg0_p64x64_q75_tt6&ur=b696e2&_nc_sid=58080a&oh=00_Af6ZfVteZxaA0xc_1eu-e0I5zePpy5oHgfm8sAmTDCLOQw&oe=6A072CA5
A94: AD097 - Carro + cx - PBB-ABR-26 | B94: [MA][cadastro][captação][quente][potencial][PBB-ABR-26][30.03.26] | C94: 1.54 | F94: 05 - [Felipe Graton] Envolvimento 60D | G94: 120244080800120520 | H94: https://www.facebook.com/418887747980692/posts/122214576476542386 | I94: https://www.instagram.com/p/DWZTi1AALYX/ | J94: https://scontent.xx.fbcdn.net/v/t15.5256-10/659321723_2254137601661098_3915150513522158111_n.jpg?_nc_cat=100&ccb=1-7&_nc_ohc=VDBtqY-s7H0Q7kNvwEEuHpl&_nc_oc=Adp2uDM1qy8yyLJ_op-8Na2qHkq9BqN9Q9teAv248oq4_356dfjrnKKzkn3yAWG1Chg&_nc_zt=23&_nc_ht=scontent.xx&edm=AAwGEdEEAAAA&_nc_gid=iEndcDk33bF5gt7MdoYrfg&_nc_tpa=Q5bMBQFZHWor874Ql8bTlvvqqHpZn8zVAHu6fhcRVglZ6YuW1Wk7SwIWyfs4BaGC4AvscALBmZGtEOsb&stp=c0.5000x0.5000f_dst-emg0_p64x64_q75_tt6&ur=b696e2&_nc_sid=58080a&oh=00_Af7zBDtP1mGP9a2Vk_X5uDo1i4dLYjvruUOt4BB1HU1JTg&oe=6A07199E
A95: AD049 - Flip + Canetão PBB-ABR-26 | B95: [MA][cadastro][captação][quente][potencial][PBB-ABR-26][30.03.26] | C95: 15.31 | D95: 5 | E95: 3.06 | F95: 05 - [Felipe Graton] Envolvimento 60D | G95: 120244080800130520 | H95: https://www.facebook.com/418887747980692/posts/122214581852542386 | I95: https://www.instagram.com/p/DWZTi2agJG2/ | J95: https://scontent.xx.fbcdn.net/v/t15.5256-10/658912530_964767329323365_336155474875441123_n.jpg?_nc_cat=108&ccb=1-7&_nc_ohc=fe34ezdWe50Q7kNvwHtIJXa&_nc_oc=AdqzYA-tTeB3StQhylV9tV-zSAsXjpiOsLZIux-hMKQWv3Sd2KK1N3ZIvqrMb8sedIY&_nc_zt=23&_nc_ht=scontent.xx&edm=AAwGEdEEAAAA&_nc_gid=iEndcDk33bF5gt7MdoYrfg&_nc_tpa=Q5bMBQHksm5yKgFKay7MzmzD0ATS0xF1flpkPJcz5Q6DeQnT56NTRS5ipQXFOJeo8CrnoCFWqfaMpamO&stp=c0.5000x0.5000f_dst-emg0_p64x64_q75_tt6&ur=b696e2&_nc_sid=58080a&oh=00_Af4NMQUS_fGc9X80CK87RyFNj2nqDTJ9UayttGUBUVxDZg&oe=6A072D09
A96: AD071 - Casa do Felipe + cx - PBB-ABR-26 | B96: [MA][cadastro][captação][quente][potencial][PBB-ABR-26][30.03.26] | C96: 345.91 | D96: 134 | E96: 2.58 | F96: 05 - [Felipe Graton] Envolvimento 60D | G96: 120244080800140520 | H96: https://www.facebook.com/418887747980692/posts/122214577814542386 | I96: https://www.instagram.com/p/DWZTiotABkB/ | J96: https://scontent.xx.fbcdn.net/v/t15.5256-10/660365971_975418021505104_4535425168932836668_n.jpg?_nc_cat=109&ccb=1-7&_nc_ohc=hVjAM1sNlSkQ7kNvwEinrqP&_nc_oc=Adp-UGcMbs0xv-7Px4kAfTrBWpat2kiYy9BJWxG_J5XrIsxLI4JZzBDiU9dI-Z8ENEM&_nc_zt=23&_nc_ht=scontent.xx&edm=AAwGEdEEAAAA&_nc_gid=iEndcDk33bF5gt7MdoYrfg&_nc_tpa=Q5bMBQHQPNRbxb-BTJpCWmhOo9VRSZ7bOZix0Px7JSO8qqgN55ZGYmQcg0yuoFRerM45x79BuorQ34hh&stp=c0.5000x0.5000f_dst-emg0_p64x64_q75_tt6&ur=b696e2&_nc_sid=58080a&oh=00_Af5rCcU0vMNiv2C81FJHeAfZJmC6_yj6nP3wXnYWBjTRPw&oe=6A070B62
A97: AD112 - Dois personagens - Brabo+ legenda - PBB-ABR-26 | B97: [MA][cadastro][captação][quente][potencial][PBB-ABR-26][30.03.26] | C97: 155.66 | D97: 40 | E97: 3.89 | F97: 04 - Viu 25% da Captação - PBB-ABR-26 | G97: 120244080800170520 | H97: https://www.facebook.com/418887747980692/posts/122214588368542386 | I97: https://www.instagram.com/p/DWmf0hMAA2n/ | J97: https://scontent.xx.fbcdn.net/v/t15.5256-10/656738039_1263737895730885_5448108828000008158_n.jpg?_nc_cat=106&ccb=1-7&_nc_ohc=irq3tXoRXr4Q7kNvwHfhpfX&_nc_oc=AdoYUAyhG0pc1eAEo4rmaCWwg14IzdWsfcGCdxNpVqwo13wS5eO91I4ddCVFKcTQGXw&_nc_zt=23&_nc_ht=scontent.xx&edm=AAwGEdEEAAAA&_nc_gid=iEndcDk33bF5gt7MdoYrfg&_nc_tpa=Q5bMBQGjp2QxcL8EWvtIXbHNxK8jRCcete1qNl0wHT7QuRH8R8qSJljxiNSLKBRbxIucQQisR-zYkdKN&stp=c0.5000x0.5000f_dst-emg0_p64x64_q75_tt6&ur=b696e2&_nc_sid=58080a&oh=00_Af7Ss-tCXw-KpqHywYiiM-jAEVS0ADnattYrOd40aUtFqQ&oe=6A072D6E
A98: AD071 - Casa do Felipe + cx - PBB-ABR-26 | B98: [MA][cadastro][captação][quente][potencial][PBB-ABR-26][30.03.26] | C98: 488.36 | D98: 159 | E98: 3.07 | F98: 04 - Viu 25% da Captação - PBB-ABR-26 | G98: 120244080800180520 | H98: https://www.facebook.com/418887747980692/posts/122214577814542386 | I98: https://www.instagram.com/p/DWmf1UzgG-D/ | J98: https://scontent.xx.fbcdn.net/v/t15.5256-10/660365971_975418021505104_4535425168932836668_n.jpg?_nc_cat=109&ccb=1-7&_nc_ohc=hVjAM1sNlSkQ7kNvwEinrqP&_nc_oc=Adp-UGcMbs0xv-7Px4kAfTrBWpat2kiYy9BJWxG_J5XrIsxLI4JZzBDiU9dI-Z8ENEM&_nc_zt=23&_nc_ht=scontent.xx&edm=AAwGEdEEAAAA&_nc_gid=iEndcDk33bF5gt7MdoYrfg&_nc_tpa=Q5bMBQGZrrrkXiVq-DvjNKax1Up-98-WYEJP5SlCD56lNnCHMP2aYUoAXsBjHASCVD4C0K45tCZu0EIY&stp=c0.5000x0.5000f_dst-emg0_p64x64_q75_tt6&ur=b696e2&_nc_sid=58080a&oh=00_Af6S9-AejdK2Lf-7PqQJfr9rG5_TJf9NDxOtesRyVQsvtw&oe=6A070B62
A99: AD095 - Felipe sentado - PBB-ABR-26 | B99: [MA][cadastro][captação][quente][potencial][PBB-ABR-26][30.03.26] | C99: 9.09 | F99: 04 - Viu 25% da Captação - PBB-ABR-26 | G99: 120244080800190520 | H99: https://www.facebook.com/418887747980692/posts/122214579746542386 | I99: https://www.instagram.com/p/DWmf1QigKLv/ | J99: https://scontent.xx.fbcdn.net/v/t15.5256-10/659015521_777825872069344_6853330414113120707_n.jpg?_nc_cat=102&ccb=1-7&_nc_ohc=BIvTDzLRsM0Q7kNvwE0L0iS&_nc_oc=Adq1MMqW9lS0rlj5wMYi6BrleQUDxMNpeF0LX67bYqwSRSXB5s5UgCADW5X2lO8j_G0&_nc_zt=23&_nc_ht=scontent.xx&edm=AAwGEdEEAAAA&_nc_gid=iEndcDk33bF5gt7MdoYrfg&_nc_tpa=Q5bMBQGlfuvvVW0OOy_MuVyckFVF0epU5JkE7SiRLTVImYtLPEKMll9fIDzicOGXIo_0-9KprGPec59c&stp=c0.5000x0.5000f_dst-emg0_p64x64_q75_tt6&ur=b696e2&_nc_sid=58080a&oh=00_Af7pq1hNv7xJuf6LKYPLsMN3Gld0Bx-mtUAXxDuF7I37vg&oe=6A072CA5
A100: AD097 - Carro + cx - PBB-ABR-26 | B100: [MA][cadastro][captação][quente][potencial][PBB-ABR-26][30.03.26] | C100: 153.29 | D100: 64 | E100: 2.4 | F100: 04 - Viu 25% da Captação - PBB-ABR-26 | G100: 120244080800200520 | H100: https://www.facebook.com/418887747980692/posts/122214576476542386 | I100: https://www.instagram.com/p/DWmf1ZqgE9B/ | J100: https://scontent.xx.fbcdn.net/v/t15.5256-10/659321723_2254137601661098_3915150513522158111_n.jpg?_nc_cat=100&ccb=1-7&_nc_ohc=VDBtqY-s7H0Q7kNvwEEuHpl&_nc_oc=Adp2uDM1qy8yyLJ_op-8Na2qHkq9BqN9Q9teAv248oq4_356dfjrnKKzkn3yAWG1Chg&_nc_zt=23&_nc_ht=scontent.xx&edm=AAwGEdEEAAAA&_nc_gid=iEndcDk33bF5gt7MdoYrfg&_nc_tpa=Q5bMBQHQ6osrmQexTU8rd4jJDZnW8xA_NPjHJsN2bbctV6zYfV_3twDk-XF5JV5zldiL7-VbwKtGtw3i&stp=c0.5000x0.5000f_dst-emg0_p64x64_q75_tt6&ur=b696e2&_nc_sid=58080a&oh=00_Af6dc3G11CtUL7vh7sIrqIPEVhf6wlQQbbGFa-NAvamP1A&oe=6A07199E
A101: AD091 - Dois personagens violão - PBB-ABR-26 | B101: [MA][cadastro][captação][quente][potencial][PBB-ABR-26][30.03.26] | C101: 0.7 | F101: 04 - Viu 25% da Captação - PBB-ABR-26 | G101: 120244080800210520 | H101: https://www.facebook.com/418887747980692/posts/122214584036542386 | I101: https://www.instagram.com/p/DWmf0-bACl9/ | J101: https://scontent.xx.fbcdn.net/v/t15.5256-10/659727968_1414282403831192_297067356207755898_n.jpg?_nc_cat=105&ccb=1-7&_nc_ohc=G5hKJk2PLlgQ7kNvwEFg0rM&_nc_oc=AdplhTQH3fp3SNxnByyBbycj1mmfCOodVgUoACuClZcn721lc2kpt7r9POuRM0FssyU&_nc_zt=23&_nc_ht=scontent.xx&edm=AAwGEdEEAAAA&_nc_gid=iEndcDk33bF5gt7MdoYrfg&_nc_tpa=Q5bMBQF-jdZsSRiex7lrtQUOAZLh_DLYSwXfWomObzHnjfFF7FHK_bfULXex4pLCStOW6dftL7gGnSiU&stp=c0.5000x0.5000f_dst-emg0_p64x64_q75_tt6&ur=b696e2&_nc_sid=58080a&oh=00_Af5_bHLHNSF1vBEKZ_UEFiSTBmp1a_oJ_GNnvl9uwKcl-w&oe=6A0729E5
A102: AD071 - Casa do Felipe + cx - PBB-ABR-26 | B102: [MA][cadastro][captação][quente][potencial][PBB-ABR-26][30.03.26] | C102: 529.13 | D102: 144 | E102: 3.67 | F102: 01 - Caiu na pag. de Captura [PBB-ABR-26] | G102: 120244080800220520 | H102: https://www.facebook.com/418887747980692/posts/122214577814542386 | I102: https://www.instagram.com/p/DWZTiotABkB/ | J102: https://scontent.xx.fbcdn.net/v/t15.5256-10/660365971_975418021505104_4535425168932836668_n.jpg?_nc_cat=109&ccb=1-7&_nc_ohc=hVjAM1sNlSkQ7kNvwEinrqP&_nc_oc=Adp-UGcMbs0xv-7Px4kAfTrBWpat2kiYy9BJWxG_J5XrIsxLI4JZzBDiU9dI-Z8ENEM&_nc_zt=23&_nc_ht=scontent.xx&edm=AAwGEdEEAAAA&_nc_gid=iEndcDk33bF5gt7MdoYrfg&_nc_tpa=Q5bMBQHQPNRbxb-BTJpCWmhOo9VRSZ7bOZix0Px7JSO8qqgN55ZGYmQcg0yuoFRerM45x79BuorQ34hh&stp=c0.5000x0.5000f_dst-emg0_p64x64_q75_tt6&ur=b696e2&_nc_sid=58080a&oh=00_Af5rCcU0vMNiv2C81FJHeAfZJmC6_yj6nP3wXnYWBjTRPw&oe=6A070B62
A103: AD049 - Flip + Canetão PBB-ABR-26 | B103: [MA][cadastro][captação][quente][potencial][PBB-ABR-26][30.03.26] | C103: 36.53 | D103: 15 | E103: 2.44 | F103: 04 - Viu 25% da Captação - PBB-ABR-26 | G103: 120244080800230520 | H103: https://www.facebook.com/418887747980692/posts/122214581852542386 | I103: https://www.instagram.com/p/DWmf1G1ALzY/ | J103: https://scontent.xx.fbcdn.net/v/t15.5256-10/658912530_964767329323365_336155474875441123_n.jpg?_nc_cat=108&ccb=1-7&_nc_ohc=fe34ezdWe50Q7kNvwHtIJXa&_nc_oc=AdqzYA-tTeB3StQhylV9tV-zSAsXjpiOsLZIux-hMKQWv3Sd2KK1N3ZIvqrMb8sedIY&_nc_zt=23&_nc_ht=scontent.xx&edm=AAwGEdEEAAAA&_nc_gid=iEndcDk33bF5gt7MdoYrfg&_nc_tpa=Q5bMBQHYGerjq_p6TD16aBD8bdeEW-6bdTb6biD7lA13nDpHCNBULTKPbh5-aUATKnXipt3roKmj5mgm&stp=c0.5000x0.5000f_dst-emg0_p64x64_q75_tt6&ur=b696e2&_nc_sid=58080a&oh=00_Af6mXgsD0MiQBQ2Q7P0ucoYkzBi_b6TvJh7ylTe7ad9mlQ&oe=6A072D09
A104: AD097 - Carro + cx - PBB-ABR-26 | B104: [MA][cadastro][captação][quente][potencial][PBB-ABR-26][30.03.26] | C104: 5.37 | D104: 3 | E104: 1.79 | F104: 01 - Caiu na pag. de Captura [PBB-ABR-26] | G104: 120244080800240520 | H104: https://www.facebook.com/418887747980692/posts/122214576476542386 | I104: https://www.instagram.com/p/DWZTiw_ADPp/ | J104: https://scontent.xx.fbcdn.net/v/t15.5256-10/659321723_2254137601661098_3915150513522158111_n.jpg?_nc_cat=100&ccb=1-7&_nc_ohc=VDBtqY-s7H0Q7kNvwEEuHpl&_nc_oc=Adp2uDM1qy8yyLJ_op-8Na2qHkq9BqN9Q9teAv248oq4_356dfjrnKKzkn3yAWG1Chg&_nc_zt=23&_nc_ht=scontent.xx&edm=AAwGEdEEAAAA&_nc_gid=iEndcDk33bF5gt7MdoYrfg&_nc_tpa=Q5bMBQFWNJwBGOd6eKXzhLyooM6FeNrJyNvkVcOnSx9xg4Cc4w0L3cGBsNKvTo2vwXJ9vqMfcrgKyqL_&stp=c0.5000x0.5000f_dst-emg0_p64x64_q75_tt6&ur=b696e2&_nc_sid=58080a&oh=00_Af5Z99JgbnlsuI45eKG-qqH0BD2tzD4I3gDt6f-6oc5esQ&oe=6A07199E
A105: AD093 - Dois personagens casa do Thales - PBB-ABR-26 | B105: [MA][cadastro][captação][quente][potencial][PBB-ABR-26][30.03.26] | C105: 0.72 | F105: 04 - Viu 25% da Captação - PBB-ABR-26 | G105: 120244080800250520 | H105: https://www.facebook.com/418887747980692/posts/122214586136542386 | I105: https://www.instagram.com/p/DWmf1U4gL76/ | J105: https://scontent.xx.fbcdn.net/v/t15.5256-10/659258083_3872133279756228_6646461170497367954_n.jpg?_nc_cat=103&ccb=1-7&_nc_ohc=bhRFkE2FzpcQ7kNvwGnxlCf&_nc_oc=AdoNaaJNXmdnykgQVwxZnMQWVeF45gR_IuB650BNQD0HhenZHTVNh99oWmCS3EQbR9A&_nc_zt=23&_nc_ht=scontent.xx&edm=AAwGEdEEAAAA&_nc_gid=iEndcDk33bF5gt7MdoYrfg&_nc_tpa=Q5bMBQFbN_IqczOprNvlxtJ_tigWAI3YG23tTkhzwmFebVQG71rr3kbFm3_njsK6Qg4dT-F67qQLZF9c&stp=c0.5000x0.5000f_dst-emg0_p64x64_q75_tt6&ur=b696e2&_nc_sid=58080a&oh=00_Af4mYpuUlctnkbVWQwxa3d4gAElTGlJIbtsfvKza5sfjjA&oe=6A072CB3
A106: AD107 - Imagem apostilas - PBB-ABR-26 | B106: [MA][cadastro][captação][quente][potencial][PBB-ABR-26][30.03.26] | C106: 401.48 | D106: 116 | E106: 3.46 | F106: 01 - Caiu na pag. de Captura [PBB-ABR-26] | G106: 120244080800260520 | H106: https://www.facebook.com/418887747980692/posts/122214595862542386 | I106: https://www.instagram.com/p/DWZTjMeAEIH/ | J106: https://scontent.xx.fbcdn.net/v/t45.1600-4/656007801_10241909975789633_3853226454270751295_n.jpg?_nc_cat=108&ccb=1-7&_nc_ohc=kT8nFml0jDMQ7kNvwGA7MPn&_nc_oc=Ado3cT5Cfy_kQvlN6xgA8vHng99VREb0P4JtrfCHfH7j8Z0lxTQIRB4rRjq4NASMPpI&_nc_zt=1&_nc_ht=scontent.xx&edm=AAwGEdEEAAAA&_nc_gid=iEndcDk33bF5gt7MdoYrfg&_nc_tpa=Q5bMBQH2J-e6cGImHBXAopemWKxhuyvZ544zmux4wcicAa1Wb7EwND6ra2x62H0kwxayZ8uydxZsHTR7&stp=c0.5000x0.5000f_dst-emg0_p64x64_q75_tt6&ur=52f3c4&_nc_sid=58080a&oh=00_Af6w2WX9yOklmUfVzIFmtfbVGVnV8z_B9NERRLeltR6nGw&oe=6A07362D
A107: AD095 - Felipe sentado - PBB-ABR-26 | B107: [MA][cadastro][captação][quente][potencial][PBB-ABR-26][30.03.26] | C107: 1.01 | F107: 01 - Caiu na pag. de Captura [PBB-ABR-26] | G107: 120244080800270520 | H107: https://www.facebook.com/418887747980692/posts/122214579746542386 | I107: https://www.instagram.com/p/DWZTjAgAGOL/ | J107: https://scontent.xx.fbcdn.net/v/t15.5256-10/659015521_777825872069344_6853330414113120707_n.jpg?_nc_cat=102&ccb=1-7&_nc_ohc=BIvTDzLRsM0Q7kNvwE0L0iS&_nc_oc=Adq1MMqW9lS0rlj5wMYi6BrleQUDxMNpeF0LX67bYqwSRSXB5s5UgCADW5X2lO8j_G0&_nc_zt=23&_nc_ht=scontent.xx&edm=AAwGEdEEAAAA&_nc_gid=iEndcDk33bF5gt7MdoYrfg&_nc_tpa=Q5bMBQGzY6YXMAk6Bz3zSlre8Y_J8jeEacELugpAncfuqxtvX4TpW2iVY3PelU044_VD8SjEUH-OwjOg&stp=c0.5000x0.5000f_dst-emg0_p64x64_q75_tt6&ur=b696e2&_nc_sid=58080a&oh=00_Af6ZfVteZxaA0xc_1eu-e0I5zePpy5oHgfm8sAmTDCLOQw&oe=6A072CA5
A108: AD107 - Imagem apostilas - PBB-ABR-26 | B108: [MA][cadastro][captação][quente][potencial][PBB-ABR-26][30.03.26] | C108: 443.67 | D108: 138 | E108: 3.22 | F108: 04 - Viu 25% da Captação - PBB-ABR-26 | G108: 120244080800280520 | H108: https://www.facebook.com/418887747980692/posts/122214595862542386 | I108: https://www.instagram.com/p/DWmf3sIgKqK/ | J108: https://scontent.xx.fbcdn.net/v/t45.1600-4/656007801_10241909975789633_3853226454270751295_n.jpg?_nc_cat=108&ccb=1-7&_nc_ohc=kT8nFml0jDMQ7kNvwGA7MPn&_nc_oc=Ado3cT5Cfy_kQvlN6xgA8vHng99VREb0P4JtrfCHfH7j8Z0lxTQIRB4rRjq4NASMPpI&_nc_zt=1&_nc_ht=scontent.xx&edm=AAwGEdEEAAAA&_nc_gid=iEndcDk33bF5gt7MdoYrfg&_nc_tpa=Q5bMBQEpQmz5Y5Lfzh3-wBuyvxBA_n6wAKFBo3FfHnr6QThQA7cTcPmp_SEQJo6OvTIgysR3htDIh1d8&stp=c0.5000x0.5000f_dst-emg0_p64x64_q75_tt6&ur=52f3c4&_nc_sid=58080a&oh=00_Af6yWrdVKjFgOO44CRSkxzj8SvFz-IyY5jVLHsKa8TmJ_g&oe=6A07362D
A109: AD110 - Banco do Brasil 2 - cx nova - PBB-ABR-26 | B109: [MA][cadastro][captação][quente][potencial][PBB-ABR-26][30.03.26] | C109: 3998.53 | D109: 1754 | E109: 2.28 | F109: 04 - Viu 25% da Captação - PBB-ABR-26 | G109: 120244080800290520 | H109: https://www.facebook.com/418887747980692/posts/122214590924542386 | I109: https://www.instagram.com/p/DWmf08tAPtX/ | J109: https://scontent.xx.fbcdn.net/v/t15.5256-10/657320602_952154174159507_7148290027186586603_n.jpg?_nc_cat=102&ccb=1-7&_nc_ohc=2qVV1ntMrJMQ7kNvwFNUoqc&_nc_oc=Adrj0pnnRilH8ZRJilrWiMsiVTDSANVGL94u5nS7E7RrB2qUIG-1e2OBQ7Fp_49LzEw&_nc_zt=23&_nc_ht=scontent.xx&edm=AAwGEdEEAAAA&_nc_gid=iEndcDk33bF5gt7MdoYrfg&_nc_tpa=Q5bMBQG1iepg64J9SPHD4XCqk3FQ4Qk-5HZ59vnN7jZOhI8Rn6ZtXkyfIVsv8i0XlrDRMfMWFiD5Js4v&stp=c0.5000x0.5000f_dst-emg0_p64x64_q75_tt6&ur=b696e2&_nc_sid=58080a&oh=00_Af77g8S40POyGfqxbYjqTiuFhFsZQzJjZVmIzw5qm4wPJA&oe=6A0712D4
A110: AD093 - Dois personagens casa do Thales - PBB-ABR-26 | B110: [MA][cadastro][captação][quente][potencial][PBB-ABR-26][30.03.26] | C110: 0.67 | D110: 1 | E110: 0.67 | F110: 01 - Caiu na pag. de Captura [PBB-ABR-26] | G110: 120244080800300520 | H110: https://www.facebook.com/418887747980692/posts/122214586136542386 | I110: https://www.instagram.com/p/DWZTjD5gCDE/ | J110: https://scontent.xx.fbcdn.net/v/t15.5256-10/659258083_3872133279756228_6646461170497367954_n.jpg?_nc_cat=103&ccb=1-7&_nc_ohc=bhRFkE2FzpcQ7kNvwGnxlCf&_nc_oc=AdoNaaJNXmdnykgQVwxZnMQWVeF45gR_IuB650BNQD0HhenZHTVNh99oWmCS3EQbR9A&_nc_zt=23&_nc_ht=scontent.xx&edm=AAwGEdEEAAAA&_nc_gid=iEndcDk33bF5gt7MdoYrfg&_nc_tpa=Q5bMBQHUi-1MXBsk3AS9ZZbm7eUsTd38IWUGUnAGlr8OlBM3HNYy1vrjeJak0QuqwPmUvxwwkLkUAv3L&stp=c0.5000x0.5000f_dst-emg0_p64x64_q75_tt6&ur=b696e2&_nc_sid=58080a&oh=00_Af638K0EHUk12v66WYOAG14BinHRCaMip5sovsxT5ld07Q&oe=6A072CB3
A111: AD049 - Flip + Canetão PBB-ABR-26 | B111: [MA][cadastro][captação][quente][potencial][PBB-ABR-26][30.03.26] | C111: 8.35 | D111: 3 | E111: 2.78 | F111: 01 - Caiu na pag. de Captura [PBB-ABR-26] | G111: 120244080800310520 | H111: https://www.facebook.com/418887747980692/posts/122214581852542386 | I111: https://www.instagram.com/p/DWZTjRsADVg/ | J111: https://scontent.xx.fbcdn.net/v/t15.5256-10/658912530_964767329323365_336155474875441123_n.jpg?_nc_cat=108&ccb=1-7&_nc_ohc=fe34ezdWe50Q7kNvwHtIJXa&_nc_oc=AdqzYA-tTeB3StQhylV9tV-zSAsXjpiOsLZIux-hMKQWv3Sd2KK1N3ZIvqrMb8sedIY&_nc_zt=23&_nc_ht=scontent.xx&edm=AAwGEdEEAAAA&_nc_gid=iEndcDk33bF5gt7MdoYrfg&_nc_tpa=Q5bMBQHksm5yKgFKay7MzmzD0ATS0xF1flpkPJcz5Q6DeQnT56NTRS5ipQXFOJeo8CrnoCFWqfaMpamO&stp=c0.5000x0.5000f_dst-emg0_p64x64_q75_tt6&ur=b696e2&_nc_sid=58080a&oh=00_Af4NMQUS_fGc9X80CK87RyFNj2nqDTJ9UayttGUBUVxDZg&oe=6A072D09
A112: AD091 - Dois personagens violão - PBB-ABR-26 | B112: [MA][cadastro][captação][quente][potencial][PBB-ABR-26][30.03.26] | C112: 0.64 | F112: 01 - Caiu na pag. de Captura [PBB-ABR-26] | G112: 120244080800320520 | H112: https://www.facebook.com/418887747980692/posts/122214584036542386 | I112: https://www.instagram.com/p/DWZTiyNgOJD/ | J112: https://scontent.xx.fbcdn.net/v/t15.5256-10/659727968_1414282403831192_297067356207755898_n.jpg?_nc_cat=105&ccb=1-7&_nc_ohc=G5hKJk2PLlgQ7kNvwEFg0rM&_nc_oc=AdplhTQH3fp3SNxnByyBbycj1mmfCOodVgUoACuClZcn721lc2kpt7r9POuRM0FssyU&_nc_zt=23&_nc_ht=scontent.xx&edm=AAwGEdEEAAAA&_nc_gid=iEndcDk33bF5gt7MdoYrfg&_nc_tpa=Q5bMBQF-jdZsSRiex7lrtQUOAZLh_DLYSwXfWomObzHnjfFF7FHK_bfULXex4pLCStOW6dftL7gGnSiU&stp=c0.5000x0.5000f_dst-emg0_p64x64_q75_tt6&ur=b696e2&_nc_sid=58080a&oh=00_Af5_bHLHNSF1vBEKZ_UEFiSTBmp1a_oJ_GNnvl9uwKcl-w&oe=6A0729E5
A113: AD112 - Dois personagens - Brabo+ legenda - PBB-ABR-26 | B113: [MA][cadastro][captação][quente][potencial][PBB-ABR-26][30.03.26] | C113: 117.18 | D113: 42 | E113: 2.79 | F113: 01 - Caiu na pag. de Captura [PBB-ABR-26] | G113: 120244080800330520 | H113: https://www.facebook.com/418887747980692/posts/122214588368542386 | I113: https://www.instagram.com/p/DWZTi6ZAEXv/ | J113: https://scontent.xx.fbcdn.net/v/t15.5256-10/656738039_1263737895730885_5448108828000008158_n.jpg?_nc_cat=106&ccb=1-7&_nc_ohc=irq3tXoRXr4Q7kNvwHfhpfX&_nc_oc=AdoYUAyhG0pc1eAEo4rmaCWwg14IzdWsfcGCdxNpVqwo13wS5eO91I4ddCVFKcTQGXw&_nc_zt=23&_nc_ht=scontent.xx&edm=AAwGEdEEAAAA&_nc_gid=iEndcDk33bF5gt7MdoYrfg&_nc_tpa=Q5bMBQEkx1wgxlaAcSd6psOGLShJ6oOb25A-77qASypX3GsuTcT3vkj3xONqZQ7BLGqeDZmTYcbPOl2L&stp=c0.5000x0.5000f_dst-emg0_p64x64_q75_tt6&ur=b696e2&_nc_sid=58080a&oh=00_Af4zoX40S_YAj5hZPbqcFj43OkaxhC95Rq92GSG_u_fPdw&oe=6A072D6E
A114: AD110 - Banco do Brasil 2 - cx nova - PBB-ABR-26 | B114: [MA][cadastro][captação][quente][potencial][PBB-ABR-26][30.03.26] | C114: 2630.12 | D114: 1115 | E114: 2.36 | F114: 01 - Caiu na pag. de Captura [PBB-ABR-26] | G114: 120244080800340520 | H114: https://www.facebook.com/418887747980692/posts/122214590924542386 | I114: https://www.instagram.com/p/DWZTizvAJb2/ | J114: https://scontent.xx.fbcdn.net/v/t15.5256-10/657320602_952154174159507_7148290027186586603_n.jpg?_nc_cat=102&ccb=1-7&_nc_ohc=2qVV1ntMrJMQ7kNvwFNUoqc&_nc_oc=Adrj0pnnRilH8ZRJilrWiMsiVTDSANVGL94u5nS7E7RrB2qUIG-1e2OBQ7Fp_49LzEw&_nc_zt=23&_nc_ht=scontent.xx&edm=AAwGEdEEAAAA&_nc_gid=iEndcDk33bF5gt7MdoYrfg&_nc_tpa=Q5bMBQEaZbTa9_NcYTg2bwJI8Uz-XN8j1WrVrNcEXL37rXZK-bn6F4unMv6zIXFgJjrlLJR3uFAxaUfJ&stp=c0.5000x0.5000f_dst-emg0_p64x64_q75_tt6&ur=b696e2&_nc_sid=58080a&oh=00_Af5oIAav3rGS5gXmGRn5wsiLc0X-Vh6wHS2_dVjGr3iMFQ&oe=6A0712D4
A115: AD097 - Carro + cx - PBB-ABR-26 | B115: [MA][cadastro][captação][quente][potencial][PBB-ABR-26][30.03.26] | C115: 1.88 | D115: 1 | E115: 1.88 | F115: 06 - [Felipe Graton] Envolvimento 180D | G115: 120244080801000520 | H115: https://www.facebook.com/418887747980692/posts/122214576476542386 | I115: https://www.instagram.com/p/DWZTiw_ADPp/ | J115: https://scontent.xx.fbcdn.net/v/t15.5256-10/659321723_2254137601661098_3915150513522158111_n.jpg?_nc_cat=100&ccb=1-7&_nc_ohc=VDBtqY-s7H0Q7kNvwEEuHpl&_nc_oc=Adp2uDM1qy8yyLJ_op-8Na2qHkq9BqN9Q9teAv248oq4_356dfjrnKKzkn3yAWG1Chg&_nc_zt=23&_nc_ht=scontent.xx&edm=AAwGEdEEAAAA&_nc_gid=iEndcDk33bF5gt7MdoYrfg&_nc_tpa=Q5bMBQFWNJwBGOd6eKXzhLyooM6FeNrJyNvkVcOnSx9xg4Cc4w0L3cGBsNKvTo2vwXJ9vqMfcrgKyqL_&stp=c0.5000x0.5000f_dst-emg0_p64x64_q75_tt6&ur=b696e2&_nc_sid=58080a&oh=00_Af5Z99JgbnlsuI45eKG-qqH0BD2tzD4I3gDt6f-6oc5esQ&oe=6A07199E
A116: AD107 - Imagem apostilas - PBB-ABR-26 | B116: [MA][cadastro][captação][quente][potencial][PBB-ABR-26][30.03.26] | C116: 4.11 | D116: 4 | E116: 1.03 | F116: 06 - [Felipe Graton] Envolvimento 180D | G116: 120244080801010520 | H116: https://www.facebook.com/418887747980692/posts/122214595862542386 | I116: https://www.instagram.com/p/DWZTjMeAEIH/ | J116: https://scontent.xx.fbcdn.net/v/t45.1600-4/656007801_10241909975789633_3853226454270751295_n.jpg?_nc_cat=108&ccb=1-7&_nc_ohc=kT8nFml0jDMQ7kNvwGA7MPn&_nc_oc=Ado3cT5Cfy_kQvlN6xgA8vHng99VREb0P4JtrfCHfH7j8Z0lxTQIRB4rRjq4NASMPpI&_nc_zt=1&_nc_ht=scontent.xx&edm=AAwGEdEEAAAA&_nc_gid=iEndcDk33bF5gt7MdoYrfg&_nc_tpa=Q5bMBQG2Gx_q_5qEEqvHFejEHPWLwKG6-RJiS1CE05My2c9ymYEiw9_qkequu8UlcjGBChaa4l1Y-zu8&stp=c0.5000x0.5000f_dst-emg0_p64x64_q75_tt6&ur=52f3c4&_nc_sid=58080a&oh=00_Af5LJsbcVmEAZI8K0yWD-FD3bQ_kSd_Ok7aHtIphZDf6eg&oe=6A07362D
A117: AD110 - Banco do Brasil 2 - cx nova - PBB-ABR-26 | B117: [MA][cadastro][captação][quente][potencial][PBB-ABR-26][30.03.26] | C117: 1128.94 | D117: 514 | E117: 2.2 | F117: 06 - [Felipe Graton] Envolvimento 180D | G117: 120244080801020520 | H117: https://www.facebook.com/418887747980692/posts/122214590924542386 | I117: https://www.instagram.com/p/DWZTizvAJb2/ | J117: https://scontent.xx.fbcdn.net/v/t15.5256-10/657320602_952154174159507_7148290027186586603_n.jpg?_nc_cat=102&ccb=1-7&_nc_ohc=2qVV1ntMrJMQ7kNvwFNUoqc&_nc_oc=Adrj0pnnRilH8ZRJilrWiMsiVTDSANVGL94u5nS7E7RrB2qUIG-1e2OBQ7Fp_49LzEw&_nc_zt=23&_nc_ht=scontent.xx&edm=AAwGEdEEAAAA&_nc_gid=iEndcDk33bF5gt7MdoYrfg&_nc_tpa=Q5bMBQEaZbTa9_NcYTg2bwJI8Uz-XN8j1WrVrNcEXL37rXZK-bn6F4unMv6zIXFgJjrlLJR3uFAxaUfJ&stp=c0.5000x0.5000f_dst-emg0_p64x64_q75_tt6&ur=b696e2&_nc_sid=58080a&oh=00_Af5oIAav3rGS5gXmGRn5wsiLc0X-Vh6wHS2_dVjGr3iMFQ&oe=6A0712D4
A118: AD112 - Dois personagens - Brabo+ legenda - PBB-ABR-26 | B118: [MA][cadastro][captação][quente][potencial][PBB-ABR-26][30.03.26] | C118: 0.41 | F118: 06 - [Felipe Graton] Envolvimento 180D | G118: 120244080801030520 | H118: https://www.facebook.com/418887747980692/posts/122214588368542386 | I118: https://www.instagram.com/p/DWZTjHrgPK1/ | J118: https://scontent.xx.fbcdn.net/v/t15.5256-10/656738039_1263737895730885_5448108828000008158_n.jpg?_nc_cat=106&ccb=1-7&_nc_ohc=irq3tXoRXr4Q7kNvwHfhpfX&_nc_oc=AdoYUAyhG0pc1eAEo4rmaCWwg14IzdWsfcGCdxNpVqwo13wS5eO91I4ddCVFKcTQGXw&_nc_zt=23&_nc_ht=scontent.xx&edm=AAwGEdEEAAAA&_nc_gid=iEndcDk33bF5gt7MdoYrfg&_nc_tpa=Q5bMBQFee1EwZ3evlqF0b1px4G0Dpau9TCvSxqQiotx2e6pRcdxfXsaJA9DFEnBVUltUz79d9OsSw_mn&stp=c0.5000x0.5000f_dst-emg0_p64x64_q75_tt6&ur=b696e2&_nc_sid=58080a&oh=00_Af4CKUcYpq22nPqwi7I6zNO50oa7-RHpF4euioP7ecKgVw&oe=6A072D6E
...

Sheet EXTRACAO-GA
A1: Ad Name | B1: Campaign Name | C1: Cost (Spend) | D1: Conversions | E1: Cost / conv. | F1: Ad Group Name | G1: Day | H1: Video Id
A2: AD093 - Dois personagens casa do Thales - PBB-ABR-26 | B2: [GA][captação][específico][principal][PBB-ABR-26][03.04.26] | C2: 9.64 | D2: 1 | E2: 9.64 | F2: 00 - Viu vídeos Pré-quali - PBB-ABR-26 | G2: 46110 | H2: IdQJSf3JppY
A3: AD093 - Dois personagens casa do Thales - PBB-ABR-26 | B3: [GA][captação][específico][principal][PBB-ABR-26][03.04.26] | C3: 3.11 | D3: 2 | E3: 1.56 | F3: 00 - Viu vídeos Pré-quali - PBB-ABR-26 | G3: 46110 | H3: M6VD6Pln568
A4: AD093 - Dois personagens casa do Thales - PBB-ABR-26 | B4: [GA][captação][específico][principal][PBB-ABR-26][03.04.26] | C4: 2.72 | D4: 0 | E4: 0 | F4: 00 - Viu vídeos Pré-quali - PBB-ABR-26 | G4: 46110 | H4: tO9pNx1LfKA
A5: AD084 - Duas pessoas com caixa - PBB-ABR-26 | B5: [GA][captação][específico][principal][PBB-ABR-26][03.04.26] | C5: 4.46 | D5: 3 | E5: 1.49 | F5: 00 - Viu vídeos Pré-quali - PBB-ABR-26 | G5: 46110 | H5: Tx0nZPWkzH0
A6: AD084 - Duas pessoas com caixa - PBB-ABR-26 | B6: [GA][captação][específico][principal][PBB-ABR-26][03.04.26] | C6: 15.43 | D6: 3 | E6: 5.14 | F6: 00 - Viu vídeos Pré-quali - PBB-ABR-26 | G6: 46110 | H6: lMk8JGTt2mc
A7: AD050 - Banco do Brasil 2 - cx nova - PBB-ABR-26 | B7: [GA][captação][específico][principal][PBB-ABR-26][03.04.26] | C7: 2.28 | D7: 1 | E7: 2.28 | F7: 00 - Viu vídeos Pré-quali - PBB-ABR-26 | G7: 46110 | H7: 8acIC41_Mmw
A8: AD050 - Banco do Brasil 2 - cx nova - PBB-ABR-26 | B8: [GA][captação][específico][principal][PBB-ABR-26][03.04.26] | C8: 2.74 | D8: 1 | E8: 2.74 | F8: 00 - Viu vídeos Pré-quali - PBB-ABR-26 | G8: 46110 | H8: Ti3VCdb7u4E
A9: AD050 - Banco do Brasil 2 - cx nova - PBB-ABR-26 | B9: [GA][captação][específico][principal][PBB-ABR-26][03.04.26] | C9: 10.05 | D9: 1 | E9: 10.05 | F9: 00 - Viu vídeos Pré-quali - PBB-ABR-26 | G9: 46110 | H9: VJqKqsMJaT4
A10: AD097 - Carro + cx - PBB-ABR-26 | B10: [GA][captação][específico][principal][PBB-ABR-26][03.04.26] | C10: 5.73 | D10: 2 | E10: 2.87 | F10: 00 - Viu vídeos Pré-quali - PBB-ABR-26 | G10: 46110 | H10: NLmBRbnX-ug
A11: AD097 - Carro + cx - PBB-ABR-26 | B11: [GA][captação][específico][principal][PBB-ABR-26][03.04.26] | C11: 8.53 | D11: 0 | E11: 0 | F11: 00 - Viu vídeos Pré-quali - PBB-ABR-26 | G11: 46110 | H11: jBKlN3bX0og
A12: AD090 - Dois personagens diva - PBB-ABR-26 | B12: [GA][captação][específico][principal][PBB-ABR-26][03.04.26] | C12: 3.66 | D12: 0 | E12: 0 | F12: 00 - Viu vídeos Pré-quali - PBB-ABR-26 | G12: 46110 | H12: 0HMdWbp57lo
A13: AD090 - Dois personagens diva - PBB-ABR-26 | B13: [GA][captação][específico][principal][PBB-ABR-26][03.04.26] | C13: 2.57 | D13: 1 | E13: 2.57 | F13: 00 - Viu vídeos Pré-quali - PBB-ABR-26 | G13: 46110 | H13: VkyRIyDco-s
... A15418: AD117 - Em frente ao Banco do Brasil - PBB-ABR-26 | B15418: [GA][captação][quente][ads-novos][PBB-ABR-26][07.04.26] | C15418: 3.55 | D15418: 0 | E15418: 0 | F15418: 05 - Envolvimento - 60D | G15418: 46125 | H15418: ZHYcOPB4Yvo

Sheet Raw Data Report
B1: Relatório sem título mar-1-2026 a mar-31-2026 | C1: #gid=574214319 | E1: Report Period: Mar 1, 2026 - Mar 31, 2026
B3: Dia | C3: Nome do anúncio | D3: Nome da campanha | E3: Nome do conjunto de anúncios | F3: Valor usado (BRL) | G3: Leads | H3: Custo por lead | I3: Início dos relatórios | J3: Término dos relatórios
B4: 2026-03-31 | C4: AD03 | D4: [ENGAJAMENTO] Distribuição de Conteúdo - 14.01.25 | E4: 00 - Advantage + | F4: 11.49 | I4: 2026-03-31 | J4: 2026-03-31
B5: 2026-03-31 | C5: AD04 | D5: [ENGAJAMENTO] Distribuição de Conteúdo - 14.01.25 | E5: 00 - Advantage + | F5: 2.05 | I5: 2026-03-31 | J5: 2026-03-31
B6: 2026-03-31 | C6: AD03 | D6: [ENGAJAMENTO] Distribuição de Conteúdo - 14.01.25 | E6: 00 - Semelhante (BR, 3%) - [M] Lista de Alunos BB 2024/25 | F6: 0.02 | I6: 2026-03-31 | J6: 2026-03-31
B7: 2026-03-31 | C7: AD04 | D7: [ENGAJAMENTO] Distribuição de Conteúdo - 14.01.25 | E7: 00 - Carreira / Bancos | F7: 7.88 | I7: 2026-03-31 | J7: 2026-03-31
B8: 2026-03-31 | C8: AD03 | D8: [ENGAJAMENTO] Distribuição de Conteúdo - 14.01.25 | E8: 00 - Carreira / Bancos | F8: 65.5 | I8: 2026-03-31 | J8: 2026-03-31
B9: 2026-03-31 | C9: AD22 - O que você faria 2 | D9: [MA][pré-qualificação][quente][PBB-ABR-26][16.03.26] | E9: 01 - [Felipe Graton] Envolvimento 180D | F9: 36.77 | G9: 1 | H9: 36.77 | I9: 2026-03-31 | J9: 2026-03-31
B10: 2026-03-31 | C10: AD22 - O que você faria 2 | D10: [MA][pré-qualificação][frio][PBB-ABR-26][16.03.26] | E10: 02 - Semelhante (BR, 1%) - [M] - Lista de Alunos INSS 2023/24 | F10: 0.19 | I10: 2026-03-31 | J10: 2026-03-31
B11: 2026-03-31 | C11: AD22 - O que você faria 2 | D11: [MA][pré-qualificação][frio][PBB-ABR-26][16.03.26] | E11: 02 - Interesse Banco | F11: 27.68 | I11: 2026-03-31 | J11: 2026-03-31
B12: 2026-03-31 | C12: AD20 - Trinta horas | D12: [MA][pré-qualificação][quente][PBB-ABR-26][16.03.26] | E12: 00 - [Felipe Graton] Envolvimento 60D | F12: 0.11 | I12: 2026-03-31 | J12: 2026-03-31
B13: 2026-03-31 | C13: AD19 - O que voce faria | D13: [MA][pré-qualificação][quente][PBB-ABR-26][16.03.26] | E13: 00 - [Felipe Graton] Envolvimento 60D | F13: 2.14 | I13: 2026-03-31 | J13: 2026-03-31
B14: 2026-03-31 | C14: AD19 - O que voce faria | D14: [MA][pré-qualificação][quente][PBB-ABR-26][16.03.26] | E14: 01 - [Felipe Graton] Envolvimento 180D | F14: 1.08 | I14: 2026-03-31 | J14: 2026-03-31
B15: 2026-03-31 | C15: AD14 - Estratégia | D15: [MA][pré-qualificação][quente][PBB-ABR-26][16.03.26] | E15: 01 - [Felipe Graton] Envolvimento 180D | F15: 2.76 | I15: 2026-03-31 | J15: 2026-03-31
B16: 2026-03-31 | C16: AD20 - Trinta horas | D16: [MA][pré-qualificação][quente][PBB-ABR-26][16.03.26] | E16: 01 - [Felipe Graton] Envolvimento 180D | F16: 74.34 | I16: 2026-03-31 | J16: 2026-03-31
B17: 2026-03-31 | C17: AD21 - Banca | D17: [MA][pré-qualificação][quente][PBB-ABR-26][16.03.26] | E17: 01 - [Felipe Graton] Envolvimento 180D | F17: 0.01 | I17: 2026-03-31 | J17: 2026-03-31
B18: 2026-03-31 | C18: AD14 - Estratégia | D18: [MA][pré-qualificação][frio][PBB-ABR-26][16.03.26] | E18: 02 - Interesse Banco | F18: 36.2 | I18: 2026-03-31 | J18: 2026-03-31
B19: 2026-03-31 | C19: AD20 - Trinta horas | D19: [MA][pré-qualificação][frio][PBB-ABR-26][16.03.26] | E19: 02 - Interesse Banco | F19: 133.63 | G19: 1 | H19: 133.63 | I19: 2026-03-31 | J19: 2026-03-31
B20: 2026-03-31 | C20: AD20 - Trinta horas | D20: [MA][pré-qualificação][frio][PBB-ABR-26][16.03.26] | E20: 02 - Semelhante (BR, 1%) - [M] - Lista de Alunos INSS 2023/24 | F20: 0.44 | I20: 2026-03-31 | J20: 2026-03-31
B21: 2026-03-31 | C21: AD23 - BB 2026 s/trilha | D21: [MA][pré-qualificação][quente][PBB-ABR-26][16.03.26] | E21: 01 - [Felipe Graton] Envolvimento 180D | F21: 0 | I21: 2026-03-31 | J21: 2026-03-31
B22: 2026-03-31 | C22: AD24 - BB 2026 c/trilha | D22: [MA][pré-qualificação][frio][PBB-ABR-26][16.03.26] | E22: 02 - Interesse Banco | F22: 30.02 | I22: 2026-03-31 | J22: 2026-03-31
B23: 2026-03-31 | C23: AD23 - BB 2026 s/trilha | D23: [MA][pré-qualificação][frio][PBB-ABR-26][16.03.26] | E23: 02 - Interesse Banco | F23: 5.3 | I23: 2026-03-31 | J23: 2026-03-31
B24: 2026-03-31 | C24: AD058 - Casa do Thales - PBB-ABR-26 | D24: [MA][cadastro][captação][quente][principal][PBB-ABR-26][30.03.26] | E24: 00 - Cadastrados Antigos | F24: 0.51 | I24: 2026-03-31 | J24: 2026-03-31
B25: 2026-03-31 | C25: AD092 - Dois personagens casa do Thales - PBB-ABR-26 | D25: [MA][cadastro][captação][quente][principal][PBB-ABR-26][30.03.26] | E25: 00 - Cadastrados Antigos | F25: 1.05 | G25: 2 | H25: 0.525 | I25: 2026-03-31 | J25: 2026-03-31
B26: 2026-03-31 | C26: AD109 - Fachada Banco do Brasil com cx PBB-ABR-26 | D26: [MA][cadastro][captação][quente][principal][PBB-ABR-26][30.03.26] | E26: 00 - Cadastrados Antigos | F26: 0.05 | I26: 2026-03-31 | J26: 2026-03-31
B27: 2026-03-31 | C27: AD050 - Banco do Brasil 2 - cx nova - PBB-ABR-26 | D27: [MA][cadastro][captação][quente][principal][PBB-ABR-26][30.03.26] | E27: 00 - Cadastrados Antigos | F27: 19.73 | G27: 8 | H27: 2.46625 | I27: 2026-03-31 | J27: 2026-03-31
B28: 2026-03-31 | C28: AD113 - Dois personagens ape do Felipe - PBB-ABR-26 | D28: [MA][cadastro][captação][quente][principal][PBB-ABR-26][30.03.26] | E28: 00 - Cadastrados Antigos | F28: 23.12 | G28: 19 | H28: 1.2168421 | I28: 2026-03-31 | J28: 2026-03-31
B29: 2026-03-31 | C29: AD111 - Dois personagens - Brabo + legenda - PBB-ABR-26 | D29: [MA][cadastro][captação][quente][principal][PBB-ABR-26][30.03.26] | E29: 00 - Cadastrados Antigos | F29: 0.01 | I29: 2026-03-31 | J29: 2026-03-31
B30: 2026-03-31 | C30: AD097 - Carro + cx - PBB-ABR-26 | D30: [MA][cadastro][captação][quente][potencial][PBB-ABR-26][30.03.26] | E30: 00 - Cadastrados Antigos | F30: 0.5 | I30: 2026-03-31 | J30: 2026-03-31
B31: 2026-03-31 | C31: AD071 - Casa do Felipe + cx - PBB-ABR-26 | D31: [MA][cadastro][captação][quente][potencial][PBB-ABR-26][30.03.26] | E31: 00 - Cadastrados Antigos | F31: 0.06 | I31: 2026-03-31 | J31: 2026-03-31
B32: 2026-03-31 | C32: AD110 - Banco do Brasil 2 - cx nova - PBB-ABR-26 | D32: [MA][cadastro][captação][quente][potencial][PBB-ABR-26][30.03.26] | E32: 00 - Cadastrados Antigos | F32: 0.31 | I32: 2026-03-31 | J32: 2026-03-31
B33: 2026-03-31 | C33: AD108 - Imagem apostilas - PBB-ABR-26 | D33: [MA][cadastro][captação][quente][principal][PBB-ABR-26][30.03.26] | E33: 00 - Cadastrados Antigos | F33: 1.12 | I33: 2026-03-31 | J33: 2026-03-31
B34: 2026-03-31 | C34: AD109 - Fachada Banco do Brasil com cx PBB-ABR-26 | D34: [MA][cadastro][captação][quente][reels][PBB-ABR-26][30.03.26] | E34: 00 - Cadastrados Antigos | F34: 1.12 | G34: 1 | H34: 1.12 | I34: 2026-03-31 | J34: 2026-03-31
B35: 2026-03-31 | C35: AD097 - Carro + cx - PBB-ABR-26 | D35: [MA][cadastro][captação][quente][reels][PBB-ABR-26][30.03.26] | E35: 00 - Cadastrados Antigos | F35: 0.01 | I35: 2026-03-31 | J35: 2026-03-31
B36: 2026-03-31 | C36: AD100 - Tudo em 1 minuto + legenda - PBB-ABR-26 | D36: [MA][cadastro][captação][quente][reels][PBB-ABR-26][30.03.26] | E36: 00 - Cadastrados Antigos | F36: 3.68 | G36: 4 | H36: 0.92 | I36: 2026-03-31 | J36: 2026-03-31
B37: 2026-03-31 | C37: AD092 - Dois personagens casa do Thales - PBB-ABR-26 | D37: [MA][cadastro][captação][quente][principal][PBB-ABR-26][30.03.26] | E37: 04 - Viu 25% da Captação - PBB-FEV-26 | F37: 3.19 | G37: 1 | H37: 3.19 | I37: 2026-03-31 | J37: 2026-03-31
B38: 2026-03-31 | C38: AD113 - Dois personagens ape do Felipe - PBB-ABR-26 | D38: [MA][cadastro][captação][quente][principal][PBB-ABR-26][30.03.26] | E38: 04 - Viu 25% da Captação - PBB-FEV-26 | F38: 129.54 | G38: 116 | H38: 1.1167241 | I38: 2026-03-31 | J38: 2026-03-31
B39: 2026-03-31 | C39: AD108 - Imagem apostilas - PBB-ABR-26 | D39: [MA][cadastro][captação][quente][principal][PBB-ABR-26][30.03.26] | E39: 04 - Viu 25% da Captação - PBB-FEV-26 | F39: 5.37 | G39: 1 | H39: 5.37 | I39: 2026-03-31 | J39: 2026-03-31
B40: 2026-03-31 | C40: AD058 - Casa do Thales - PBB-ABR-26 | D40: [MA][cadastro][captação][quente][principal][PBB-ABR-26][30.03.26] | E40: 04 - Viu 25% da Captação - PBB-FEV-26 | F40: 3.12 | G40: 1 | H40: 3.12 | I40: 2026-03-31 | J40: 2026-03-31
B41: 2026-03-31 | C41: AD059 - Fachada Banco do Brasil + cx nova PBB-ABR-26 | D41: [MA][cadastro][captação][quente][principal][PBB-ABR-26][30.03.26] | E41: 04 - Viu 25% da Captação - PBB-FEV-26 | F41: 0.57 | I41: 2026-03-31 | J41: 2026-03-31
B42: 2026-03-31 | C42: AD050 - Banco do Brasil 2 - cx nova - PBB-ABR-26 | D42: [MA][cadastro][captação][quente][principal][PBB-ABR-26][30.03.26] | E42: 04 - Viu 25% da Captação - PBB-FEV-26 | F42: 83.04 | G42: 44 | H42: 1.8872727 | I42: 2026-03-31 | J42: 2026-03-31
B43: 2026-03-31 | C43: AD109 - Fachada Banco do Brasil com cx PBB-ABR-26 | D43: [MA][cadastro][captação][quente][principal][PBB-ABR-26][30.03.26] | E43: 04 - Viu 25% da Captação - PBB-FEV-26 | F43: 0.83 | I43: 2026-03-31 | J43: 2026-03-31
B44: 2026-03-31 | C44: AD111 - Dois personagens - Brabo + legenda - PBB-ABR-26 | D44: [MA][cadastro][captação][quente][principal][PBB-ABR-26][30.03.26] | E44: 04 - Viu 25% da Captação - PBB-FEV-26 | F44: 0.13 | I44: 2026-03-31 | J44: 2026-03-31
B45: 2026-03-31 | C45: AD113 - Dois personagens ape do Felipe - PBB-ABR-26 | D45: [MA][cadastro][captação][quente][principal][PBB-ABR-26][30.03.26] | E45: 01 - Caiu na pag. de Captura [PBB-ABR-26] | F45: 42.53 | G45: 37 | H45: 1.1494595 | I45: 2026-03-31 | J45: 2026-03-31
B46: 2026-03-31 | C46: AD050 - Banco do Brasil 2 - cx nova - PBB-ABR-26 | D46: [MA][cadastro][captação][quente][principal][PBB-ABR-26][30.03.26] | E46: 01 - Caiu na pag. de Captura [PBB-ABR-26] | F46: 4.29 | G46: 1 | H46: 4.29 | I46: 2026-03-31 | J46: 2026-03-31
B47: 2026-03-31 | C47: AD092 - Dois personagens casa do Thales - PBB-ABR-26 | D47: [MA][cadastro][captação][quente][principal][PBB-ABR-26][30.03.26] | E47: 01 - Caiu na pag. de Captura [PBB-ABR-26] | F47: 0 | I47: 2026-03-31 | J47: 2026-03-31
B48: 2026-03-31 | C48: AD109 - Fachada Banco do Brasil com cx PBB-ABR-26 | D48: [MA][cadastro][captação][quente][principal][PBB-ABR-26][30.03.26] | E48: 01 - Caiu na pag. de Captura [PBB-ABR-26] | F48: 0.83 | I48: 2026-03-31 | J48: 2026-03-31
B49: 2026-03-31 | C49: AD058 - Casa do Thales - PBB-ABR-26 | D49: [MA][cadastro][captação][quente][principal][PBB-ABR-26][30.03.26] | E49: 01 - Caiu na pag. de Captura [PBB-ABR-26] | F49: 1.09 | G49: 1 | H49: 1.09 | I49: 2026-03-31 | J49: 2026-03-31
B50: 2026-03-31 | C50: AD092 - Dois personagens casa do Thales - PBB-ABR-26 | D50: [MA][cadastro][captação][quente][principal][PBB-ABR-26][30.03.26] | E50: 05 - [Felipe Graton] Envolvimento 60D | F50: 0.52 | I50: 2026-03-31 | J50: 2026-03-31
B51: 2026-03-31 | C51: AD113 - Dois personagens ape do Felipe - PBB-ABR-26 | D51: [MA][cadastro][captação][quente][principal][PBB-ABR-26][30.03.26] | E51: 05 - [Felipe Graton] Envolvimento 60D | F51: 192.74 | G51: 163 | H51: 1.182454 | I51: 2026-03-31 | J51: 2026-03-31
B52: 2026-03-31 | C52: AD050 - Banco do Brasil 2 - cx nova - PBB-ABR-26 | D52: [MA][cadastro][captação][quente][principal][PBB-ABR-26][30.03.26] | E52: 05 - [Felipe Graton] Envolvimento 60D | F52: 0 | I52: 2026-03-31 | J52: 2026-03-31
B53: 2026-03-31 | C53: AD058 - Casa do Thales - PBB-ABR-26 | D53: [MA][cadastro][captação][quente][principal][PBB-ABR-26][30.03.26] | E53: 05 - [Felipe Graton] Envolvimento 60D | F53: 0.36 | I53: 2026-03-31 | J53: 2026-03-31
B54: 2026-03-31 | C54: AD109 - Fachada Banco do Brasil com cx PBB-ABR-26 | D54: [MA][cadastro][captação][quente][principal][PBB-ABR-26][30.03.26] | E54: 05 - [Felipe Graton] Envolvimento 60D | F54: 0.09 | I54: 2026-03-31 | J54: 2026-03-31
B55: 2026-03-31 | C55: AD111 - Dois personagens - Brabo + legenda - PBB-ABR-26 | D55: [MA][cadastro][captação][quente][principal][PBB-ABR-26][30.03.26] | E55: 05 - [Felipe Graton] Envolvimento 60D | F55: 0.01 | I55: 2026-03-31 | J55: 2026-03-31
B56: 2026-03-31 | C56: AD111 - Dois personagens - Brabo + legenda - PBB-ABR-26 | D56: [MA][cadastro][captação][quente][principal][PBB-ABR-26][30.03.26] | E56: 03 - Viu 50% da Captação - PBB-FEV-26 | F56: 0.11 | G56: 1 | H56: 0.11 | I56: 2026-03-31 | J56: 2026-03-31
B57: 2026-03-31 | C57: AD113 - Dois personagens ape do Felipe - PBB-ABR-26 | D57: [MA][cadastro][captação][quente][principal][PBB-ABR-26][30.03.26] | E57: 03 - Viu 50% da Captação - PBB-FEV-26 | F57: 546.68 | G57: 487 | H57: 1.1225462 | I57: 2026-03-31 | J57: 2026-03-31
B58: 2026-03-31 | C58: AD092 - Dois personagens casa do Thales - PBB-ABR-26 | D58: [MA][cadastro][captação][quente][principal][PBB-ABR-26][30.03.26] | E58: 03 - Viu 50% da Captação - PBB-FEV-26 | F58: 14.17 | G58: 2 | H58: 7.085 | I58: 2026-03-31 | J58: 2026-03-31
B59: 2026-03-31 | C59: AD108 - Imagem apostilas - PBB-ABR-26 | D59: [MA][cadastro][captação][quente][principal][PBB-ABR-26][30.03.26] | E59: 03 - Viu 50% da Captação - PBB-FEV-26 | F59: 9.73 | G59: 4 | H59: 2.4325 | I59: 2026-03-31 | J59: 2026-03-31
B60: 2026-03-31 | C60: AD109 - Fachada Banco do Brasil com cx PBB-ABR-26 | D60: [MA][cadastro][captação][quente][principal][PBB-ABR-26][30.03.26] | E60: 03 - Viu 50% da Captação - PBB-FEV-26 | F60: 3.29 | I60: 2026-03-31 | J60: 2026-03-31
B61: 2026-03-31 | C61: AD050 - Banco do Brasil 2 - cx nova - PBB-ABR-26 | D61: [MA][cadastro][captação][quente][principal][PBB-ABR-26][30.03.26] | E61: 03 - Viu 50% da Captação - PBB-FEV-26 | F61: 7.68 | G61: 2 | H61: 3.84 | I61: 2026-03-31 | J61: 2026-03-31
B62: 2026-03-31 | C62: AD058 - Casa do Thales - PBB-ABR-26 | D62: [MA][cadastro][captação][quente][principal][PBB-ABR-26][30.03.26] | E62: 03 - Viu 50% da Captação - PBB-FEV-26 | F62: 2.93 | G62: 1 | H62: 2.93 | I62: 2026-03-31 | J62: 2026-03-31
B63: 2026-03-31 | C63: AD059 - Fachada Banco do Brasil + cx nova PBB-ABR-26 | D63: [MA][cadastro][captação][quente][principal][PBB-ABR-26][30.03.26] | E63: 03 - Viu 50% da Captação - PBB-FEV-26 | F63: 0.59 | I63: 2026-03-31 | J63: 2026-03-31
B64: 2026-03-31 | C64: AD113 - Dois personagens ape do Felipe - PBB-ABR-26 | D64: [MA][cadastro][captação][quente][principal][PBB-ABR-26][30.03.26] | E64: 06 - [Felipe Graton] Envolvimento 180D | F64: 16.83 | G64: 19 | H64: 0.88578947 | I64: 2026-03-31 | J64: 2026-03-31
B65: 2026-03-31 | C65: AD092 - Dois personagens casa do Thales - PBB-ABR-26 | D65: [MA][cadastro][captação][quente][principal][PBB-ABR-26][30.03.26] | E65: 06 - [Felipe Graton] Envolvimento 180D | F65: 0.01 | I65: 2026-03-31 | J65: 2026-03-31
B66: 2026-03-31 | C66: AD058 - Casa do Thales - PBB-ABR-26 | D66: [MA][cadastro][captação][quente][principal][PBB-ABR-26][30.03.26] | E66: 06 - [Felipe Graton] Envolvimento 180D | F66: 0.28 | I66: 2026-03-31 | J66: 2026-03-31
B67: 2026-03-31 | C67: AD108 - Imagem apostilas - PBB-ABR-26 | D67: [MA][cadastro][captação][quente][principal][PBB-ABR-26][30.03.26] | E67: 06 - [Felipe Graton] Envolvimento 180D | F67: 0.37 | I67: 2026-03-31 | J67: 2026-03-31
B68: 2026-03-31 | C68: AD050 - Banco do Brasil 2 - cx nova - PBB-ABR-26 | D68: [MA][cadastro][captação][quente][principal][PBB-ABR-26][30.03.26] | E68: 06 - [Felipe Graton] Envolvimento 180D | F68: 6.95 | G68: 5 | H68: 1.39 | I68: 2026-03-31 | J68: 2026-03-31
B69: 2026-03-31 | C69: AD111 - Dois personagens - Brabo + legenda - PBB-ABR-26 | D69: [MA][cadastro][captação][quente][principal][PBB-ABR-26][30.03.26] | E69: 02 - Visitou o Site da Brabo - 180D | F69: 0.15 | G69: 1 | H69: 0.15 | I69: 2026-03-31 | J69: 2026-03-31
B70: 2026-03-31 | C70: AD092 - Dois personagens casa do Thales - PBB-ABR-26 | D70: [MA][cadastro][captação][quente][principal][PBB-ABR-26][30.03.26] | E70: 02 - Visitou o Site da Brabo - 180D | F70: 1.09 | G70: 1 | H70: 1.09 | I70: 2026-03-31 | J70: 2026-03-31
B71: 2026-03-31 | C71: AD058 - Casa do Thales - PBB-ABR-26 | D71: [MA][cadastro][captação][quente][principal][PBB-ABR-26][30.03.26] | E71: 02 - Visitou o Site da Brabo - 180D | F71: 0.89 | I71: 2026-03-31 | J71: 2026-03-31
B72: 2026-03-31 | C72: AD113 - Dois personagens ape do Felipe - PBB-ABR-26 | D72: [MA][cadastro][captação][quente][principal][PBB-ABR-26][30.03.26] | E72: 02 - Visitou o Site da Brabo - 180D | F72: 31.25 | G72: 31 | H72: 1.0080645 | I72: 2026-03-31 | J72: 2026-03-31
B73: 2026-03-31 | C73: AD059 - Fachada Banco do Brasil + cx nova PBB-ABR-26 | D73: [MA][cadastro][captação][quente][principal][PBB-ABR-26][30.03.26] | E73: 02 - Visitou o Site da Brabo - 180D | F73: 0.05 | I73: 2026-03-31 | J73: 2026-03-31
B74: 2026-03-31 | C74: AD108 - Imagem apostilas - PBB-ABR-26 | D74: [MA][cadastro][captação][quente][principal][PBB-ABR-26][30.03.26] | E74: 02 - Visitou o Site da Brabo - 180D | F74: 1.24 | G74: 1 | H74: 1.24 | I74: 2026-03-31 | J74: 2026-03-31
B75: 2026-03-31 | C75: AD050 - Banco do Brasil 2 - cx nova - PBB-ABR-26 | D75: [MA][cadastro][captação][quente][principal][PBB-ABR-26][30.03.26] | E75: 02 - Visitou o Site da Brabo - 180D | F75: 29.34 | G75: 14 | H75: 2.0957143 | I75: 2026-03-31 | J75: 2026-03-31
B76: 2026-03-31 | C76: AD109 - Fachada Banco do Brasil com cx PBB-ABR-26 | D76: [MA][cadastro][captação][quente][principal][PBB-ABR-26][30.03.26] | E76: 02 - Visitou o Site da Brabo - 180D | F76: 0.19 | I76: 2026-03-31 | J76: 2026-03-31
B77: 2026-03-31 | C77: AD110 - Banco do Brasil 2 - cx nova - PBB-ABR-26 | D77: [MA][cadastro][captação][quente][potencial][PBB-ABR-26][30.03.26] | E77: 02 - Visitou o Site da Brabo - 180D | F77: 15.87 | G77: 9 | H77: 1.7633333 | I77: 2026-03-31 | J77: 2026-03-31
B78: 2026-03-31 | C78: AD110 - Banco do Brasil 2 - cx nova - PBB-ABR-26 | D78: [MA][cadastro][captação][quente][potencial][PBB-ABR-26][30.03.26] | E78: 02 - Visitou o Site da Brabo - 180D | F78: 0.48 | I78: 2026-03-31 | J78: 2026-03-31
B79: 2026-03-31 | C79: AD112 - Dois personagens - Brabo+ legenda - PBB-ABR-26 | D79: [MA][cadastro][captação][quente][potencial][PBB-ABR-26][30.03.26] | E79: 02 - Visitou o Site da Brabo - 180D | F79: 2.91 | I79: 2026-03-31 | J79: 2026-03-31
B80: 2026-03-31 | C80: AD091 - Dois personagens violão - PBB-ABR-26 | D80: [MA][cadastro][captação][quente][potencial][PBB-ABR-26][30.03.26] | E80: 02 - Visitou o Site da Brabo - 180D | F80: 0.22 | G80: 1 | H80: 0.22 | I80: 2026-03-31 | J80: 2026-03-31
B81: 2026-03-31 | C81: AD093 - Dois personagens casa do Thales - PBB-ABR-26 | D81: [MA][cadastro][captação][quente][potencial][PBB-ABR-26][30.03.26] | E81: 02 - Visitou o Site da Brabo - 180D | F81: 0.13 | G81: 1 | H81: 0.13 | I81: 2026-03-31 | J81: 2026-03-31
B82: 2026-03-31 | C82: AD049 - Flip + Canetão PBB-ABR-26 | D82: [MA][cadastro][captação][quente][potencial][PBB-ABR-26][30.03.26] | E82: 02 - Visitou o Site da Brabo - 180D | F82: 2.84 | I82: 2026-03-31 | J82: 2026-03-31
B83: 2026-03-31 | C83: AD097 - Carro + cx - PBB-ABR-26 | D83: [MA][cadastro][captação][quente][potencial][PBB-ABR-26][30.03.26] | E83: 02 - Visitou o Site da Brabo - 180D | F83: 0.4 | I83: 2026-03-31 | J83: 2026-03-31
B84: 2026-03-31 | C84: AD049 - Flip + Canetão PBB-ABR-26 | D84: [MA][cadastro][captação][quente][potencial][PBB-ABR-26][30.03.26] | E84: 03 - Viu 50% da Captação - PBB-FEV-26 | F84: 0.23 | I84: 2026-03-31 | J84: 2026-03-31
B85: 2026-03-31 | C85: AD071 - Casa do Felipe + cx - PBB-ABR-26 | D85: [MA][cadastro][captação][quente][potencial][PBB-ABR-26][30.03.26] | E85: 02 - Visitou o Site da Brabo - 180D | F85: 17.87 | G85: 4 | H85: 4.4675 | I85: 2026-03-31 | J85: 2026-03-31
B86: 2026-03-31 | C86: AD091 - Dois personagens violão - PBB-ABR-26 | D86: [MA][cadastro][captação][quente][potencial][PBB-ABR-26][30.03.26] | E86: 03 - Viu 50% da Captação - PBB-FEV-26 | F86: 0 | I86: 2026-03-31 | J86: 2026-03-31
B87: 2026-03-31 | C87: AD110 - Banco do Brasil 2 - cx nova - PBB-ABR-26 | D87: [MA][cadastro][captação][quente][potencial][PBB-ABR-26][30.03.26] | E87: 03 - Viu 50% da Captação - PBB-FEV-26 | F87: 3.59 | I87: 2026-03-31 | J87: 2026-03-31
B88: 2026-03-31 | C88: AD071 - Casa do Felipe + cx - PBB-ABR-26 | D88: [MA][cadastro][captação][quente][potencial][PBB-ABR-26][30.03.26] | E88: 03 - Viu 50% da Captação - PBB-FEV-26 | F88: 0.01 | I88: 2026-03-31 | J88: 2026-03-31
B89: 2026-03-31 | C89: AD110 - Banco do Brasil 2 - cx nova - PBB-ABR-26 | D89: [MA][cadastro][captação][quente][potencial][PBB-ABR-26][30.03.26] | E89: 05 - [Felipe Graton] Envolvimento 60D | F89: 0.33 | G89: 1 | H89: 0.33 | I89: 2026-03-31 | J89: 2026-03-31
B90: 2026-03-31 | C90: AD110 - Banco do Brasil 2 - cx nova - PBB-ABR-26 | D90: [MA][cadastro][captação][quente][potencial][PBB-ABR-26][30.03.26] | E90: 05 - [Felipe Graton] Envolvimento 60D | F90: 0.14 | I90: 2026-03-31 | J90: 2026-03-31
B91: 2026-03-31 | C91: AD097 - Carro + cx - PBB-ABR-26 | D91: [MA][cadastro][captação][quente][potencial][PBB-ABR-26][30.03.26] | E91: 03 - Viu 50% da Captação - PBB-FEV-26 | F91: 0.02 | I91: 2026-03-31 | J91: 2026-03-31
B92: 2026-03-31 | C92: AD112 - Dois personagens - Brabo+ legenda - PBB-ABR-26 | D92: [MA][cadastro][captação][quente][potencial][PBB-ABR-26][30.03.26] | E92: 05 - [Felipe Graton] Envolvimento 60D | F92: 0.16 | I92: 2026-03-31 | J92: 2026-03-31
B93: 2026-03-31 | C93: AD071 - Casa do Felipe + cx - PBB-ABR-26 | D93: [MA][cadastro][captação][quente][potencial][PBB-ABR-26][30.03.26] | E93: 05 - [Felipe Graton] Envolvimento 60D | F93: 21.73 | G93: 10 | H93: 2.173 | I93: 2026-03-31 | J93: 2026-03-31
B94: 2026-03-31 | C94: AD071 - Casa do Felipe + cx - PBB-ABR-26 | D94: [MA][cadastro][captação][quente][potencial][PBB-ABR-26][30.03.26] | E94: 04 - Viu 25% da Captação - PBB-FEV-26 | F94: 57.2 | G94: 19 | H94: 3.0105263 | I94: 2026-03-31 | J94: 2026-03-31
B95: 2026-03-31 | C95: AD097 - Carro + cx - PBB-ABR-26 | D95: [MA][cadastro][captação][quente][potencial][PBB-ABR-26][30.03.26] | E95: 04 - Viu 25% da Captação - PBB-FEV-26 | F95: 0.02 | I95: 2026-03-31 | J95: 2026-03-31
B96: 2026-03-31 | C96: AD071 - Casa do Felipe + cx - PBB-ABR-26 | D96: [MA][cadastro][captação][quente][potencial][PBB-ABR-26][30.03.26] | E96: 01 - Caiu na pag. de Captura [PBB-ABR-26] | F96: 0.61 | I96: 2026-03-31 | J96: 2026-03-31
B97: 2026-03-31 | C97: AD049 - Flip + Canetão PBB-ABR-26 | D97: [MA][cadastro][captação][quente][potencial][PBB-ABR-26][30.03.26] | E97: 04 - Viu 25% da Captação - PBB-FEV-26 | F97: 1.02 | I97: 2026-03-31 | J97: 2026-03-31
B98: 2026-03-31 | C98: AD110 - Banco do Brasil 2 - cx nova - PBB-ABR-26 | D98: [MA][cadastro][captação][quente][potencial][PBB-ABR-26][30.03.26] | E98: 04 - Viu 25% da Captação - PBB-FEV-26 | F98: 9.33 | I98: 2026-03-31 | J98: 2026-03-31
B99: 2026-03-31 | C99: AD049 - Flip + Canetão PBB-ABR-26 | D99: [MA][cadastro][captação][quente][potencial][PBB-ABR-26][30.03.26] | E99: 01 - Caiu na pag. de Captura [PBB-ABR-26] | F99: 0.01 | I99: 2026-03-31 | J99: 2026-03-31
B100: 2026-03-31 | C100: AD112 - Dois personagens - Brabo+ legenda - PBB-ABR-26 | D100: [MA][cadastro][captação][quente][potencial][PBB-ABR-26][30.03.26] | E100: 01 - Caiu na pag. de Captura [PBB-ABR-26] | F100: 2.77 | G100: 1 | H100: 2.77 | I100: 2026-03-31 | J100: 2026-03-31
B101: 2026-03-31 | C101: AD110 - Banco do Brasil 2 - cx nova - PBB-ABR-26 | D101: [MA][cadastro][captação][quente][potencial][PBB-ABR-26][30.03.26] | E101: 01 - Caiu na pag. de Captura [PBB-ABR-26] | F101: 0.1 | I101: 2026-03-31 | J101: 2026-03-31
...
